Workbook

Sheet Historical Financials
B1: Model by Brian Githinji
B3: Company name | C3: Carbacid Investments PLc | D3: Ticker | E3: CARB | H3: Fomarting
B4: Share price | C4: 30.9 | D4: Share price date | E4: 46197 | H4: Black text | I4: Historical
B5: Financial Year - Last year ended | C5: 45869 | D5: Model date | E5: 46202 | H5: Blue text | I5: Forecast
B6: Shares Outstanding (Millions) | C6: 254852
B8: Financial year ended | D8: 43830 | E8: =EOMONTH(D8,12) -> 44196 | F8: =EOMONTH(E8,12) -> 44561 | G8: =EOMONTH(F8,12) -> 44926 | H8: =EOMONTH(G8,12) -> 45291 | I8: =EOMONTH(H8,12) -> 45657 | J8: =EOMONTH(I8,12) -> 46022 | K8: =EOMONTH(J8,12) -> 46387 | L8: =EOMONTH(K8,12) -> 46752 | ... O8: =EOMONTH(N8,12) -> 47848
B9: Financial year | D9: =TEXT(D8,"yyyy") -> 2019 | E9: =TEXT(E8,"yyyy") -> 2020 | F9: =TEXT(F8,"yyyy") -> 2021 | G9: =TEXT(G8,"yyyy") -> 2022 | H9: =TEXT(H8,"yyyy") -> 2023 | I9: =TEXT(I8,"yyyy") -> 2024 | J9: =TEXT(J8,"yyyy") -> 2025 | K9: =TEXT(K8,"yyyy") -> 2026 | ... O9: =TEXT(O8,"yyyy") -> 2030 | Q9: 2026 Forecast | R9: 2026 Actual | S9: Actual / Forecast | U9: FY 2025 | V9: HY 2025 | W9: HY 2026 | X9: Y-O-Y | Y9: YTD
B10: Income statement | C10: KShs’m
B11: Revenue | D11: 630500 | E11: 682878 | F11: 906588 | G11: 1414660 | H11: 1720943 | I11: 2066315 | J11: 2099850
B12: Cost of sales | D12: -230231 | E12: -258667 | F12: -352941 | G12: -574483 | H12: -708621 | I12: -846795 | J12: -747182
B13: Gross profit | D13: =D11+D12 -> 400269 | E13: =E11+E12 -> 424211 | F13: =F11+F12 -> 553647 | G13: =G11+G12 -> 840177 | H13: =H11+H12 -> 1012322 | I13: =I11+I12 -> 1219520 | J13: =J11+J12 -> 1352668
B14: Other income | D14: 203666 | E14: 230759 | F14: 240780 | G14: 320988 | H14: 394298 | I14: 354492 | J14: 322516
B15: Fair value gain/(loss) on equity investments | D15: -54938 | E15: -38850 | F15: 12533 | G15: 22674 | H15: 26561 | I15: -31224 | J15: 121234
B16: Fair value gain/(loss) on investment property | D16: 4600 | E16: -2349 | F16: -2591 | G16: 0 | H16: -2420 | I16: -4860 | J16: 0
B17: Impairment Loss | D17: -27 | E17: 0 | F17: 0 | G17: 0 | H17: 0 | I17: 0 | J17: 0
B18: Administrative expenses | D18: -176417 | E18: -186812 | F18: -264104 | G18: -266606 | H18: -333344 | I18: -371054 | J18: -440031
B19: Operating profit | D19: =D13+SUM(D14,D15,D16,D17,D18) -> 377153 | E19: =E13+SUM(E14,E15,E16,E17,E18) -> 426959 | F19: =F13+SUM(F14,F15,F16,F17,F18) -> 540265 | G19: =G13+SUM(G14,G15,G16,G17,G18) -> 917233 | H19: =H13+SUM(H14,H15,H16,H17,H18) -> 1097417 | I19: =I13+SUM(I14,I15,I16,I17,I18) -> 1166874 | J19: =J13+SUM(J14,J15,J16,J17,J18) -> 1356387
B20: Depreciation & amortisation | D20: 54706 | E20: 55115 | F20: 61261 | G20: 72638 | H20: 83875 | I20: 97641 | J20: 154347
B21: Finance income / interest income | D21: 161914 | E21: 186877 | F21: 196289 | G21: 243404 | H21: 255294 | I21: 273469 | J21: 263955
B22: Finance cost | D22: 0 | E22: 0 | F22: 0 | G22: -3404 | H22: -16435 | I22: -43116 | J22: -67823
B23: Profit before tax | D23: =D19+D22 -> 377153 | E23: =E19+E22 -> 426959 | F23: =F19+F22 -> 540265 | G23: =G19+G22 -> 913829 | H23: =H19+H22 -> 1080982 | I23: =I19+I22 -> 1123758 | J23: =J19+J22 -> 1288564
B24: Tax expense | D24: -112564 | E24: -102305 | F24: -125166 | G24: -206165 | H24: -264969 | I24: -280484 | J24: -285650
B25: Profit after tax | D25: =D23+D24 -> 264589 | E25: =E23+E24 -> 324654 | F25: =F23+F24 -> 415099 | G25: =G23+G24 -> 707664 | H25: =H23+H24 -> 816013 | I25: =I23+I24 -> 843274 | J25: =J23+J24 -> 1002914
B26: Basic EPS (KSh) | D26: =D25/D28 -> 1.0382065 | E26: =E25/E28 -> 1.2738923 | F26: =F25/F28 -> 1.6287845 | G26: =G25/G28 -> 2.7767646 | H26: =H25/H28 -> 3.2019093 | I26: =I25/I28 -> 3.3088773 | J26: =J25/J28 -> 3.9352801
B27: DPS declared (KSh) | D27: 0.7 | E27: 0.7 | F27: 1.6 | G27: 1.7 | H27: 1.7 | I27: 1.7 | J27: 2
B28: Shares outstanding ('000) | D28: 254852 | E28: 254852 | F28: 254852 | G28: 254852 | H28: 254852 | I28: 254852 | J28: 254852
B30: Balance Sheet
B31: Cash and cash equivalents | D31: =D82 -> 220036 | E31: =E82 -> 6095 | F31: =F82 -> 167636 | G31: =G82 -> 15251 | H31: =H82 -> 117454 | I31: =I82 -> 524882 | J31: =J82 -> 118576
B32: Short-term bank deposits | D32: 501290 | E32: 813641 | F32: 813115 | G32: 299325 | H32: 254658 | I32: 399676 | J32: 894600
B33: Trade and other receivables | D33: 174741 | E33: 195453 | F33: 213297 | G33: 367176 | H33: 547906 | I33: 581108 | J33: 640533
B34: Inventories | D34: 41236 | E34: 33863 | F34: 39898 | G34: 64954 | H34: 87190 | I34: 140612 | J34: 159475
B35: Current tax recoverable | D35: 3427 | E35: 7274 | F35: 8996 | G35: 9071 | H35: 13706 | I35: 105640 | J35: 0
B36: Other current assets | D36: 15625 | E36: 0 | F36: 0 | G36: 0 | H36: 0 | I36: 0 | J36: 0
B37: Total current assets | D37: =SUM(D31,D32,D33,D34,D35,D36) -> 956355 | E37: =SUM(E31,E32,E33,E34,E35,E36) -> 1056326 | F37: =SUM(F31,F32,F33,F34,F35,F36) -> 1242942 | G37: =SUM(G31,G32,G33,G34,G35,G36) -> 755777 | H37: =SUM(H31,H32,H33,H34,H35,H36) -> 1020914 | I37: =SUM(I31,I32,I33,I34,I35,I36) -> 1751918 | J37: =SUM(J31,J32,J33,J34,J35,J36) -> 1813184
B38: Property, plant and equipment | D38: 919401 | E38: 883728 | F38: 938139 | G38: 994565 | H38: 1360091 | I38: 1963988 | J38: 2221789
B39: Investment property | D39: 249800 | E39: 247451 | F39: 244414 | G39: 299152 | H39: 296732 | I39: 145894 | J39: 222900
B40: Intangible assets | D40: 391 | E40: 346 | F40: 877 | G40: 1528 | H40: 912 | I40: 1853 | J40: 3716
B41: Right-of-use assets / prepaid lease | D41: 52961 | E41: 52672 | F41: 52383 | G41: 52094 | H41: 51805 | I41: 51516 | J41: 51227
B42: Financial assets | D42: 1324593 | E42: 1387308 | F42: 1440469 | G42: 2358631 | H42: 2382670 | I42: 2363154 | J42: 2366872
B43: Total non-current assets | D43: =SUM(D38,D39,D40,D41,D42) -> 2547146 | E43: =SUM(E38,E39,E40,E41,E42) -> 2571505 | F43: =SUM(F38,F39,F40,F41,F42) -> 2676282 | G43: =SUM(G38,G39,G40,G41,G42) -> 3705970 | H43: =SUM(H38,H39,H40,H41,H42) -> 4092210 | I43: =SUM(I38,I39,I40,I41,I42) -> 4526405 | J43: =SUM(J38,J39,J40,J41,J42) -> 4866504
B44: TOTAL ASSETS | D44: =D43+D37 -> 3503501 | E44: =E43+E37 -> 3627831 | F44: =F43+F37 -> 3919224 | G44: =G43+G37 -> 4461747 | H44: =H43+H37 -> 5113124 | I44: =I43+I37 -> 6278323 | J44: =J43+J37 -> 6679688
B45: Trade and other payables | D45: 106421 | E45: 112983 | F45: 170906 | G45: 275897 | H45: 388142 | I45: 408883 | J45: 257648
B46: Dividend payable | D46: 33555 | E46: 46712 | F46: 45639 | G46: 59149 | H46: 72167 | I46: 84778 | J46: 100135
B47: Current tax payable | D47: 27981 | E47: 23599 | F47: 32813 | G47: 74636 | H47: 0 | I47: 0 | J47: 12003
B48: Current borrowings | D48: 0 | E48: 0 | F48: 0 | G48: 47838 | H48: 68841 | I48: 177080 | J48: 276719
B49: Total current liabilities | D49: =SUM(D45:D48) -> 167957 | E49: =SUM(E45:E48) -> 183294 | F49: =SUM(F45:F48) -> 249358 | G49: =SUM(G45:G48) -> 457520 | H49: =SUM(H45:H48) -> 529150 | I49: =SUM(I45:I48) -> 670741 | J49: =SUM(J45:J48) -> 646505
B50: Non-current borrowings | D50: 0 | E50: 0 | F50: 0 | G50: 40197 | H50: 205491 | I50: 655496 | J50: 500554
B51: Deferred income tax | D51: 208052 | E51: 192441 | F51: 181067 | G51: 175330 | H51: 216581 | I51: 380158 | J51: 391035
B52: Total non-current liabilities | D52: =D51+D50 -> 208052 | E52: =E51+E50 -> 192441 | F52: =F51+F50 -> 181067 | G52: =G51+G50 -> 215527 | H52: =H51+H50 -> 422072 | I52: =I51+I50 -> 1035654 | J52: =J51+J50 -> 891589
B53: TOTAL LIABILITES | D53: =D49+D52 -> 376009 | E53: =E49+E52 -> 375735 | F53: =F49+F52 -> 430425 | G53: =G49+G52 -> 673047 | H53: =H49+H52 -> 951222 | I53: =I49+I52 -> 1706395 | J53: =J49+J52 -> 1538094
B54: Share capital | D54: 254852 | E54: 254852 | F54: 254852 | G54: 254852 | H54: 254852 | I54: 254852 | J54: 254852
B55: Share premium | D55: 27 | E55: 27 | F55: 27 | G55: 27 | H55: 27 | I55: 27 | J55: 27
B56: Revaluation / other reserves | D56: 143324 | E56: 121670 | F56: 57938 | G56: 42477 | H56: 32914 | I56: 10798 | J56: 0
B57: Retained earnings | D57: 2729289 | E57: 2875547 | F57: 3175982 | G57: 3491344 | H57: 3874109 | I57: 4306251 | J57: 4886715
B58: TOTAL EQUITY | D58: =D54+D55+D56+D57 -> 3127492 | E58: =E54+E55+E56+E57 -> 3252096 | F58: =F54+F55+F56+F57 -> 3488799 | G58: =G54+G55+G56+G57 -> 3788700 | H58: =H54+H55+H56+H57 -> 4161902 | I58: =I54+I55+I56+I57 -> 4571928 | J58: =J54+J55+J56+J57 -> 5141594
B59: TOTAL LIABILITIES & EQUITES | D59: =D58+D53 -> 3503501 | E59: =E58+E53 -> 3627831 | F59: =F58+F53 -> 3919224 | G59: =G58+G53 -> 4461747 | H59: =H58+H53 -> 5113124 | I59: =I58+I53 -> 6278323 | J59: =J58+J53 -> 6679688
B61: Cash Flow Statement
B62: Profit after tax | D62: =D25 -> 264589 | E62: =E25 -> 324654 | F62: =F25 -> 415099 | G62: =G25 -> 707664 | H62: =H25 -> 816013 | I62: =I25 -> 843274 | J62: =J25 -> 1002914
B63: Depreciation & amortisation | D63: =D20 -> 54706 | E63: =E20 -> 55115 | F63: =F20 -> 61261 | G63: =G20 -> 72638 | H63: =H20 -> 83875 | I63: =I20 -> 97641 | J63: =J20 -> 154347
B64: Cash generated from operations | D64: 299281 | E64: 319674 | F64: 420512 | G64: 632782 | H64: 799208 | I64: 909527 | J64: 881169
B65: Interest received | D65: 161914 | E65: 186877 | F65: 196289 | G65: 243404 | H65: 255294 | I65: 273469 | J65: 263955
B66: Interest paid | D66: 0 | E66: 0 | F66: 0 | G66: 0 | H66: -16435 | I66: -43116 | J66: -67823
B67: Income tax paid | D67: -49791 | E67: -116865 | F67: -129048 | G67: -170154 | H67: -298904 | I67: -208839 | J67: -157128
B68: Net cash generated from operating activities | D68: =SUM(D64,D65,D66,D67) -> 411404 | E68: =SUM(E64,E65,E66,E67) -> 389686 | F68: =SUM(F64,F65,F66,F67) -> 487753 | G68: =SUM(G64,G65,G66,G67) -> 706032 | H68: =SUM(H64,H65,H66,H67) -> 739163 | I68: =SUM(I64,I65,I66,I67) -> 931041 | J68: =SUM(J64,J65,J66,J67) -> 920173
B69: Purchase of property, plant and equipment | D69: -37687 | E69: -49857 | F69: -125589 | G69: -179959 | H69: -471582 | I69: -705615 | J69: -426911
B70: Purchase of intangible assets | D70: 0 | E70: -194 | F70: -752 | G70: -1267 | H70: 0 | I70: -1212 | J70: -3224
B71: Purchase/proceeds of investment property | D71: 0 | E71: 0 | F71: 446 | G71: -2938 | H71: 0 | I71: =168473-5022 -> 163451 | J71: -77006
B72: Proceeds from disposal of property,plant and requirement | D72: 6746 | E72: 38 | F72: 8340 | H72: 9017 | I72: 8771 | J72: 15833
B73: Net financial investment movement | D73: -45315 | E73: -398291 | F73: =531-220102 -> -219571 | G73: -381698 | H73: 47189 | I73: -156728 | J73: -377408
B74: Dividends received | D74: 15305 | E74: 9916 | F74: 10914 | G74: 13663 | H74: 12349 | I74: 30113 | J74: 15431
B75: Net cash used in investing activities | D75: =SUM(D69,D70,D71,D73,D74,D72) -> -60951 | E75: =SUM(E69,E70,E71,E73,E74,E72) -> -438388 | F75: =SUM(F69,F70,F71,F73,F74,F72) -> -326212 | G75: =SUM(G69,G70,G71,G73,G74,G72) -> -552199 | H75: =SUM(H69,H70,H71,H73,H74,H72) -> -403027 | I75: =SUM(I69,I70,I71,I73,I74,I72) -> -661220 | J75: =SUM(J69,J70,J71,J73,J74,J72) -> -853285
B76: Net borrowings movement | D76: 0 | E76: 0 | F76: 0 | G76: 88035 | H76: 186297 | I76: 607177 | J76: -51800
B77: Dividends paid | D77: -173233 | E77: -165239 | F77: -185665 | G77: -394253 | H77: -420230 | I77: -420637 | J77: -417891
B78: Net cash from financing activities | D78: =D76+D77 -> -173233 | E78: =E76+E77 -> -165239 | F78: =F76+F77 -> -185665 | G78: =G76+G77 -> -306218 | H78: =H76+H77 -> -233933 | I78: =I76+I77 -> 186540 | J78: =J76+J77 -> -469691
B79: FX effect on borrowings | D79: 0 | E79: 0 | F79: 0 | G79: 0 | H79: 0 | I79: -48933 | J79: -3503
B80: Net change in cash | D80: =D68+D75+D78+D79 -> 177220 | E80: =E68+E75+E78 -> -213941 | F80: =F68+F75 -> 161541 | G80: =G68+G75+G78 -> -152385 | H80: =H68+H75+H78 -> 102203 | I80: =I68+I75+I78+I79 -> 407428 | J80: =J68+J75+J78+J79 -> -406306
B81: Opening cash | D81: 42816 | E81: =D82 -> 220036 | F81: =E82 -> 6095 | G81: =F82 -> 167636 | H81: =G82 -> 15251 | I81: =H82 -> 117454 | J81: =I82 -> 524882
B82: Closing cash | D82: =D80+D81 -> 220036 | E82: =E80+E81 -> 6095 | F82: =F80+F81 -> 167636 | G82: =G80+G81 -> 15251 | H82: =H80+H81 -> 117454 | I82: =I80+I81 -> 524882 | J82: =J80+J81 -> 118576

Sheet Carbacid Model
B1: Model by Brian Githinji
B2: Carbacid Investments PLC | Industrial + Investment Holding SOTP
B4: Company | C4: Carbacid Investments PLC
B5: NSE Ticker | C5: CARB
B6: Sector | C6: Manufacturing / Industrial Gases
B7: Current Price | C7: =Assumptions_Log!D4 -> 33.1
B8: Target Price | C8: =C200 -> 32.855509
B9: Upside / Downside | C9: =C8/C7-1 -> -0.0073864476
B10: Recommendation | C10: =C203 -> HOLD
B11: Market Capitalisation | C11: =C7*C12 -> 8435.6012
B12: Shares Outstanding | C12: =Assumptions_Log!D6 -> 254.852
B13: Model Date | C13: 46205
C15: Units | D15: 2019A | E15: 2020A | F15: 2021A | G15: 2022A | H15: 2023A | I15: 2024A | J15: 2025A | K15: 2026F | L15: 2027F | M15: 2028F | N15: 2029F | O15: 2030F
B17: KEY ASSUMPTIONS AND FORECAST DRIVERS
B19: CO2 volume growth | C19: % | D19: - | E19: - | F19: - | G19: - | H19: - | I19: - | J19: - | K19: =Assumptions_Log!G$24 -> 0.035 | L19: =Assumptions_Log!H$24 -> 0.04 | M19: =Assumptions_Log!I$24 -> 0.045 | N19: =Assumptions_Log!J$24 -> 0.045 | O19: =Assumptions_Log!K$24 -> 0.04
B20: CO2 price / mix / FX growth | C20: % | D20: - | E20: - | F20: - | G20: - | H20: - | I20: - | J20: - | K20: =Assumptions_Log!G$25 -> 0.015 | L20: =Assumptions_Log!H$25 -> 0.015 | M20: =Assumptions_Log!I$25 -> 0.015 | N20: =Assumptions_Log!J$25 -> 0.015 | O20: =Assumptions_Log!K$25 -> 0.015
B21: Transport/logistics revenue growth | C21: % | D21: - | E21: - | F21: - | G21: - | H21: - | I21: - | J21: - | K21: =Assumptions_Log!G$26 -> 0.07 | L21: =Assumptions_Log!H$26 -> 0.06 | M21: =Assumptions_Log!I$26 -> 0.055 | N21: =Assumptions_Log!J$26 -> 0.05 | O21: =Assumptions_Log!K$26 -> 0.045
B22: Other services growth | C22: % | D22: - | E22: - | F22: - | G22: - | H22: - | I22: - | J22: - | K22: =Assumptions_Log!G$27 -> 0 | L22: =Assumptions_Log!H$27 -> 0 | M22: =Assumptions_Log!I$27 -> 0 | N22: =Assumptions_Log!J$27 -> 0 | O22: =Assumptions_Log!K$27 -> 0
B23: Cost of sales / revenue | C23: % | D23: =IFERROR(-D51/D50,"") -> 0.36515623 | E23: =IFERROR(-E51/E50,"") -> 0.37878948 | F23: =IFERROR(-F51/F50,"") -> 0.38930694 | G23: =IFERROR(-G51/G50,"") -> 0.40609263 | H23: =IFERROR(-H51/H50,"") -> 0.4117632 | I23: =IFERROR(-I51/I50,"") -> 0.40980925 | J23: =IFERROR(-J51/J50,"") -> 0.35582637 | K23: =Assumptions_Log!G$28 -> 0.36 | L23: =Assumptions_Log!H$28 -> 0.37 | M23: =Assumptions_Log!I$28 -> 0.375 | N23: =Assumptions_Log!J$28 -> 0.38 | O23: =Assumptions_Log!K$28 -> 0.38
B24: Gross margin | C24: % | D24: =IFERROR(D53,"") -> 0.63484377 | E24: =IFERROR(E53,"") -> 0.62121052 | F24: =IFERROR(F53,"") -> 0.61069306 | G24: =IFERROR(G53,"") -> 0.59390737 | H24: =IFERROR(H53,"") -> 0.5882368 | I24: =IFERROR(I53,"") -> 0.59019075 | J24: =IFERROR(J53,"") -> 0.64417363 | K24: =1-Assumptions_Log!G$28 -> 0.64 | L24: =1-Assumptions_Log!H$28 -> 0.63 | M24: =1-Assumptions_Log!I$28 -> 0.625 | N24: =1-Assumptions_Log!J$28 -> 0.62 | O24: =1-Assumptions_Log!K$28 -> 0.62
B25: Administrative expenses / revenue | C25: % | D25: =IFERROR(-D54/D50,"") -> 0.27980492 | E25: =IFERROR(-E54/E50,"") -> 0.2735657 | F25: =IFERROR(-F54/F50,"") -> 0.29131645 | G25: =IFERROR(-G54/G50,"") -> 0.18845942 | H25: =IFERROR(-H54/H50,"") -> 0.19369845 | I25: =IFERROR(-I54/I50,"") -> 0.17957281 | J25: =IFERROR(-J54/J50,"") -> 0.20955354 | K25: =Assumptions_Log!G$29 -> 0.21 | L25: =Assumptions_Log!H$29 -> 0.208 | M25: =Assumptions_Log!I$29 -> 0.205 | N25: =Assumptions_Log!J$29 -> 0.203 | O25: =Assumptions_Log!K$29 -> 0.2
B26: D&A / average PPE | C26: % | D26: =IFERROR(D57/AVERAGE(D93,D93),"") -> 0.059501784 | E26: =IFERROR(E57/AVERAGE(D93,E93),"") -> 0.06113262 | F26: =IFERROR(F57/AVERAGE(E93,F93),"") -> 0.067250793 | G26: =IFERROR(G57/AVERAGE(F93,G93),"") -> 0.075167227 | H26: =IFERROR(H57/AVERAGE(G93,H93),"") -> 0.071241829 | I26: =IFERROR(I57/AVERAGE(H93,I93),"") -> 0.058747701 | J26: =IFERROR(J57/AVERAGE(I93,J93),"") -> 0.073748315 | K26: =Assumptions_Log!G$30 -> 0.07 | L26: =Assumptions_Log!H$30 -> 0.07 | M26: =Assumptions_Log!I$30 -> 0.07 | N26: =Assumptions_Log!J$30 -> 0.068 | O26: =Assumptions_Log!K$30 -> 0.068
B27: Capex / revenue | C27: % | D27: =IFERROR(D123/D50,"") -> 0.059773196 | E27: =IFERROR(E123/E50,"") -> 0.073294205 | F27: =IFERROR(F123/F50,"") -> 0.13935878 | G27: =IFERROR(G123/G50,"") -> 0.12810569 | H27: =IFERROR(H123/H50,"") -> 0.27402535 | I27: =IFERROR(I123/I50,"") -> 0.34207127 | J27: =IFERROR(J123/J50,"") -> 0.20484082 | K27: =Assumptions_Log!G$31 -> 0.18 | L27: =Assumptions_Log!H$31 -> 0.1 | M27: =Assumptions_Log!I$31 -> 0.09 | N27: =Assumptions_Log!J$31 -> 0.08 | O27: =Assumptions_Log!K$31 -> 0.08
B28: Receivable days | C28: days | D28: =IFERROR(D89/D50*365,"") -> 101.15855 | E28: =IFERROR(E89/E50*365,"") -> 104.47012 | F28: =IFERROR(F89/F50*365,"") -> 85.875177 | G28: =IFERROR(G89/G50*365,"") -> 94.736007 | H28: =IFERROR(H89/H50*365,"") -> 116.20704 | I28: =IFERROR(I89/I50*365,"") -> 102.64864 | J28: =IFERROR(J89/J50*365,"") -> 111.33869 | K28: =Assumptions_Log!G$32 -> 112 | L28: =Assumptions_Log!H$32 -> 110 | M28: =Assumptions_Log!I$32 -> 108 | N28: =Assumptions_Log!J$32 -> 106 | O28: =Assumptions_Log!K$32 -> 105
B29: Inventory days | C29: days | D29: =IFERROR(D90/(-D51)*365,"") -> 65.374081 | E29: =IFERROR(E90/(-E51)*365,"") -> 47.783424 | F29: =IFERROR(F90/(-F51)*365,"") -> 41.261202 | G29: =IFERROR(G90/(-G51)*365,"") -> 41.268776 | H29: =IFERROR(H90/(-H51)*365,"") -> 44.910255 | I29: =IFERROR(I90/(-I51)*365,"") -> 60.608979 | J29: =IFERROR(J90/(-J51)*365,"") -> 77.903878 | K29: =Assumptions_Log!G$33 -> 75 | L29: =Assumptions_Log!H$33 -> 75 | M29: =Assumptions_Log!I$33 -> 74 | N29: =Assumptions_Log!J$33 -> 74 | O29: =Assumptions_Log!K$33 -> 73
B30: Payable days | C30: days | D30: =IFERROR(D99/(-D51)*365,"") -> 168.71605 | E30: =IFERROR(E99/(-E51)*365,"") -> 159.42813 | F30: =IFERROR(F99/(-F51)*365,"") -> 176.74538 | G30: =IFERROR(G99/(-G51)*365,"") -> 175.29223 | H30: =IFERROR(H99/(-H51)*365,"") -> 199.9261 | I30: =IFERROR(I99/(-I51)*365,"") -> 176.24371 | J30: =IFERROR(J99/(-J51)*365,"") -> 125.8616 | K30: =Assumptions_Log!G$34 -> 126 | L30: =Assumptions_Log!H$34 -> 125 | M30: =Assumptions_Log!I$34 -> 124 | N30: =Assumptions_Log!J$34 -> 123 | O30: =Assumptions_Log!K$34 -> 122
B31: Financial assets growth | C31: % | D31: - | E31: - | F31: - | G31: - | H31: - | I31: - | J31: - | K31: =Assumptions_Log!G$37 -> 0.03 | L31: =Assumptions_Log!H$37 -> 0.03 | M31: =Assumptions_Log!I$37 -> 0.03 | N31: =Assumptions_Log!J$37 -> 0.03 | O31: =Assumptions_Log!K$37 -> 0.03
B32: Investment asset yield | C32: % | D32: - | E32: - | F32: - | G32: - | H32: - | I32: - | J32: - | K32: =Assumptions_Log!G$39 -> 0.08 | L32: =Assumptions_Log!H$39 -> 0.08 | M32: =Assumptions_Log!I$39 -> 0.08 | N32: =Assumptions_Log!J$39 -> 0.08 | O32: =Assumptions_Log!K$39 -> 0.08
B33: Dividend payout ratio | C33: % | D33: =IFERROR(D70/D69,"") -> 0.67423967 | E33: =IFERROR(E70/E69,"") -> 0.549497 | F33: =IFERROR(F70/F69,"") -> 0.98232759 | G33: =IFERROR(G70/G69,"") -> 0.61222332 | H33: =IFERROR(H70/H69,"") -> 0.53093321 | I33: =IFERROR(I70/I69,"") -> 0.51376943 | J33: =IFERROR(J70/J69,"") -> 0.50822304 | K33: =Assumptions_Log!G$40 -> 0.52 | L33: =Assumptions_Log!H$40 -> 0.52 | M33: =Assumptions_Log!I$40 -> 0.52 | N33: =Assumptions_Log!J$40 -> 0.52 | O33: =Assumptions_Log!K$40 -> 0.52
B36: REVENUE BUILD-UP – DRIVER-BASED
B38: CO2 sales revenue | C38: KSh mn | D38: =Segment_Financials!D6 -> 485.907 | E38: =Segment_Financials!E6 -> 536.286 | F38: =Segment_Financials!F6 -> 662.311 | G38: =Segment_Financials!G6 -> 954.771 | H38: =Segment_Financials!H6 -> 1082.416 | I38: =Segment_Financials!I6 -> 1340.801 | J38: =Segment_Financials!J6 -> 1314.242 | K38: =J38*(1+K19+K20) -> 1379.9541 | L38: =K38*(1+L19+L20) -> 1455.8516 | M38: =L38*(1+M19+M20) -> 1543.2027 | N38: =M38*(1+N19+N20) -> 1635.7948 | O38: =N38*(1+O19+O20) -> 1725.7635
B39: Transport / logistics revenue | C39: KSh mn | D39: =Segment_Financials!D7 -> 144.593 | E39: =Segment_Financials!E7 -> 146.592 | F39: =Segment_Financials!F7 -> 244.277 | G39: =Segment_Financials!G7 -> 459.889 | H39: =Segment_Financials!H7 -> 638.527 | I39: =Segment_Financials!I7 -> 725.514 | J39: =Segment_Financials!J7 -> 785.608 | K39: =J39*(1+K21) -> 840.60056 | L39: =K39*(1+L21) -> 891.03659 | M39: =L39*(1+M21) -> 940.04361 | N39: =M39*(1+N21) -> 987.04579 | O39: =N39*(1+O21) -> 1031.4628
B40: Other operating revenue / services | C40: KSh mn | D40: =Segment_Financials!D8 -> 0 | E40: =Segment_Financials!E8 -> 0 | F40: =Segment_Financials!F8 -> 0 | G40: =Segment_Financials!G8 -> 0 | H40: =Segment_Financials!H8 -> 0 | I40: =Segment_Financials!I8 -> 0 | J40: =Segment_Financials!J8 -> 0 | K40: =J40*(1+K22) -> 0 | L40: =K40*(1+L22) -> 0 | M40: =L40*(1+M22) -> 0 | N40: =M40*(1+N22) -> 0 | O40: =N40*(1+O22) -> 0
B41: Total operating revenue | C41: KSh mn | D41: =SUM(D38:D40) -> 630.5 | E41: =SUM(E38:E40) -> 682.878 | F41: =SUM(F38:F40) -> 906.588 | G41: =SUM(G38:G40) -> 1414.66 | H41: =SUM(H38:H40) -> 1720.943 | I41: =SUM(I38:I40) -> 2066.315 | J41: =SUM(J38:J40) -> 2099.85 | K41: =SUM(K38:K40) -> 2220.5547 | ... O41: =SUM(O38:O40) -> 2757.2264
B42: Revenue growth | C42: % | D42: - | E42: =IFERROR(E41/D41-1,"") -> 0.083073751 | F42: =IFERROR(F41/E41-1,"") -> 0.32759878 | G42: =IFERROR(G41/F41-1,"") -> 0.56042215 | H42: =IFERROR(H41/G41-1,"") -> 0.21650644 | I42: =IFERROR(I41/H41-1,"") -> 0.20068765 | J42: =IFERROR(J41/I41-1,"") -> 0.016229375 | K42: =IFERROR(K41/J41-1,"") -> 0.057482515 | L42: =IFERROR(L41/K41-1,"") -> 0.056892772 | ... O42: =IFERROR(O41/N41-1,"") -> 0.05123673
B43: CO2 sales growth | C43: % | D43: - | E43: =IFERROR(E38/D38-1,"") -> 0.10368033 | F43: =IFERROR(F38/E38-1,"") -> 0.23499588 | G43: =IFERROR(G38/F38-1,"") -> 0.44157503 | H43: =IFERROR(H38/G38-1,"") -> 0.13369174 | I43: =IFERROR(I38/H38-1,"") -> 0.23871136 | J43: =IFERROR(J38/I38-1,"") -> -0.019808309 | K43: =IFERROR(K38/J38-1,"") -> 0.05 | L43: =IFERROR(L38/K38-1,"") -> 0.055 | ... O43: =IFERROR(O38/N38-1,"") -> 0.055
B44: Transport/logistics growth | C44: % | D44: - | E44: =IFERROR(E39/D39-1,"") -> 0.013825012 | F44: =IFERROR(F39/E39-1,"") -> 0.66637334 | G44: =IFERROR(G39/F39-1,"") -> 0.88265371 | H44: =IFERROR(H39/G39-1,"") -> 0.38843721 | I44: =IFERROR(I39/H39-1,"") -> 0.13623073 | J44: =IFERROR(J39/I39-1,"") -> 0.082829553 | K44: =IFERROR(K39/J39-1,"") -> 0.07 | L44: =IFERROR(L39/K39-1,"") -> 0.06 | ... O44: =IFERROR(O39/N39-1,"") -> 0.045
B48: INCOME STATEMENT – OPERATING VS INVESTMENT SPLIT
B50: Revenue | C50: KSh mn | D50: ='Historical Financials'!D11/1000 -> 630.5 | E50: ='Historical Financials'!E11/1000 -> 682.878 | F50: ='Historical Financials'!F11/1000 -> 906.588 | G50: ='Historical Financials'!G11/1000 -> 1414.66 | H50: ='Historical Financials'!H11/1000 -> 1720.943 | I50: ='Historical Financials'!I11/1000 -> 2066.315 | J50: ='Historical Financials'!J11/1000 -> 2099.85 | K50: =K41 -> 2220.5547 | L50: =L41 -> 2346.8882 | M50: =M41 -> 2483.2463 | N50: =N41 -> 2622.8406 | O50: =O41 -> 2757.2264
B51: Cost of sales | C51: KSh mn | D51: ='Historical Financials'!D12/1000 -> -230.231 | E51: ='Historical Financials'!E12/1000 -> -258.667 | F51: ='Historical Financials'!F12/1000 -> -352.941 | G51: ='Historical Financials'!G12/1000 -> -574.483 | H51: ='Historical Financials'!H12/1000 -> -708.621 | I51: ='Historical Financials'!I12/1000 -> -846.795 | J51: ='Historical Financials'!J12/1000 -> -747.182 | K51: =-K50*K23 -> -799.39968 | L51: =-L50*L23 -> -868.34862 | M51: =-M50*M23 -> -931.21735 | N51: =-N50*N23 -> -996.67943 | O51: =-O50*O23 -> -1047.746
B52: Gross profit | C52: KSh mn | D52: ='Historical Financials'!D13/1000 -> 400.269 | E52: ='Historical Financials'!E13/1000 -> 424.211 | F52: ='Historical Financials'!F13/1000 -> 553.647 | G52: ='Historical Financials'!G13/1000 -> 840.177 | H52: ='Historical Financials'!H13/1000 -> 1012.322 | I52: ='Historical Financials'!I13/1000 -> 1219.52 | J52: ='Historical Financials'!J13/1000 -> 1352.668 | K52: =K50+K51 -> 1421.155 | L52: =L50+L51 -> 1478.5395 | M52: =M50+M51 -> 1552.0289 | N52: =N50+N51 -> 1626.1612 | O52: =O50+O51 -> 1709.4804
B53: Gross margin | C53: % | D53: =IFERROR(D52/D50,"") -> 0.63484377 | E53: =IFERROR(E52/E50,"") -> 0.62121052 | F53: =IFERROR(F52/F50,"") -> 0.61069306 | G53: =IFERROR(G52/G50,"") -> 0.59390737 | H53: =IFERROR(H52/H50,"") -> 0.5882368 | I53: =IFERROR(I52/I50,"") -> 0.59019075 | J53: =IFERROR(J52/J50,"") -> 0.64417363 | K53: =IFERROR(K52/K50,"") -> 0.64 | ... O53: =IFERROR(O52/O50,"") -> 0.62
B54: Administrative expenses | C54: KSh mn | D54: ='Historical Financials'!D18/1000 -> -176.417 | E54: ='Historical Financials'!E18/1000 -> -186.812 | F54: ='Historical Financials'!F18/1000 -> -264.104 | G54: ='Historical Financials'!G18/1000 -> -266.606 | H54: ='Historical Financials'!H18/1000 -> -333.344 | I54: ='Historical Financials'!I18/1000 -> -371.054 | J54: ='Historical Financials'!J18/1000 -> -440.031 | K54: =-K50*K25 -> -466.31648 | L54: =-L50*L25 -> -488.15274 | M54: =-M50*M25 -> -509.06549 | N54: =-N50*N25 -> -532.43665 | O54: =-O50*O25 -> -551.44528
B55: Normalised operating EBIT | C55: KSh mn | D55: =D52+D54 -> 223.852 | E55: =E52+E54 -> 237.399 | F55: =F52+F54 -> 289.543 | G55: =G52+G54 -> 573.571 | H55: =H52+H54 -> 678.978 | I55: =I52+I54 -> 848.466 | J55: =J52+J54 -> 912.637 | K55: =K52+K54 -> 954.8385 | ... O55: =O52+O54 -> 1158.0351
B56: Operating EBIT margin | C56: % | D56: =IFERROR(D55/D50,"") -> 0.35503886 | E56: =IFERROR(E55/E50,"") -> 0.34764482 | F56: =IFERROR(F55/F50,"") -> 0.31937661 | G56: =IFERROR(G55/G50,"") -> 0.40544795 | H56: =IFERROR(H55/H50,"") -> 0.39453834 | I56: =IFERROR(I55/I50,"") -> 0.41061794 | J56: =IFERROR(J55/J50,"") -> 0.43462009 | K56: =IFERROR(K55/K50,"") -> 0.43 | ... O56: =IFERROR(O55/O50,"") -> 0.42
B57: Depreciation & amortisation | C57: KSh mn | D57: ='Historical Financials'!D20/1000 -> 54.706 | E57: ='Historical Financials'!E20/1000 -> 55.115 | F57: ='Historical Financials'!F20/1000 -> 61.261 | G57: ='Historical Financials'!G20/1000 -> 72.638 | H57: ='Historical Financials'!H20/1000 -> 83.875 | I57: ='Historical Financials'!I20/1000 -> 97.641 | J57: ='Historical Financials'!J20/1000 -> 154.347 | K57: =J93*K26 -> 155.52523 | L57: =K93*L26 -> 172.61745 | M57: =L93*M26 -> 176.96245 | N57: =M93*N26 -> 175.0704 | O57: =N93*O26 -> 177.43386
B58: Operating EBITDA | C58: KSh mn | D58: =D55+D57 -> 278.558 | E58: =E55+E57 -> 292.514 | F58: =F55+F57 -> 350.804 | G58: =G55+G57 -> 646.209 | H58: =H55+H57 -> 762.853 | I58: =I55+I57 -> 946.107 | J58: =J55+J57 -> 1066.984 | K58: =K55+K57 -> 1110.3637 | ... O58: =O55+O57 -> 1335.4689
B59: EBITDA margin | C59: % | D59: =IFERROR(D58/D50,"") -> 0.44180492 | E59: =IFERROR(E58/E50,"") -> 0.4283547 | F59: =IFERROR(F58/F50,"") -> 0.38694975 | G59: =IFERROR(G58/G50,"") -> 0.45679457 | H59: =IFERROR(H58/H50,"") -> 0.44327616 | I59: =IFERROR(I58/I50,"") -> 0.45787162 | J59: =IFERROR(J58/J50,"") -> 0.50812391 | K59: =IFERROR(K58/K50,"") -> 0.50003891 | ... O59: =IFERROR(O58/O50,"") -> 0.4843523
B60: Investment / other income | C60: KSh mn | D60: =('Historical Financials'!D14+'Historical Financials'!D21)/1000 -> 365.58 | E60: =('Historical Financials'!E14+'Historical Financials'!E21)/1000 -> 417.636 | F60: =('Historical Financials'!F14+'Historical Financials'!F21)/1000 -> 437.069 | G60: =('Historical Financials'!G14+'Historical Financials'!G21)/1000 -> 564.392 | H60: =('Historical Financials'!H14+'Historical Financials'!H21)/1000 -> 649.592 | I60: =('Historical Financials'!I14+'Historical Financials'!I21)/1000 -> 627.961 | J60: =('Historical Financials'!J14+'Historical Financials'!J21)/1000 -> 586.471 | K60: =J96*K32 -> 189.34976 | L60: =K96*L32 -> 195.03025 | M60: =L96*M32 -> 200.88116 | N60: =M96*N32 -> 206.9076 | O60: =N96*O32 -> 213.11482
B61: Fair value gains/(losses) | C61: KSh mn | D61: =('Historical Financials'!D15+'Historical Financials'!D16)/1000 -> -50.338 | E61: =('Historical Financials'!E15+'Historical Financials'!E16)/1000 -> -41.199 | F61: =('Historical Financials'!F15+'Historical Financials'!F16)/1000 -> 9.942 | G61: =('Historical Financials'!G15+'Historical Financials'!G16)/1000 -> 22.674 | H61: =('Historical Financials'!H15+'Historical Financials'!H16)/1000 -> 24.141 | I61: =('Historical Financials'!I15+'Historical Financials'!I16)/1000 -> -36.084 | J61: =('Historical Financials'!J15+'Historical Financials'!J16)/1000 -> 121.234 | K61: =0 -> 0 | L61: =0 -> 0 | M61: =0 -> 0 | N61: =0 -> 0 | O61: =0 -> 0
B62: Reported operating profit | C62: KSh mn | D62: =D55+D60+D61 -> 539.094 | E62: =E55+E60+E61 -> 613.836 | F62: =F55+F60+F61 -> 736.554 | G62: =G55+G60+G61 -> 1160.637 | H62: =H55+H60+H61 -> 1352.711 | I62: =I55+I60+I61 -> 1440.343 | J62: =J55+J60+J61 -> 1620.342 | K62: =K55+K60+K61 -> 1144.1883 | ... O62: =O55+O60+O61 -> 1371.1499
B63: Finance costs | C63: KSh mn | D63: ='Historical Financials'!D22/1000 -> 0 | E63: ='Historical Financials'!E22/1000 -> 0 | F63: ='Historical Financials'!F22/1000 -> 0 | G63: ='Historical Financials'!G22/1000 -> -3.404 | H63: ='Historical Financials'!H22/1000 -> -16.435 | I63: ='Historical Financials'!I22/1000 -> -43.116 | J63: ='Historical Financials'!J22/1000 -> -67.823 | K63: =-AVERAGE(J102+J105,K102+K105)*Assumptions_Log!$D$11 -> -88.609122 | L63: =-AVERAGE(K102+K105,L102+L105)*Assumptions_Log!$D$11 -> -79.74821 | M63: =-AVERAGE(L102+L105,M102+M105)*Assumptions_Log!$D$11 -> -71.773389 | N63: =-AVERAGE(M102+M105,N102+N105)*Assumptions_Log!$D$11 -> -64.59605 | O63: =-AVERAGE(N102+N105,O102+O105)*Assumptions_Log!$D$11 -> -58.136445
B64: Profit before tax | C64: KSh mn | D64: =D62+D63 -> 539.094 | E64: =E62+E63 -> 613.836 | F64: =F62+F63 -> 736.554 | G64: =G62+G63 -> 1157.233 | H64: =H62+H63 -> 1336.276 | I64: =I62+I63 -> 1397.227 | J64: =J62+J63 -> 1552.519 | K64: =K62+K63 -> 1055.5791 | ... O64: =O62+O63 -> 1313.0135
B65: Tax expense | C65: KSh mn | D65: ='Historical Financials'!D24/1000 -> -112.564 | E65: ='Historical Financials'!E24/1000 -> -102.305 | F65: ='Historical Financials'!F24/1000 -> -125.166 | G65: ='Historical Financials'!G24/1000 -> -206.165 | H65: ='Historical Financials'!H24/1000 -> -264.969 | I65: ='Historical Financials'!I24/1000 -> -280.484 | J65: ='Historical Financials'!J24/1000 -> -285.65 | K65: =-K64*Assumptions_Log!$D$12 -> -242.7832 | L65: =-L64*Assumptions_Log!$D$12 -> -254.30384 | M65: =-M64*Assumptions_Log!$D$12 -> -269.57638 | N65: =-N64*Assumptions_Log!$D$12 -> -284.2883 | O65: =-O64*Assumptions_Log!$D$12 -> -301.9931
B66: Profit after tax | C66: KSh mn | D66: ='Historical Financials'!D25/1000 -> 264.589 | E66: ='Historical Financials'!E25/1000 -> 324.654 | F66: ='Historical Financials'!F25/1000 -> 415.099 | G66: ='Historical Financials'!G25/1000 -> 707.664 | H66: ='Historical Financials'!H25/1000 -> 816.013 | I66: ='Historical Financials'!I25/1000 -> 843.274 | J66: ='Historical Financials'!J25/1000 -> 1002.914 | K66: =K64+K65 -> 812.79594 | L66: =L64+L65 -> 851.36501 | M66: =M64+M65 -> 902.49483 | N66: =N64+N65 -> 951.74778 | O66: =O64+O65 -> 1011.0204
B67: Net margin | C67: % | D67: =IFERROR(D66/D50,"") -> 0.41964948 | E67: =IFERROR(E66/E50,"") -> 0.47542021 | F67: =IFERROR(F66/F50,"") -> 0.45786951 | G67: =IFERROR(G66/G50,"") -> 0.5002361 | H67: =IFERROR(H66/H50,"") -> 0.4741662 | I67: =IFERROR(I66/I50,"") -> 0.40810525 | J67: =IFERROR(J66/J50,"") -> 0.47761221 | K67: =IFERROR(K66/K50,"") -> 0.36603284 | ... O67: =IFERROR(O66/O50,"") -> 0.36668022
B68: Shares outstanding | C68: mn | D68: ='Historical Financials'!D28/1000 -> 254.852 | E68: ='Historical Financials'!E28/1000 -> 254.852 | F68: ='Historical Financials'!F28/1000 -> 254.852 | G68: ='Historical Financials'!G28/1000 -> 254.852 | H68: ='Historical Financials'!H28/1000 -> 254.852 | I68: ='Historical Financials'!I28/1000 -> 254.852 | J68: ='Historical Financials'!J28/1000 -> 254.852 | K68: =J68 -> 254.852 | L68: =K68 -> 254.852 | M68: =L68 -> 254.852 | N68: =M68 -> 254.852 | O68: =N68 -> 254.852
B69: EPS | C69: KSh | D69: =IFERROR(D66/D68,"") -> 1.0382065 | E69: =IFERROR(E66/E68,"") -> 1.2738923 | F69: =IFERROR(F66/F68,"") -> 1.6287845 | G69: =IFERROR(G66/G68,"") -> 2.7767646 | H69: =IFERROR(H66/H68,"") -> 3.2019093 | I69: =IFERROR(I66/I68,"") -> 3.3088773 | J69: =IFERROR(J66/J68,"") -> 3.9352801 | K69: =IFERROR(K66/K68,"") -> 3.1892861 | ... O69: =IFERROR(O66/O68,"") -> 3.9670882
B70: DPS | C70: KSh | D70: ='Historical Financials'!D27 -> 0.7 | E70: ='Historical Financials'!E27 -> 0.7 | F70: ='Historical Financials'!F27 -> 1.6 | G70: ='Historical Financials'!G27 -> 1.7 | H70: ='Historical Financials'!H27 -> 1.7 | I70: ='Historical Financials'!I27 -> 1.7 | J70: ='Historical Financials'!J27 -> 2 | K70: =K69*K33 -> 1.6584288 | L70: =L69*L33 -> 1.7371251 | M70: =M69*M33 -> 1.8414504 | N70: =N69*N33 -> 1.9419461 | O70: =O69*O33 -> 2.0628859
B71: Dividends declared | C71: KSh mn | D71: =D70*D68 -> 178.3964 | E71: =E70*E68 -> 178.3964 | F71: =F70*F68 -> 407.7632 | G71: =G70*G68 -> 433.2484 | H71: =H70*H68 -> 433.2484 | I71: =I70*I68 -> 433.2484 | J71: =J70*J68 -> 509.704 | K71: =K70*K68 -> 422.65389 | ... O71: =O70*O68 -> 525.73059
B84: BALANCE SHEET – OPERATING ASSETS AND NON-OPERATING ASSET BASE
B87: Cash and cash equivalents | C87: KSh mn | D87: ='Historical Financials'!D31/1000 -> 220.036 | E87: ='Historical Financials'!E31/1000 -> 6.095 | F87: ='Historical Financials'!F31/1000 -> 167.636 | G87: ='Historical Financials'!G31/1000 -> 15.251 | H87: ='Historical Financials'!H31/1000 -> 117.454 | I87: ='Historical Financials'!I31/1000 -> 524.882 | J87: ='Historical Financials'!J31/1000 -> 118.576 | K87: =J87+K149 -> 159.49741 | L87: =K87+L149 -> 417.47591 | M87: =L87+M149 -> 722.30936 | N87: =M87+N149 -> 1067.0321 | O87: =N87+O149 -> 1433.5632
B88: Short-term bank deposits / excess liquidity | C88: KSh mn | D88: ='Historical Financials'!D32/1000 -> 501.29 | E88: ='Historical Financials'!E32/1000 -> 813.641 | F88: ='Historical Financials'!F32/1000 -> 813.115 | G88: ='Historical Financials'!G32/1000 -> 299.325 | H88: ='Historical Financials'!H32/1000 -> 254.658 | I88: ='Historical Financials'!I32/1000 -> 399.676 | J88: ='Historical Financials'!J32/1000 -> 894.6 | K88: =K115-(K87+K89+K90+K91+K97) -> 891.73689 | L88: =L115-(L87+L89+L90+L91+L97) -> 833.63526 | M88: =M115-(M87+M89+M90+M91+M97) -> 775.32134 | N88: =N115-(N87+N89+N90+N91+N97) -> 714.77754 | O88: =O115-(O87+O89+O90+O91+O97) -> 653.05845
B89: Trade and other receivables | C89: KSh mn | D89: ='Historical Financials'!D33/1000 -> 174.741 | E89: ='Historical Financials'!E33/1000 -> 195.453 | F89: ='Historical Financials'!F33/1000 -> 213.297 | G89: ='Historical Financials'!G33/1000 -> 367.176 | H89: ='Historical Financials'!H33/1000 -> 547.906 | I89: ='Historical Financials'!I33/1000 -> 581.108 | J89: ='Historical Financials'!J33/1000 -> 640.533 | K89: =K50*K128/365 -> 681.37568 | L89: =L50*L128/365 -> 707.28137 | M89: =M50*M128/365 -> 734.76876 | N89: =N50*N128/365 -> 761.70166 | O89: =O50*O128/365 -> 793.17472
B90: Inventories | C90: KSh mn | D90: ='Historical Financials'!D34/1000 -> 41.236 | E90: ='Historical Financials'!E34/1000 -> 33.863 | F90: ='Historical Financials'!F34/1000 -> 39.898 | G90: ='Historical Financials'!G34/1000 -> 64.954 | H90: ='Historical Financials'!H34/1000 -> 87.19 | I90: ='Historical Financials'!I34/1000 -> 140.612 | J90: ='Historical Financials'!J34/1000 -> 159.475 | K90: =-K51*K129/365 -> 164.26021 | L90: =-L51*L129/365 -> 178.4278 | M90: =-M51*M129/365 -> 188.79475 | N90: =-N51*N129/365 -> 202.06652 | O90: =-O51*O129/365 -> 209.54921
B91: Tax recoverable / other current assets | C91: KSh mn | D91: =('Historical Financials'!D35+'Historical Financials'!D36)/1000 -> 19.052 | E91: =('Historical Financials'!E35+'Historical Financials'!E36)/1000 -> 7.274 | F91: =('Historical Financials'!F35+'Historical Financials'!F36)/1000 -> 8.996 | G91: =('Historical Financials'!G35+'Historical Financials'!G36)/1000 -> 9.071 | H91: =('Historical Financials'!H35+'Historical Financials'!H36)/1000 -> 13.706 | I91: =('Historical Financials'!I35+'Historical Financials'!I36)/1000 -> 105.64 | J91: =('Historical Financials'!J35+'Historical Financials'!J36)/1000 -> 0 | K91: =K50*Assumptions_Log!G$35 -> 11.102773 | L91: =L50*Assumptions_Log!H$35 -> 11.734441 | M91: =M50*Assumptions_Log!I$35 -> 12.416231 | N91: =N50*Assumptions_Log!J$35 -> 13.114203 | O91: =O50*Assumptions_Log!K$35 -> 13.786132
B92: Total current assets | C92: KSh mn | D92: =SUM(D87:D91) -> 956.355 | E92: =SUM(E87:E91) -> 1056.326 | F92: =SUM(F87:F91) -> 1242.942 | G92: =SUM(G87:G91) -> 755.777 | H92: =SUM(H87:H91) -> 1020.914 | I92: =SUM(I87:I91) -> 1751.918 | J92: =SUM(J87:J91) -> 1813.184 | K92: =SUM(K87:K91) -> 1907.973 | ... O92: =SUM(O87:O91) -> 3103.1317
B93: Property, plant and equipment | C93: KSh mn | D93: ='Historical Financials'!D38/1000 -> 919.401 | E93: ='Historical Financials'!E38/1000 -> 883.728 | F93: ='Historical Financials'!F38/1000 -> 938.139 | G93: ='Historical Financials'!G38/1000 -> 994.565 | H93: ='Historical Financials'!H38/1000 -> 1360.091 | I93: ='Historical Financials'!I38/1000 -> 1963.988 | J93: ='Historical Financials'!J38/1000 -> 2221.789 | K93: =J93+K123-K57 -> 2465.9636 | L93: =K93+L123-L57 -> 2528.035 | M93: =L93+M123-M57 -> 2574.5647 | N93: =M93+N123-N57 -> 2609.3215 | O93: =N93+O123-O57 -> 2652.4658
B94: Investment property | C94: KSh mn | D94: ='Historical Financials'!D39/1000 -> 249.8 | E94: ='Historical Financials'!E39/1000 -> 247.451 | F94: ='Historical Financials'!F39/1000 -> 244.414 | G94: ='Historical Financials'!G39/1000 -> 299.152 | H94: ='Historical Financials'!H39/1000 -> 296.732 | I94: ='Historical Financials'!I39/1000 -> 145.894 | J94: ='Historical Financials'!J39/1000 -> 222.9 | K94: =J94*(1+Assumptions_Log!G$38) -> 225.129 | L94: =K94*(1+Assumptions_Log!H$38) -> 227.38029 | M94: =L94*(1+Assumptions_Log!I$38) -> 229.65409 | N94: =M94*(1+Assumptions_Log!J$38) -> 231.95063 | O94: =N94*(1+Assumptions_Log!K$38) -> 234.27014
B95: Intangibles and right-of-use assets | C95: KSh mn | D95: =('Historical Financials'!D40+'Historical Financials'!D41)/1000 -> 53.352 | E95: =('Historical Financials'!E40+'Historical Financials'!E41)/1000 -> 53.018 | F95: =('Historical Financials'!F40+'Historical Financials'!F41)/1000 -> 53.26 | G95: =('Historical Financials'!G40+'Historical Financials'!G41)/1000 -> 53.622 | H95: =('Historical Financials'!H40+'Historical Financials'!H41)/1000 -> 52.717 | I95: =('Historical Financials'!I40+'Historical Financials'!I41)/1000 -> 53.369 | J95: =('Historical Financials'!J40+'Historical Financials'!J41)/1000 -> 54.943 | K95: =MAX(0,J95-0.3) -> 54.643 | L95: =MAX(0,K95-0.3) -> 54.343 | M95: =MAX(0,L95-0.3) -> 54.043 | N95: =MAX(0,M95-0.3) -> 53.743 | O95: =MAX(0,N95-0.3) -> 53.443
B96: Financial assets | C96: KSh mn | D96: ='Historical Financials'!D42/1000 -> 1324.593 | E96: ='Historical Financials'!E42/1000 -> 1387.308 | F96: ='Historical Financials'!F42/1000 -> 1440.469 | G96: ='Historical Financials'!G42/1000 -> 2358.631 | H96: ='Historical Financials'!H42/1000 -> 2382.67 | I96: ='Historical Financials'!I42/1000 -> 2363.154 | J96: ='Historical Financials'!J42/1000 -> 2366.872 | K96: =J96*(1+K31) -> 2437.8782 | L96: =K96*(1+L31) -> 2511.0145 | M96: =L96*(1+M31) -> 2586.3449 | N96: =M96*(1+N31) -> 2663.9353 | O96: =N96*(1+O31) -> 2743.8533
B97: Total non-current assets | C97: KSh mn | D97: =SUM(D93:D96) -> 2547.146 | E97: =SUM(E93:E96) -> 2571.505 | F97: =SUM(F93:F96) -> 2676.282 | G97: =SUM(G93:G96) -> 3705.97 | H97: =SUM(H93:H96) -> 4092.21 | I97: =SUM(I93:I96) -> 4526.405 | J97: =SUM(J93:J96) -> 4866.504 | K97: =SUM(K93:K96) -> 5183.6138 | ... O97: =SUM(O93:O96) -> 5684.0323
B98: Total assets | C98: KSh mn | D98: =D92+D97 -> 3503.501 | E98: =E92+E97 -> 3627.831 | F98: =F92+F97 -> 3919.224 | G98: =G92+G97 -> 4461.747 | H98: =H92+H97 -> 5113.124 | I98: =I92+I97 -> 6278.323 | J98: =J92+J97 -> 6679.688 | K98: =K92+K97 -> 7091.5867 | ... O98: =O92+O97 -> 8787.164
B99: Trade and other payables | C99: KSh mn | D99: ='Historical Financials'!D45/1000 -> 106.421 | E99: ='Historical Financials'!E45/1000 -> 112.983 | F99: ='Historical Financials'!F45/1000 -> 170.906 | G99: ='Historical Financials'!G45/1000 -> 275.897 | H99: ='Historical Financials'!H45/1000 -> 388.142 | I99: ='Historical Financials'!I45/1000 -> 408.883 | J99: ='Historical Financials'!J45/1000 -> 257.648 | K99: =-K51*K130/365 -> 275.95715 | L99: =-L51*L130/365 -> 297.37967 | M99: =-M51*M130/365 -> 316.35877 | N99: =-N51*N130/365 -> 335.86732 | O99: =-O51*O130/365 -> 350.20552
B100: Dividends payable | C100: KSh mn | D100: ='Historical Financials'!D46/1000 -> 33.555 | E100: ='Historical Financials'!E46/1000 -> 46.712 | F100: ='Historical Financials'!F46/1000 -> 45.639 | G100: ='Historical Financials'!G46/1000 -> 59.149 | H100: ='Historical Financials'!H46/1000 -> 72.167 | I100: ='Historical Financials'!I46/1000 -> 84.778 | J100: ='Historical Financials'!J46/1000 -> 100.135 | K100: =K71*0.2 -> 84.530778 | L100: =L71*0.2 -> 88.541962 | M100: =M71*0.2 -> 93.859462 | N100: =N71*0.2 -> 98.981769 | O100: =O71*0.2 -> 105.14612
B101: Tax payable | C101: KSh mn | D101: ='Historical Financials'!D47/1000 -> 27.981 | E101: ='Historical Financials'!E47/1000 -> 23.599 | F101: ='Historical Financials'!F47/1000 -> 32.813 | G101: ='Historical Financials'!G47/1000 -> 74.636 | H101: ='Historical Financials'!H47/1000 -> 0 | I101: ='Historical Financials'!I47/1000 -> 0 | J101: ='Historical Financials'!J47/1000 -> 12.003 | K101: =-K65*0.05 -> 12.13916 | L101: =-L65*0.05 -> 12.715192 | M101: =-M65*0.05 -> 13.478819 | N101: =-N65*0.05 -> 14.214415 | O101: =-O65*0.05 -> 15.099655
B102: Current borrowings | C102: KSh mn | D102: ='Historical Financials'!D48/1000 -> 0 | E102: ='Historical Financials'!E48/1000 -> 0 | F102: ='Historical Financials'!F48/1000 -> 0 | G102: ='Historical Financials'!G48/1000 -> 47.838 | H102: ='Historical Financials'!H48/1000 -> 68.841 | I102: ='Historical Financials'!I48/1000 -> 177.08 | J102: ='Historical Financials'!J48/1000 -> 276.719 | K102: =J102*0.9 -> 249.0471 | L102: =K102*0.9 -> 224.14239 | M102: =L102*0.9 -> 201.72815 | N102: =M102*0.9 -> 181.55534 | O102: =N102*0.9 -> 163.3998
B103: Other current liabilities | C103: KSh mn | D103: ='Historical Financials'!D49/1000-SUM(D99:D102) -> 0 | E103: ='Historical Financials'!E49/1000-SUM(E99:E102) -> 0 | F103: ='Historical Financials'!F49/1000-SUM(F99:F102) -> 0 | G103: ='Historical Financials'!G49/1000-SUM(G99:G102) -> 0 | H103: ='Historical Financials'!H49/1000-SUM(H99:H102) -> 0 | I103: ='Historical Financials'!I49/1000-SUM(I99:I102) -> 0 | J103: ='Historical Financials'!J49/1000-SUM(J99:J102) -> 0 | K103: =K50*Assumptions_Log!G$36 -> 88.822186 | L103: =L50*Assumptions_Log!H$36 -> 93.875527 | M103: =M50*Assumptions_Log!I$36 -> 99.329851 | N103: =N50*Assumptions_Log!J$36 -> 104.91362 | O103: =O50*Assumptions_Log!K$36 -> 110.28906
B104: Total current liabilities | C104: KSh mn | D104: =SUM(D99:D103) -> 167.957 | E104: =SUM(E99:E103) -> 183.294 | F104: =SUM(F99:F103) -> 249.358 | G104: =SUM(G99:G103) -> 457.52 | H104: =SUM(H99:H103) -> 529.15 | I104: =SUM(I99:I103) -> 670.741 | J104: =SUM(J99:J103) -> 646.505 | K104: =SUM(K99:K103) -> 710.49637 | ... O104: =SUM(O99:O103) -> 744.14015
B105: Non-current borrowings | C105: KSh mn | D105: ='Historical Financials'!D50/1000 -> 0 | E105: ='Historical Financials'!E50/1000 -> 0 | F105: ='Historical Financials'!F50/1000 -> 0 | G105: ='Historical Financials'!G50/1000 -> 40.197 | H105: ='Historical Financials'!H50/1000 -> 205.491 | I105: ='Historical Financials'!I50/1000 -> 655.496 | J105: ='Historical Financials'!J50/1000 -> 500.554 | K105: =J105*0.9 -> 450.4986 | L105: =K105*0.9 -> 405.44874 | M105: =L105*0.9 -> 364.90387 | N105: =M105*0.9 -> 328.41348 | O105: =N105*0.9 -> 295.57213
B106: Deferred tax liability | C106: KSh mn | D106: ='Historical Financials'!D51/1000 -> 208.052 | E106: ='Historical Financials'!E51/1000 -> 192.441 | F106: ='Historical Financials'!F51/1000 -> 181.067 | G106: ='Historical Financials'!G51/1000 -> 175.33 | H106: ='Historical Financials'!H51/1000 -> 216.581 | I106: ='Historical Financials'!I51/1000 -> 380.158 | J106: ='Historical Financials'!J51/1000 -> 391.035 | K106: =J106*1.02 -> 398.8557 | L106: =K106*1.02 -> 406.83281 | M106: =L106*1.02 -> 414.96947 | N106: =M106*1.02 -> 423.26886 | O106: =N106*1.02 -> 431.73424
B107: Other non-current liabilities | C107: KSh mn | D107: ='Historical Financials'!D52/1000-SUM(D105:D106) -> 0 | E107: ='Historical Financials'!E52/1000-SUM(E105:E106) -> 0 | F107: ='Historical Financials'!F52/1000-SUM(F105:F106) -> 0 | G107: ='Historical Financials'!G52/1000-SUM(G105:G106) -> 0 | H107: ='Historical Financials'!H52/1000-SUM(H105:H106) -> 0 | I107: ='Historical Financials'!I52/1000-SUM(I105:I106) -> 0 | J107: ='Historical Financials'!J52/1000-SUM(J105:J106) -> 0 | K107: =0 -> 0 | L107: =0 -> 0 | M107: =0 -> 0 | N107: =0 -> 0 | O107: =0 -> 0
B108: Total non-current liabilities | C108: KSh mn | D108: =SUM(D105:D107) -> 208.052 | E108: =SUM(E105:E107) -> 192.441 | F108: =SUM(F105:F107) -> 181.067 | G108: =SUM(G105:G107) -> 215.527 | H108: =SUM(H105:H107) -> 422.072 | I108: =SUM(I105:I107) -> 1035.654 | J108: =SUM(J105:J107) -> 891.589 | K108: =SUM(K105:K107) -> 849.3543 | ... O108: =SUM(O105:O107) -> 727.30637
B109: Total liabilities | C109: KSh mn | D109: =D104+D108 -> 376.009 | E109: =E104+E108 -> 375.735 | F109: =F104+F108 -> 430.425 | G109: =G104+G108 -> 673.047 | H109: =H104+H108 -> 951.222 | I109: =I104+I108 -> 1706.395 | J109: =J104+J108 -> 1538.094 | K109: =K104+K108 -> 1559.8507 | ... O109: =O104+O108 -> 1471.4465
B110: Share capital | C110: KSh mn | D110: ='Historical Financials'!D54/1000 -> 254.852 | E110: ='Historical Financials'!E54/1000 -> 254.852 | F110: ='Historical Financials'!F54/1000 -> 254.852 | G110: ='Historical Financials'!G54/1000 -> 254.852 | H110: ='Historical Financials'!H54/1000 -> 254.852 | I110: ='Historical Financials'!I54/1000 -> 254.852 | J110: ='Historical Financials'!J54/1000 -> 254.852 | K110: =J110 -> 254.852 | L110: =K110 -> 254.852 | M110: =L110 -> 254.852 | N110: =M110 -> 254.852 | O110: =N110 -> 254.852
B111: Share premium | C111: KSh mn | D111: ='Historical Financials'!D55/1000 -> 0.027 | E111: ='Historical Financials'!E55/1000 -> 0.027 | F111: ='Historical Financials'!F55/1000 -> 0.027 | G111: ='Historical Financials'!G55/1000 -> 0.027 | H111: ='Historical Financials'!H55/1000 -> 0.027 | I111: ='Historical Financials'!I55/1000 -> 0.027 | J111: ='Historical Financials'!J55/1000 -> 0.027 | K111: =J111 -> 0.027 | L111: =K111 -> 0.027 | M111: =L111 -> 0.027 | N111: =M111 -> 0.027 | O111: =N111 -> 0.027
B112: Other reserves | C112: KSh mn | D112: ='Historical Financials'!D56/1000 -> 143.324 | E112: ='Historical Financials'!E56/1000 -> 121.67 | F112: ='Historical Financials'!F56/1000 -> 57.938 | G112: ='Historical Financials'!G56/1000 -> 42.477 | H112: ='Historical Financials'!H56/1000 -> 32.914 | I112: ='Historical Financials'!I56/1000 -> 10.798 | J112: ='Historical Financials'!J56/1000 -> 0 | K112: =J112 -> 0 | L112: =K112 -> 0 | M112: =L112 -> 0 | N112: =M112 -> 0 | O112: =N112 -> 0
B113: Retained earnings | C113: KSh mn | D113: ='Historical Financials'!D57/1000 -> 2729.289 | E113: ='Historical Financials'!E57/1000 -> 2875.547 | F113: ='Historical Financials'!F57/1000 -> 3175.982 | G113: ='Historical Financials'!G57/1000 -> 3491.344 | H113: ='Historical Financials'!H57/1000 -> 3874.109 | I113: ='Historical Financials'!I57/1000 -> 4306.251 | J113: ='Historical Financials'!J57/1000 -> 4886.715 | K113: =J113+K66-K71 -> 5276.8571 | L113: =K113+L66-L71 -> 5685.5123 | M113: =L113+M66-M71 -> 6118.7098 | N113: =M113+N66-N71 -> 6575.5487 | O113: =N113+O66-O71 -> 7060.8385
B114: Total equity | C114: KSh mn | D114: =SUM(D110:D113) -> 3127.492 | E114: =SUM(E110:E113) -> 3252.096 | F114: =SUM(F110:F113) -> 3488.799 | G114: =SUM(G110:G113) -> 3788.7 | H114: =SUM(H110:H113) -> 4161.902 | I114: =SUM(I110:I113) -> 4571.928 | J114: =SUM(J110:J113) -> 5141.594 | K114: =SUM(K110:K113) -> 5531.7361 | ... O114: =SUM(O110:O113) -> 7315.7175
B115: Total liabilities and equity | C115: KSh mn | D115: =D109+D114 -> 3503.501 | E115: =E109+E114 -> 3627.831 | F115: =F109+F114 -> 3919.224 | G115: =G109+G114 -> 4461.747 | H115: =H109+H114 -> 5113.124 | I115: =I109+I114 -> 6278.323 | J115: =J109+J114 -> 6679.688 | K115: =K109+K114 -> 7091.5867 | ... O115: =O109+O114 -> 8787.164
B116: Balance check | C116: KSh mn | D116: =D98-D115 -> 0 | E116: =E98-E115 -> 0 | F116: =F98-F115 -> 0 | G116: =G98-G115 -> 0 | H116: =H98-H115 -> 0 | I116: =I98-I115 -> 0 | J116: =J98-J115 -> 0 | K116: =K98-K115 -> 0 | ... O116: =O98-O115 -> 0
B120: WORKING CAPITAL, CAPEX AND INVESTED CAPITAL
B123: Capital expenditure | C123: KSh mn | D123: =-('Historical Financials'!D69+'Historical Financials'!D70)/1000 -> 37.687 | E123: =-('Historical Financials'!E69+'Historical Financials'!E70)/1000 -> 50.051 | F123: =-('Historical Financials'!F69+'Historical Financials'!F70)/1000 -> 126.341 | G123: =-('Historical Financials'!G69+'Historical Financials'!G70)/1000 -> 181.226 | H123: =-('Historical Financials'!H69+'Historical Financials'!H70)/1000 -> 471.582 | I123: =-('Historical Financials'!I69+'Historical Financials'!I70)/1000 -> 706.827 | J123: =-('Historical Financials'!J69+'Historical Financials'!J70)/1000 -> 430.135 | K123: =K50*K27 -> 399.69984 | L123: =L50*L27 -> 234.68882 | M123: =M50*M27 -> 223.49216 | N123: =N50*N27 -> 209.82725 | O123: =O50*O27 -> 220.57811
B124: Capex / revenue | C124: % | D124: =IFERROR(D123/D50,"") -> 0.059773196 | E124: =IFERROR(E123/E50,"") -> 0.073294205 | F124: =IFERROR(F123/F50,"") -> 0.13935878 | G124: =IFERROR(G123/G50,"") -> 0.12810569 | H124: =IFERROR(H123/H50,"") -> 0.27402535 | I124: =IFERROR(I123/I50,"") -> 0.34207127 | J124: =IFERROR(J123/J50,"") -> 0.20484082 | K124: =IFERROR(K123/K50,"") -> 0.18 | ... O124: =IFERROR(O123/O50,"") -> 0.08
B125: Depreciation & amortisation | C125: KSh mn | D125: =D57 -> 54.706 | E125: =E57 -> 55.115 | F125: =F57 -> 61.261 | G125: =G57 -> 72.638 | H125: =H57 -> 83.875 | I125: =I57 -> 97.641 | J125: =J57 -> 154.347 | K125: =K57 -> 155.52523 | ... O125: =O57 -> 177.43386
B126: Operating net working capital | C126: KSh mn | D126: =D89+D90-D99 -> 109.556 | E126: =E89+E90-E99 -> 116.333 | F126: =F89+F90-F99 -> 82.289 | G126: =G89+G90-G99 -> 156.233 | H126: =H89+H90-H99 -> 246.954 | I126: =I89+I90-I99 -> 312.837 | J126: =J89+J90-J99 -> 542.36 | K126: =K89+K90-K99 -> 569.67874 | ... O126: =O89+O90-O99 -> 652.5184
B127: Change in net working capital | C127: KSh mn | D127: 0 | E127: =E126-D126 -> 6.777 | F127: =F126-E126 -> -34.044 | G127: =G126-F126 -> 73.944 | H127: =H126-G126 -> 90.721 | I127: =I126-H126 -> 65.883 | J127: =J126-I126 -> 229.523 | K127: =K126-J126 -> 27.318735 | L127: =L126-K126 -> 18.650765 | ... O127: =O126-N126 -> 24.617542
B128: Receivable days | C128: days | D128: =D28 -> 101.15855 | E128: =E28 -> 104.47012 | F128: =F28 -> 85.875177 | G128: =G28 -> 94.736007 | H128: =H28 -> 116.20704 | I128: =I28 -> 102.64864 | J128: =J28 -> 111.33869 | K128: =K28 -> 112 | ... O128: =O28 -> 105
B129: Inventory days | C129: days | D129: =D29 -> 65.374081 | E129: =E29 -> 47.783424 | F129: =F29 -> 41.261202 | G129: =G29 -> 41.268776 | H129: =H29 -> 44.910255 | I129: =I29 -> 60.608979 | J129: =J29 -> 77.903878 | K129: =K29 -> 75 | ... O129: =O29 -> 73
B130: Payable days | C130: days | D130: =D30 -> 168.71605 | E130: =E30 -> 159.42813 | F130: =F30 -> 176.74538 | G130: =G30 -> 175.29223 | H130: =H30 -> 199.9261 | I130: =I30 -> 176.24371 | J130: =J30 -> 125.8616 | K130: =K30 -> 126 | ... O130: =O30 -> 122
...

Sheet Assumptions_Log
B1: Carbacid Investments PLC – Assumptions Log
B3: Category | C3: Assumption | D3: Base / Value | E3: Unit | F3: Source / Rationale | G3: FY2026F | H3: FY2027F | I3: FY2028F | J3: FY2029F | K3: FY2030F
B4: Market | C4: Current share price | D4: 33.1 | E4: KSh/share | F4: MarketScreener / NSE end-of-day quote, 01-Jul-2026
B5: Market | C5: Share price date | D5: 2026-07-01 | E5: date | F5: Source: MarketScreener quote snapshot
B6: Market | C6: Shares outstanding | D6: 254.852 | E6: mn shares | F6: Linked to Historical Financials / 2025 AR share count
B7: Valuation | C7: Risk-free rate | D7: 0.1232 | E7: % | F7: Kenya 10Y government bond yield, 01-Jul-2026
B8: Valuation | C8: Beta | D8: 0.65 | E8: x | F8: Small-cap industrial / specialty gas adjusted beta
B9: Valuation | C9: Equity risk premium | D9: 0.045 | E9: % | F9: Kenya / frontier market equity risk premium assumption
B10: Valuation | C10: Cost of equity | D10: =D7+D8*D9 -> 0.15245 | E10: % | F10: CAPM
B11: Valuation | C11: Pre-tax cost of debt | D11: 0.12 | E11: % | F11: Normalised local/FX borrowing cost; anchored to FY2024 loan note disclosure
B12: Valuation | C12: Tax rate | D12: 0.23 | E12: % | F12: Normalised cash tax rate based on recent effective tax rates
B13: Valuation | C13: Target debt weight | D13: 0.09 | E13: % | F13: Conservative long-run capital structure assumption
B14: Valuation | C14: WACC | D14: =D10*(1-D13)+D11*(1-D12)*D13 -> 0.1470455 | E14: % | F14: WACC = CoE x E/V + after-tax CoD x D/V
B15: Valuation | C15: Terminal growth | D15: 0.05 | E15: % | F15: Long-run nominal growth assumption
B16: Valuation | C16: DCF / SOTP weight | D16: 0.65 | E16: % | F16: Primary method; separates operating value and non-operating investments
B17: Valuation | C17: EV/EBITDA weight | D17: 0.2 | E17: % | F17: Operating multiple cross-check
B18: Valuation | C18: P/E weight | D18: 0.15 | E18: % | F18: Earnings cross-check; lower weight due investment-income volatility
B19: Valuation | C19: EV/EBITDA exit multiple | D19: 6 | E19: x | F19: Specialty industrial / gas multiple cross-check
B20: Valuation | C20: P/E exit multiple | D20: 10 | E20: x | F20: Market earnings multiple sanity check
B21: Revenue Mix | C21: CO2 sales mix of revenue | D21: =Segment_Financials!J12 -> 0.62587423 | E21: % | F21: Calculated from Note 6: CO2 sales / total operating revenue
B22: Revenue Mix | C22: Transport revenue mix | D22: =Segment_Financials!J13 -> 0.37412577 | E22: % | F22: Calculated from Note 6: transport revenue / total operating revenue
B23: Revenue Mix | C23: Other services revenue mix | D23: =1-D21-D22 -> 0 | E23: % | F23: Calculated residual from Note 6; no other operating revenue separately disclosed
B24: Forecast Driver | C24: CO2 volume growth | E24: % | F24: Calculated from Note 6 CO2 sales history, moderated for FY2025 FX drag and new market expansion | G24: 0.035 | H24: 0.04 | I24: 0.045 | J24: 0.045 | K24: 0.04
B25: Forecast Driver | C25: CO2 price / mix / FX | E25: % | F25: Calculated from Note 5 export mix / Note 6 sales mix; allows pricing, mix and FX effect | G25: 0.015 | H25: 0.015 | I25: 0.015 | J25: 0.015 | K25: 0.015
B26: Forecast Driver | C26: Transport/logistics growth | E26: % | F26: Calculated from Note 6 transport revenue history; tapered to reflect mature export logistics base | G26: 0.07 | H26: 0.06 | I26: 0.055 | J26: 0.05 | K26: 0.045
B27: Forecast Driver | C27: Other services growth | E27: % | F27: No separate other operating revenue disclosed in Note 6; set to 0% | G27: 0 | H27: 0 | I27: 0 | J27: 0 | K27: 0
B28: Forecast Driver | C28: Cost of sales / revenue | E28: % | F28: Royalty, power, fuel, labour and maintenance assumptions | G28: 0.36 | H28: 0.37 | I28: 0.375 | J28: 0.38 | K28: 0.38
B29: Forecast Driver | C29: Administrative expenses / revenue | E29: % | F29: Fixed-cost absorption offset by regional expansion | G29: 0.21 | H29: 0.208 | I29: 0.205 | J29: 0.203 | K29: 0.2
B30: Forecast Driver | C30: D&A / average PPE | E30: % | F30: PPE depreciation intensity | G30: 0.07 | H30: 0.07 | I30: 0.07 | J30: 0.068 | K30: 0.068
B31: Forecast Driver | C31: Capex / revenue | E31: % | F31: Solar expansion / fleet / plant maintenance | G31: 0.18 | H31: 0.1 | I31: 0.09 | J31: 0.08 | K31: 0.08
B32: Forecast Driver | C32: Receivable days | E32: days | F32: Historical collection cycle adjusted for export mix | G32: 112 | H32: 110 | I32: 108 | J32: 106 | K32: 105
B33: Forecast Driver | C33: Inventory days | E33: days | F33: Gas inventory and spares inventory cycle | G33: 75 | H33: 75 | I33: 74 | J33: 74 | K33: 73
B34: Forecast Driver | C34: Payable days | E34: days | F34: Supplier/royalty payment cycle | G34: 126 | H34: 125 | I34: 124 | J34: 123 | K34: 122
B35: Forecast Driver | C35: Other current assets / revenue | E35: % | F35: Small operating accruals | G35: 0.005 | H35: 0.005 | I35: 0.005 | J35: 0.005 | K35: 0.005
... B40: Capital Return | C40: Dividend payout ratio | E40: % | F40: Consistent dividend payout, with reinvestment for growth | G40: 0.52 | H40: 0.52 | I40: 0.52 | J40: 0.52 | K40: 0.52

Sheet Segment_Financials
B1: Carbacid Investments PLC – Segment Financials from Annual Reports
C3: Units | D3: 2019A | E3: 2020A | F3: 2021A | G3: 2022A | H3: 2023A | I3: 2024A | J3: 2025A | K3: 2026F | L3: 2027F | M3: 2028F | N3: 2029F | O3: 2030F
B5: REVENUE SPLIT – NOTE 6 ACTUALS / FORECAST
B6: CO2 sales revenue | C6: KSh mn | D6: 485.907 | E6: 536.286 | F6: 662.311 | G6: 954.771 | H6: 1082.416 | I6: 1340.801 | J6: 1314.242 | K6: ='Carbacid Model'!K38 -> 1379.9541 | L6: ='Carbacid Model'!L38 -> 1455.8516 | M6: ='Carbacid Model'!M38 -> 1543.2027 | N6: ='Carbacid Model'!N38 -> 1635.7948 | O6: ='Carbacid Model'!O38 -> 1725.7635
B7: Transport revenue | C7: KSh mn | D7: 144.593 | E7: 146.592 | F7: 244.277 | G7: 459.889 | H7: 638.527 | I7: 725.514 | J7: 785.608 | K7: ='Carbacid Model'!K39 -> 840.60056 | L7: ='Carbacid Model'!L39 -> 891.03659 | M7: ='Carbacid Model'!M39 -> 940.04361 | N7: ='Carbacid Model'!N39 -> 987.04579 | O7: ='Carbacid Model'!O39 -> 1031.4628
B8: Other operating revenue / services | C8: KSh mn | D8: 0 | E8: 0 | F8: 0 | G8: 0 | H8: 0 | I8: 0 | J8: 0 | K8: ='Carbacid Model'!K40 -> 0 | L8: ='Carbacid Model'!L40 -> 0 | M8: ='Carbacid Model'!M40 -> 0 | N8: ='Carbacid Model'!N40 -> 0 | O8: ='Carbacid Model'!O40 -> 0
B9: Total operating revenue | C9: KSh mn | D9: =SUM(D6:D8) -> 630.5 | E9: =SUM(E6:E8) -> 682.878 | F9: =SUM(F6:F8) -> 906.588 | G9: =SUM(G6:G8) -> 1414.66 | H9: =SUM(H6:H8) -> 1720.943 | I9: =SUM(I6:I8) -> 2066.315 | J9: =SUM(J6:J8) -> 2099.85 | K9: ='Carbacid Model'!K41 -> 2220.5547 | L9: ='Carbacid Model'!L41 -> 2346.8882 | M9: ='Carbacid Model'!M41 -> 2483.2463 | N9: ='Carbacid Model'!N41 -> 2622.8406 | O9: ='Carbacid Model'!O41 -> 2757.2264
B10: CO2 sales growth | C10: % | D10: ="" | E10: =IFERROR(E6/D6-1,"") -> 0.10368033 | F10: =IFERROR(F6/E6-1,"") -> 0.23499588 | G10: =IFERROR(G6/F6-1,"") -> 0.44157503 | H10: =IFERROR(H6/G6-1,"") -> 0.13369174 | I10: =IFERROR(I6/H6-1,"") -> 0.23871136 | J10: =IFERROR(J6/I6-1,"") -> -0.019808309 | K10: =IFERROR(K6/J6-1,"") -> 0.05 | L10: =IFERROR(L6/K6-1,"") -> 0.055 | ... O10: =IFERROR(O6/N6-1,"") -> 0.055
B11: Transport revenue growth | C11: % | D11: ="" | E11: =IFERROR(E7/D7-1,"") -> 0.013825012 | F11: =IFERROR(F7/E7-1,"") -> 0.66637334 | G11: =IFERROR(G7/F7-1,"") -> 0.88265371 | H11: =IFERROR(H7/G7-1,"") -> 0.38843721 | I11: =IFERROR(I7/H7-1,"") -> 0.13623073 | J11: =IFERROR(J7/I7-1,"") -> 0.082829553 | K11: =IFERROR(K7/J7-1,"") -> 0.07 | L11: =IFERROR(L7/K7-1,"") -> 0.06 | ... O11: =IFERROR(O7/N7-1,"") -> 0.045
B12: CO2 revenue mix | C12: % | D12: =IFERROR(D6/D9,"") -> 0.77066931 | E12: =IFERROR(E6/E9,"") -> 0.78533208 | F12: =IFERROR(F6/F9,"") -> 0.73055346 | G12: =IFERROR(G6/G9,"") -> 0.67491199 | H12: =IFERROR(H6/H9,"") -> 0.62896679 | I12: =IFERROR(I6/I9,"") -> 0.64888509 | J12: =IFERROR(J6/J9,"") -> 0.62587423 | K12: =IFERROR(K6/K9,"") -> 0.62144568 | ... O12: =IFERROR(O6/O9,"") -> 0.62590564
B13: Transport revenue mix | C13: % | D13: =IFERROR(D7/D9,"") -> 0.22933069 | E13: =IFERROR(E7/E9,"") -> 0.21466792 | F13: =IFERROR(F7/F9,"") -> 0.26944654 | G13: =IFERROR(G7/G9,"") -> 0.32508801 | H13: =IFERROR(H7/H9,"") -> 0.37103321 | I13: =IFERROR(I7/I9,"") -> 0.35111491 | J13: =IFERROR(J7/J9,"") -> 0.37412577 | K13: =IFERROR(K7/K9,"") -> 0.37855432 | ... O13: =IFERROR(O7/O9,"") -> 0.37409436
B14: Domestic sales | C14: KSh mn | D14: 371.283 | E14: 464.405 | F14: 437.065 | G14: 422.215 | H14: 394.023 | I14: 501.652 | J14: 613.397 | K14: =K9-K15 -> 688.37194 | L14: =L9-L15 -> 751.00421 | M14: =M9-M15 -> 819.47127 | N14: =N9-N15 -> 891.76581 | O14: =O9-O15 -> 965.02924
B15: Export sales | C15: KSh mn | D15: 259.217 | E15: 218.473 | F15: 469.523 | G15: 992.445 | H15: 1326.92 | I15: 1564.663 | J15: 1486.453 | K15: =K9*K16 -> 1532.1827 | L15: =L9*L16 -> 1595.884 | M15: =M9*M16 -> 1663.775 | N15: =N9*N16 -> 1731.0748 | O15: =O9*O16 -> 1792.1972
B16: Export revenue mix | C16: % | D16: =IFERROR(D15/D9,"") -> 0.41112926 | E16: =IFERROR(E15/E9,"") -> 0.31992977 | F16: =IFERROR(F15/F9,"") -> 0.51790119 | G16: =IFERROR(G15/G9,"") -> 0.70154313 | H16: =IFERROR(H15/H9,"") -> 0.77104239 | I16: =IFERROR(I15/I9,"") -> 0.75722385 | J16: =IFERROR(J15/J9,"") -> 0.70788533 | K16: 0.69 | L16: 0.68 | M16: 0.67 | N16: 0.66 | O16: 0.65
B18: SEGMENT RESULTS – NOTE 5 ACTUALS / FORECAST
B19: Trading revenue from contracts with customers | C19: KSh mn | D19: 630.5 | E19: 682.878 | F19: 906.588 | G19: 1414.66 | H19: 1720.943 | I19: 2066.315 | J19: 2099.85 | K19: ='Carbacid Model'!K41 -> 2220.5547 | L19: ='Carbacid Model'!L41 -> 2346.8882 | M19: ='Carbacid Model'!M41 -> 2483.2463 | N19: ='Carbacid Model'!N41 -> 2622.8406 | O19: ='Carbacid Model'!O41 -> 2757.2264
B20: Investment revenue from contracts with customers | C20: KSh mn | D20: 0 | E20: 0 | F20: 0 | G20: 0 | H20: 0 | I20: 0 | J20: 0 | K20: 0 | L20: 0 | M20: 0 | N20: 0 | O20: 0
B21: Trading interest income | C21: KSh mn | D21: 1.979 | E21: 0.036 | F21: 0.001 | G21: 0.985 | H21: 0.791 | I21: 1.373 | J21: 3.196 | K21: ='Carbacid Model'!K60*0.01 -> 1.8934976 | L21: ='Carbacid Model'!L60*0.01 -> 1.9503025 | M21: ='Carbacid Model'!M60*0.01 -> 2.0088116 | N21: ='Carbacid Model'!N60*0.01 -> 2.069076 | O21: ='Carbacid Model'!O60*0.01 -> 2.1311482
B22: Investment interest income | C22: KSh mn | D22: 159.935 | E22: 186.841 | F22: 196.289 | G22: 242.419 | H22: 254.503 | I22: 272.096 | J22: 260.759 | K22: ='Carbacid Model'!K60-K21 -> 187.45626 | L22: ='Carbacid Model'!L60-L21 -> 193.07995 | M22: ='Carbacid Model'!M60-M21 -> 198.87235 | N22: ='Carbacid Model'!N60-N21 -> 204.83852 | O22: ='Carbacid Model'!O60-O21 -> 210.98367
B23: Fair value gain/(loss) on investment property | C23: KSh mn | D23: 4.6 | E23: -2.349 | F23: -2.591 | G23: 0 | H23: -2.489 | I23: -4.86 | J23: 0 | K23: 0 | L23: 0 | M23: 0 | N23: 0 | O23: 0
B24: Trading profit before tax | C24: KSh mn | D24: 247.783 | E24: 264.702 | F24: 352.96 | G24: 620.684 | H24: 764.671 | I24: 867.202 | J24: 915.707 | K24: ='Carbacid Model'!K55+K21 -> 956.732 | L24: ='Carbacid Model'!L55+L21 -> 992.33711 | M24: ='Carbacid Model'!M55+M21 -> 1044.9722 | N24: ='Carbacid Model'!N55+N21 -> 1095.7936 | O24: ='Carbacid Model'!O55+O21 -> 1160.1662
B25: Investment profit before tax | C25: KSh mn | D25: 129.37 | E25: 162.257 | F25: 187.305 | G25: 293.145 | H25: 316.445 | I25: 256.556 | J25: 372.857 | K25: ='Carbacid Model'!K64-K24 -> 98.84714 | L25: ='Carbacid Model'!L64-L24 -> 113.33174 | M25: ='Carbacid Model'!M64-M24 -> 127.09896 | N25: ='Carbacid Model'!N64-N24 -> 140.24247 | O25: ='Carbacid Model'!O64-O24 -> 152.84723
B26: Group profit before tax | C26: KSh mn | D26: 377.153 | E26: 426.959 | F26: 540.265 | G26: 913.829 | H26: 1080.982 | I26: 1123.758 | J26: 1288.564 | K26: ='Carbacid Model'!K64 -> 1055.5791 | L26: ='Carbacid Model'!L64 -> 1105.6689 | M26: ='Carbacid Model'!M64 -> 1172.0712 | N26: ='Carbacid Model'!N64 -> 1236.0361 | O26: ='Carbacid Model'!O64 -> 1313.0135
B27: Trading PBT margin | C27: % | D27: =IFERROR(D24/D19,"") -> 0.39299445 | E27: =IFERROR(E24/E19,"") -> 0.38762707 | F27: =IFERROR(F24/F19,"") -> 0.3893279 | G27: =IFERROR(G24/G19,"") -> 0.43875136 | H27: =IFERROR(H24/H19,"") -> 0.44433255 | I27: =IFERROR(I24/I19,"") -> 0.41968529 | J27: =IFERROR(J24/J19,"") -> 0.4360821 | K27: =IFERROR(K24/K19,"") -> 0.43085271 | ... O27: =IFERROR(O24/O19,"") -> 0.42077293
B28: Investment PBT / investment assets | C28: % | D28: =IFERROR(D25/D32,"") -> 0.054493973 | E28: =IFERROR(E25/E32,"") -> 0.072854129 | F28: =IFERROR(F25/F32,"") -> 0.073941331 | G28: =IFERROR(G25/G32,"") -> 0.093607204 | H28: =IFERROR(H25/H32,"") -> 0.089543771 | I28: =IFERROR(I25/I32,"") -> 0.052317069 | J28: =IFERROR(J25/J32,"") -> 0.067349366 | K28: =IFERROR(K25/K32,"") -> 0.011594472 | ... O28: =IFERROR(O25/O32,"") -> 0.016803704
B30: SEGMENT ASSETS AND LIABILITIES – NOTE 5 ACTUALS
B31: Trading segment assets | C31: KSh mn | D31: 1129.478 | E31: 1400.682 | F31: 1386.067 | G31: 1329.533 | H31: 1978.573 | I31: 3216.495 | J31: 3268.685 | K31: ='Carbacid Model'!K93+'Carbacid Model'!K89+'Carbacid Model'!K90+'Carbacid Model'!K92 -> 5219.5724 | L31: ='Carbacid Model'!L93+'Carbacid Model'!L89+'Carbacid Model'!L90+'Carbacid Model'!L92 -> 5562.2989 | M31: ='Carbacid Model'!M93+'Carbacid Model'!M89+'Carbacid Model'!M90+'Carbacid Model'!M92 -> 5931.7386 | N31: ='Carbacid Model'!N93+'Carbacid Model'!N89+'Carbacid Model'!N90+'Carbacid Model'!N92 -> 6331.7818 | O31: ='Carbacid Model'!O93+'Carbacid Model'!O89+'Carbacid Model'!O90+'Carbacid Model'!O92 -> 6758.3214
B32: Investment segment assets | C32: KSh mn | D32: 2374.024 | E32: 2227.149 | F32: 2533.157 | G32: 3131.65 | H32: 3533.97 | I32: 4903.868 | J32: 5536.162 | K32: ='Carbacid Model'!K88+'Carbacid Model'!K96+'Carbacid Model'!K97+'Carbacid Model'!K101 -> 8525.368 | L32: ='Carbacid Model'!L88+'Carbacid Model'!L96+'Carbacid Model'!L97+'Carbacid Model'!L101 -> 8678.1377 | M32: ='Carbacid Model'!M88+'Carbacid Model'!M96+'Carbacid Model'!M97+'Carbacid Model'!M101 -> 8819.7518 | N32: ='Carbacid Model'!N88+'Carbacid Model'!N96+'Carbacid Model'!N97+'Carbacid Model'!N101 -> 8951.8777 | O32: ='Carbacid Model'!O88+'Carbacid Model'!O96+'Carbacid Model'!O97+'Carbacid Model'!O101 -> 9096.0437
B33: Group segment assets | C33: KSh mn | D33: 3503.501 | E33: 3627.831 | F33: 3919.224 | G33: 4461.183 | H33: 5512.543 | I33: 8120.363 | J33: 8804.847 | K33: =K31+K32 -> 13744.94 | L33: =L31+L32 -> 14240.437 | M33: =M31+M32 -> 14751.49 | N33: =N31+N32 -> 15283.659 | O33: =O31+O32 -> 15854.365
B34: Trading segment liabilities | C34: KSh mn | D34: 323.403 | E34: 314.5 | F34: 164.384 | G34: 593.809 | H34: 795.504 | I34: 2797.818 | J34: 2804.285 | K34: ='Carbacid Model'!K99+'Carbacid Model'!K102+'Carbacid Model'!K105 -> 975.50285 | L34: ='Carbacid Model'!L99+'Carbacid Model'!L102+'Carbacid Model'!L105 -> 926.9708 | M34: ='Carbacid Model'!M99+'Carbacid Model'!M102+'Carbacid Model'!M105 -> 882.99079 | N34: ='Carbacid Model'!N99+'Carbacid Model'!N102+'Carbacid Model'!N105 -> 845.83613 | O34: ='Carbacid Model'!O99+'Carbacid Model'!O102+'Carbacid Model'!O105 -> 809.17746
B35: Investment segment liabilities | C35: KSh mn | D35: 52.607 | E35: 61.235 | F35: 266.041 | G35: 38.477 | H35: 321.362 | I35: 351.703 | J35: 451.051 | K35: ='Carbacid Model'!K100+'Carbacid Model'!K103 -> 173.35296 | L35: ='Carbacid Model'!L100+'Carbacid Model'!L103 -> 182.41749 | M35: ='Carbacid Model'!M100+'Carbacid Model'!M103 -> 193.18931 | N35: ='Carbacid Model'!N100+'Carbacid Model'!N103 -> 203.89539 | O35: ='Carbacid Model'!O100+'Carbacid Model'!O103 -> 215.43517
B36: Group segment liabilities | C36: KSh mn | D36: 376.009 | E36: 375.735 | F36: 430.425 | G36: 632.286 | H36: 1116.866 | I36: 3149.521 | J36: 3255.336 | K36: =K34+K35 -> 1148.8558 | L36: =L34+L35 -> 1109.3883 | M36: =M34+M35 -> 1076.1801 | N36: =N34+N35 -> 1049.7315 | O36: =O34+O35 -> 1024.6126
B38: SEGMENT SUPPORTING ITEMS – NOTE 5 / NOTE 9 ACTUALS
B39: Tax expense – Trading | C39: KSh mn | D39: -77.31 | E39: -78.44 | F39: -100.804 | G39: -188.297 | H39: -228.214 | I39: -252.529 | J39: -273.876 | K39: ='Carbacid Model'!K65*K27 -> -104.6038 | L39: ='Carbacid Model'!L65*L27 -> -107.52755 | M39: ='Carbacid Model'!M65*M27 -> -113.44015 | N39: ='Carbacid Model'!N65*N27 -> -118.77249 | O39: ='Carbacid Model'!O65*O27 -> -127.07052
B40: Tax expense – Investment | C40: KSh mn | D40: -35.254 | E40: -23.865 | F40: -24.362 | G40: -17.868 | H40: -36.755 | I40: -27.955 | J40: -11.774 | K40: ='Carbacid Model'!K65-K39 -> -138.1794 | L40: ='Carbacid Model'!L65-L39 -> -146.77629 | M40: ='Carbacid Model'!M65-M39 -> -156.13623 | N40: ='Carbacid Model'!N65-N39 -> -165.51581 | O40: ='Carbacid Model'!O65-O39 -> -174.92258
B41: Tax expense – Group | C41: KSh mn | D41: -112.564 | E41: -102.305 | F41: -125.166 | G41: -206.165 | H41: -264.969 | I41: -280.484 | J41: -285.65 | K41: ='Carbacid Model'!K65 -> -242.7832 | L41: ='Carbacid Model'!L65 -> -254.30384 | M41: ='Carbacid Model'!M65 -> -269.57638 | N41: ='Carbacid Model'!N65 -> -284.2883 | O41: ='Carbacid Model'!O65 -> -301.9931
B42: Depreciation PPE – Trading | C42: KSh mn | D42: 53.574 | E42: 54.587 | F42: 60.717 | G42: 69.025 | H42: 82.936 | I42: 97.047 | J42: 152.663 | K42: ='Carbacid Model'!K57 -> 155.52523 | L42: ='Carbacid Model'!L57 -> 172.61745 | M42: ='Carbacid Model'!M57 -> 176.96245 | N42: ='Carbacid Model'!N57 -> 175.0704 | O42: ='Carbacid Model'!O57 -> 177.43386
B43: Depreciation PPE – Investment | C43: KSh mn | D43: 0 | E43: 0 | F43: 0 | G43: 2.708 | H43: 0.034 | I43: 0.034 | J43: 0.034 | K43: 0 | L43: 0 | M43: 0 | N43: 0 | O43: 0
B44: Depreciation PPE – Group | C44: KSh mn | D44: 53.574 | E44: 54.587 | F44: 60.717 | G44: 71.733 | H44: 82.97 | I44: 97.081 | J44: 152.697 | K44: =K42+K43 -> 155.52523 | L44: =L42+L43 -> 172.61745 | M44: =M42+M43 -> 176.96245 | N44: =N42+N43 -> 175.0704 | O44: =O42+O43 -> 177.43386
B45: Amortisation of intangible assets | C45: KSh mn | D45: 0.179 | E45: 0.239 | F45: 0.239 | G45: 0.616 | H45: 0.616 | I45: 0.271 | J45: 1.361 | K45: 0 | L45: 0 | M45: 0 | N45: 0 | O45: 0
B46: Depreciation of right-of-use assets – Trading | C46: KSh mn | D46: 0 | E46: 0 | F46: 0 | G46: 0 | H46: 0 | I46: 5.085 | J46: 3.272 | K46: 0 | L46: 0 | M46: 0 | N46: 0 | O46: 0
B47: Depreciation of right-of-use assets – Investment | C47: KSh mn | D47: 0.953 | E47: 0.289 | F47: 0.289 | G47: 0.289 | H47: 0.289 | I47: 0.289 | J47: 0.289 | K47: 0 | L47: 0 | M47: 0 | N47: 0 | O47: 0
B48: Depreciation of right-of-use assets – Group | C48: KSh mn | D48: 0.953 | E48: 0.289 | F48: 0.289 | G48: 0.289 | H48: 0.289 | I48: 5.374 | J48: 3.561 | K48: =K46+K47 -> 0 | L48: =L46+L47 -> 0 | M48: =M46+M47 -> 0 | N48: =N46+N47 -> 0 | O48: =O46+O47 -> 0
B49: Capital expenditure – Trading | C49: KSh mn | D49: 37.017 | E49: 49.857 | F49: 0 | G49: 179.959 | H49: 467.798 | I49: 704.611 | J49: 426.911 | K49: ='Carbacid Model'!K123 -> 399.69984 | L49: ='Carbacid Model'!L123 -> 234.68882 | M49: ='Carbacid Model'!M123 -> 223.49216 | N49: ='Carbacid Model'!N123 -> 209.82725 | O49: ='Carbacid Model'!O123 -> 220.57811
B50: Capital expenditure – Investment | C50: KSh mn | D50: 0.67 | E50: 0 | F50: 125.589 | G50: 0 | H50: 0 | I50: 1.004 | J50: 0 | K50: 0 | L50: 0 | M50: 0 | N50: 0 | O50: 0
B51: Capital expenditure – Group | C51: KSh mn | D51: 37.687 | E51: 49.857 | F51: 125.589 | G51: 179.959 | H51: 471.368 | I51: 705.615 | J51: 426.911 | K51: =K49+K50 -> 399.69984 | L51: =L49+L50 -> 234.68882 | M51: =M49+M50 -> 223.49216 | N51: =N49+N50 -> 209.82725 | O51: =O49+O50 -> 220.57811

Sheet Valuation_Summary
B1: Carbacid Investments PLC – Valuation Summary
B3: Valuation method | C3: Weight | D3: Fair value / share | E3: Comment
B4: FCFF DCF / SOTP | C4: ='Carbacid Model'!C197 -> 0.65 | D4: ='Carbacid Model'!C192 -> 37.652874 | E4: Primary method; operating value + separate non-operating assets
B5: EV/EBITDA | C5: ='Carbacid Model'!C198 -> 0.2 | D5: ='Carbacid Model'!C194 -> 26.921628 | E5: Industrial / specialty gas cross-check
B6: P/E | C6: ='Carbacid Model'!C199 -> 0.15 | D6: ='Carbacid Model'!C196 -> 19.978765 | E6: Earnings cross-check; lowest weight due investment income volatility
B8: Weighted target price | C8: ='Carbacid Model'!C200 -> 32.855509
B9: Current price | C9: ='Carbacid Model'!C201 -> 33.1
B10: Upside / downside | C10: ='Carbacid Model'!C202 -> -0.0073864476
B11: Recommendation | C11: ='Carbacid Model'!C203 -> HOLD
B12: Market capitalisation at target | C12: ='Carbacid Model'!C200*Assumptions_Log!D6 -> 8373.2921
B13: Model date | C13: 46205
B14: Methodology | C14: Industrial SOTP: FCFF operating value + non-operating investments; DDM not used.
B17: Judgement | C17: Use SOTP because Carbacid combines an operating CO₂ business and an investment portfolio. Reported PAT includes investment income and fair-value movements, so operating cash flow is valued separately from non-operating assets.
B18: Revenue logic | C18: Revenue is split using actual Note 6 disclosures: CO2 sales revenue and transport revenue. Other operating services are set to zero unless disclosed in future reports.
B19: Gross margin logic | C19: FY2025 margin benefits from solar power and plant efficiency, but royalty, labour, maintenance and fuel costs are expected to create partial mean reversion.
B20: Investment portfolio | C20: Cash/deposits, financial assets and investment property are added separately at latest actual book/fair value to avoid double-counting.
B21: Recommendation rule | C21: BUY >15% upside; SELL <-10% downside; otherwise HOLD.

Sheet Sensitivity
B1: Carbacid Investments PLC – Sensitivity Analysis
B3: DCF/SOTP Sensitivity: Target Price vs WACC and Terminal Growth
B4: Terminal g \ WACC | C4: 0.13 | D4: 0.14 | E4: 0.15 | F4: 0.16 | G4: 0.17 | H4: 0.18
B5: 0.03 | C5: =((('Carbacid Model'!$K$156/(1+C$4))+('Carbacid Model'!$L$156/(1+C$4)^2)+('Carbacid Model'!$M$156/(1+C$4)^3)+('Carbacid Model'!$N$156/(1+C$4)^4)+('Carbacid Model'!$O$156/(1+C$4)^5)+(('Carbacid Model'!$O$156*(1+$B5)/(C$4-$B5))/(1+C$4)^5)+'Carbacid Model'!$C$188-'Carbacid Model'!$C$189)/'Carbacid Model'!$C$191) -> 38.52082 | D5: =((('Carbacid Model'!$K$156/(1+D$4))+('Carbacid Model'!$L$156/(1+D$4)^2)+('Carbacid Model'!$M$156/(1+D$4)^3)+('Carbacid Model'!$N$156/(1+D$4)^4)+('Carbacid Model'!$O$156/(1+D$4)^5)+(('Carbacid Model'!$O$156*(1+$B5)/(D$4-$B5))/(1+D$4)^5)+'Carbacid Model'!$C$188-'Carbacid Model'!$C$189)/'Carbacid Model'!$C$191) -> 35.925421 | E5: =((('Carbacid Model'!$K$156/(1+E$4))+('Carbacid Model'!$L$156/(1+E$4)^2)+('Carbacid Model'!$M$156/(1+E$4)^3)+('Carbacid Model'!$N$156/(1+E$4)^4)+('Carbacid Model'!$O$156/(1+E$4)^5)+(('Carbacid Model'!$O$156*(1+$B5)/(E$4-$B5))/(1+E$4)^5)+'Carbacid Model'!$C$188-'Carbacid Model'!$C$189)/'Carbacid Model'!$C$191) -> 33.764854 | F5: =((('Carbacid Model'!$K$156/(1+F$4))+('Carbacid Model'!$L$156/(1+F$4)^2)+('Carbacid Model'!$M$156/(1+F$4)^3)+('Carbacid Model'!$N$156/(1+F$4)^4)+('Carbacid Model'!$O$156/(1+F$4)^5)+(('Carbacid Model'!$O$156*(1+$B5)/(F$4-$B5))/(1+F$4)^5)+'Carbacid Model'!$C$188-'Carbacid Model'!$C$189)/'Carbacid Model'!$C$191) -> 31.938698 | G5: =((('Carbacid Model'!$K$156/(1+G$4))+('Carbacid Model'!$L$156/(1+G$4)^2)+('Carbacid Model'!$M$156/(1+G$4)^3)+('Carbacid Model'!$N$156/(1+G$4)^4)+('Carbacid Model'!$O$156/(1+G$4)^5)+(('Carbacid Model'!$O$156*(1+$B5)/(G$4-$B5))/(1+G$4)^5)+'Carbacid Model'!$C$188-'Carbacid Model'!$C$189)/'Carbacid Model'!$C$191) -> 30.375228 | H5: =((('Carbacid Model'!$K$156/(1+H$4))+('Carbacid Model'!$L$156/(1+H$4)^2)+('Carbacid Model'!$M$156/(1+H$4)^3)+('Carbacid Model'!$N$156/(1+H$4)^4)+('Carbacid Model'!$O$156/(1+H$4)^5)+(('Carbacid Model'!$O$156*(1+$B5)/(H$4-$B5))/(1+H$4)^5)+'Carbacid Model'!$C$188-'Carbacid Model'!$C$189)/'Carbacid Model'!$C$191) -> 29.021847
B6: 0.04 | C6: =((('Carbacid Model'!$K$156/(1+C$4))+('Carbacid Model'!$L$156/(1+C$4)^2)+('Carbacid Model'!$M$156/(1+C$4)^3)+('Carbacid Model'!$N$156/(1+C$4)^4)+('Carbacid Model'!$O$156/(1+C$4)^5)+(('Carbacid Model'!$O$156*(1+$B6)/(C$4-$B6))/(1+C$4)^5)+'Carbacid Model'!$C$188-'Carbacid Model'!$C$189)/'Carbacid Model'!$C$191) -> 40.723967 | D6: =((('Carbacid Model'!$K$156/(1+D$4))+('Carbacid Model'!$L$156/(1+D$4)^2)+('Carbacid Model'!$M$156/(1+D$4)^3)+('Carbacid Model'!$N$156/(1+D$4)^4)+('Carbacid Model'!$O$156/(1+D$4)^5)+(('Carbacid Model'!$O$156*(1+$B6)/(D$4-$B6))/(1+D$4)^5)+'Carbacid Model'!$C$188-'Carbacid Model'!$C$189)/'Carbacid Model'!$C$191) -> 37.665574 | E6: =((('Carbacid Model'!$K$156/(1+E$4))+('Carbacid Model'!$L$156/(1+E$4)^2)+('Carbacid Model'!$M$156/(1+E$4)^3)+('Carbacid Model'!$N$156/(1+E$4)^4)+('Carbacid Model'!$O$156/(1+E$4)^5)+(('Carbacid Model'!$O$156*(1+$B6)/(E$4-$B6))/(1+E$4)^5)+'Carbacid Model'!$C$188-'Carbacid Model'!$C$189)/'Carbacid Model'!$C$191) -> 35.165197 | F6: =((('Carbacid Model'!$K$156/(1+F$4))+('Carbacid Model'!$L$156/(1+F$4)^2)+('Carbacid Model'!$M$156/(1+F$4)^3)+('Carbacid Model'!$N$156/(1+F$4)^4)+('Carbacid Model'!$O$156/(1+F$4)^5)+(('Carbacid Model'!$O$156*(1+$B6)/(F$4-$B6))/(1+F$4)^5)+'Carbacid Model'!$C$188-'Carbacid Model'!$C$189)/'Carbacid Model'!$C$191) -> 33.083271 | G6: =((('Carbacid Model'!$K$156/(1+G$4))+('Carbacid Model'!$L$156/(1+G$4)^2)+('Carbacid Model'!$M$156/(1+G$4)^3)+('Carbacid Model'!$N$156/(1+G$4)^4)+('Carbacid Model'!$O$156/(1+G$4)^5)+(('Carbacid Model'!$O$156*(1+$B6)/(G$4-$B6))/(1+G$4)^5)+'Carbacid Model'!$C$188-'Carbacid Model'!$C$189)/'Carbacid Model'!$C$191) -> 31.323177 | H6: =((('Carbacid Model'!$K$156/(1+H$4))+('Carbacid Model'!$L$156/(1+H$4)^2)+('Carbacid Model'!$M$156/(1+H$4)^3)+('Carbacid Model'!$N$156/(1+H$4)^4)+('Carbacid Model'!$O$156/(1+H$4)^5)+(('Carbacid Model'!$O$156*(1+$B6)/(H$4-$B6))/(1+H$4)^5)+'Carbacid Model'!$C$188-'Carbacid Model'!$C$189)/'Carbacid Model'!$C$191) -> 29.815906
B7: 0.05 | C7: =((('Carbacid Model'!$K$156/(1+C$4))+('Carbacid Model'!$L$156/(1+C$4)^2)+('Carbacid Model'!$M$156/(1+C$4)^3)+('Carbacid Model'!$N$156/(1+C$4)^4)+('Carbacid Model'!$O$156/(1+C$4)^5)+(('Carbacid Model'!$O$156*(1+$B7)/(C$4-$B7))/(1+C$4)^5)+'Carbacid Model'!$C$188-'Carbacid Model'!$C$189)/'Carbacid Model'!$C$191) -> 43.477901 | D7: =((('Carbacid Model'!$K$156/(1+D$4))+('Carbacid Model'!$L$156/(1+D$4)^2)+('Carbacid Model'!$M$156/(1+D$4)^3)+('Carbacid Model'!$N$156/(1+D$4)^4)+('Carbacid Model'!$O$156/(1+D$4)^5)+(('Carbacid Model'!$O$156*(1+$B7)/(D$4-$B7))/(1+D$4)^5)+'Carbacid Model'!$C$188-'Carbacid Model'!$C$189)/'Carbacid Model'!$C$191) -> 39.792429 | E7: =((('Carbacid Model'!$K$156/(1+E$4))+('Carbacid Model'!$L$156/(1+E$4)^2)+('Carbacid Model'!$M$156/(1+E$4)^3)+('Carbacid Model'!$N$156/(1+E$4)^4)+('Carbacid Model'!$O$156/(1+E$4)^5)+(('Carbacid Model'!$O$156*(1+$B7)/(E$4-$B7))/(1+E$4)^5)+'Carbacid Model'!$C$188-'Carbacid Model'!$C$189)/'Carbacid Model'!$C$191) -> 36.845609 | F7: =((('Carbacid Model'!$K$156/(1+F$4))+('Carbacid Model'!$L$156/(1+F$4)^2)+('Carbacid Model'!$M$156/(1+F$4)^3)+('Carbacid Model'!$N$156/(1+F$4)^4)+('Carbacid Model'!$O$156/(1+F$4)^5)+(('Carbacid Model'!$O$156*(1+$B7)/(F$4-$B7))/(1+F$4)^5)+'Carbacid Model'!$C$188-'Carbacid Model'!$C$189)/'Carbacid Model'!$C$191) -> 34.435947 | G7: =((('Carbacid Model'!$K$156/(1+G$4))+('Carbacid Model'!$L$156/(1+G$4)^2)+('Carbacid Model'!$M$156/(1+G$4)^3)+('Carbacid Model'!$N$156/(1+G$4)^4)+('Carbacid Model'!$O$156/(1+G$4)^5)+(('Carbacid Model'!$O$156*(1+$B7)/(G$4-$B7))/(1+G$4)^5)+'Carbacid Model'!$C$188-'Carbacid Model'!$C$189)/'Carbacid Model'!$C$191) -> 32.429118 | H7: =((('Carbacid Model'!$K$156/(1+H$4))+('Carbacid Model'!$L$156/(1+H$4)^2)+('Carbacid Model'!$M$156/(1+H$4)^3)+('Carbacid Model'!$N$156/(1+H$4)^4)+('Carbacid Model'!$O$156/(1+H$4)^5)+(('Carbacid Model'!$O$156*(1+$B7)/(H$4-$B7))/(1+H$4)^5)+'Carbacid Model'!$C$188-'Carbacid Model'!$C$189)/'Carbacid Model'!$C$191) -> 30.732127
B8: 0.06 | C8: =((('Carbacid Model'!$K$156/(1+C$4))+('Carbacid Model'!$L$156/(1+C$4)^2)+('Carbacid Model'!$M$156/(1+C$4)^3)+('Carbacid Model'!$N$156/(1+C$4)^4)+('Carbacid Model'!$O$156/(1+C$4)^5)+(('Carbacid Model'!$O$156*(1+$B8)/(C$4-$B8))/(1+C$4)^5)+'Carbacid Model'!$C$188-'Carbacid Model'!$C$189)/'Carbacid Model'!$C$191) -> 47.018673 | D8: =((('Carbacid Model'!$K$156/(1+D$4))+('Carbacid Model'!$L$156/(1+D$4)^2)+('Carbacid Model'!$M$156/(1+D$4)^3)+('Carbacid Model'!$N$156/(1+D$4)^4)+('Carbacid Model'!$O$156/(1+D$4)^5)+(('Carbacid Model'!$O$156*(1+$B8)/(D$4-$B8))/(1+D$4)^5)+'Carbacid Model'!$C$188-'Carbacid Model'!$C$189)/'Carbacid Model'!$C$191) -> 42.450998 | E8: =((('Carbacid Model'!$K$156/(1+E$4))+('Carbacid Model'!$L$156/(1+E$4)^2)+('Carbacid Model'!$M$156/(1+E$4)^3)+('Carbacid Model'!$N$156/(1+E$4)^4)+('Carbacid Model'!$O$156/(1+E$4)^5)+(('Carbacid Model'!$O$156*(1+$B8)/(E$4-$B8))/(1+E$4)^5)+'Carbacid Model'!$C$188-'Carbacid Model'!$C$189)/'Carbacid Model'!$C$191) -> 38.899445 | F8: =((('Carbacid Model'!$K$156/(1+F$4))+('Carbacid Model'!$L$156/(1+F$4)^2)+('Carbacid Model'!$M$156/(1+F$4)^3)+('Carbacid Model'!$N$156/(1+F$4)^4)+('Carbacid Model'!$O$156/(1+F$4)^5)+(('Carbacid Model'!$O$156*(1+$B8)/(F$4-$B8))/(1+F$4)^5)+'Carbacid Model'!$C$188-'Carbacid Model'!$C$189)/'Carbacid Model'!$C$191) -> 36.059158 | G8: =((('Carbacid Model'!$K$156/(1+G$4))+('Carbacid Model'!$L$156/(1+G$4)^2)+('Carbacid Model'!$M$156/(1+G$4)^3)+('Carbacid Model'!$N$156/(1+G$4)^4)+('Carbacid Model'!$O$156/(1+G$4)^5)+(('Carbacid Model'!$O$156*(1+$B8)/(G$4-$B8))/(1+G$4)^5)+'Carbacid Model'!$C$188-'Carbacid Model'!$C$189)/'Carbacid Model'!$C$191) -> 33.736138 | H8: =((('Carbacid Model'!$K$156/(1+H$4))+('Carbacid Model'!$L$156/(1+H$4)^2)+('Carbacid Model'!$M$156/(1+H$4)^3)+('Carbacid Model'!$N$156/(1+H$4)^4)+('Carbacid Model'!$O$156/(1+H$4)^5)+(('Carbacid Model'!$O$156*(1+$B8)/(H$4-$B8))/(1+H$4)^5)+'Carbacid Model'!$C$188-'Carbacid Model'!$C$189)/'Carbacid Model'!$C$191) -> 31.801052
B9: 0.07 | C9: =((('Carbacid Model'!$K$156/(1+C$4))+('Carbacid Model'!$L$156/(1+C$4)^2)+('Carbacid Model'!$M$156/(1+C$4)^3)+('Carbacid Model'!$N$156/(1+C$4)^4)+('Carbacid Model'!$O$156/(1+C$4)^5)+(('Carbacid Model'!$O$156*(1+$B9)/(C$4-$B9))/(1+C$4)^5)+'Carbacid Model'!$C$188-'Carbacid Model'!$C$189)/'Carbacid Model'!$C$191) -> 51.739702 | D9: =((('Carbacid Model'!$K$156/(1+D$4))+('Carbacid Model'!$L$156/(1+D$4)^2)+('Carbacid Model'!$M$156/(1+D$4)^3)+('Carbacid Model'!$N$156/(1+D$4)^4)+('Carbacid Model'!$O$156/(1+D$4)^5)+(('Carbacid Model'!$O$156*(1+$B9)/(D$4-$B9))/(1+D$4)^5)+'Carbacid Model'!$C$188-'Carbacid Model'!$C$189)/'Carbacid Model'!$C$191) -> 45.869157 | E9: =((('Carbacid Model'!$K$156/(1+E$4))+('Carbacid Model'!$L$156/(1+E$4)^2)+('Carbacid Model'!$M$156/(1+E$4)^3)+('Carbacid Model'!$N$156/(1+E$4)^4)+('Carbacid Model'!$O$156/(1+E$4)^5)+(('Carbacid Model'!$O$156*(1+$B9)/(E$4-$B9))/(1+E$4)^5)+'Carbacid Model'!$C$188-'Carbacid Model'!$C$189)/'Carbacid Model'!$C$191) -> 41.466741 | F9: =((('Carbacid Model'!$K$156/(1+F$4))+('Carbacid Model'!$L$156/(1+F$4)^2)+('Carbacid Model'!$M$156/(1+F$4)^3)+('Carbacid Model'!$N$156/(1+F$4)^4)+('Carbacid Model'!$O$156/(1+F$4)^5)+(('Carbacid Model'!$O$156*(1+$B9)/(F$4-$B9))/(1+F$4)^5)+'Carbacid Model'!$C$188-'Carbacid Model'!$C$189)/'Carbacid Model'!$C$191) -> 38.043084 | G9: =((('Carbacid Model'!$K$156/(1+G$4))+('Carbacid Model'!$L$156/(1+G$4)^2)+('Carbacid Model'!$M$156/(1+G$4)^3)+('Carbacid Model'!$N$156/(1+G$4)^4)+('Carbacid Model'!$O$156/(1+G$4)^5)+(('Carbacid Model'!$O$156*(1+$B9)/(G$4-$B9))/(1+G$4)^5)+'Carbacid Model'!$C$188-'Carbacid Model'!$C$189)/'Carbacid Model'!$C$191) -> 35.304563 | H9: =((('Carbacid Model'!$K$156/(1+H$4))+('Carbacid Model'!$L$156/(1+H$4)^2)+('Carbacid Model'!$M$156/(1+H$4)^3)+('Carbacid Model'!$N$156/(1+H$4)^4)+('Carbacid Model'!$O$156/(1+H$4)^5)+(('Carbacid Model'!$O$156*(1+$B9)/(H$4-$B9))/(1+H$4)^5)+'Carbacid Model'!$C$188-'Carbacid Model'!$C$189)/'Carbacid Model'!$C$191) -> 33.064326
B12: Weighted Target Sensitivity: EV/EBITDA and P/E Multiples
B13: P/E \ EV/EBITDA | C13: 5 | D13: 5.5 | E13: 6 | F13: 6.5 | G13: 7 | H13: 7.5
B14: 8 | C14: ='Carbacid Model'!$C$192*'Carbacid Model'!$C$197+((('Carbacid Model'!$O$58*C$13*'Carbacid Model'!$O$157)+'Carbacid Model'!$C$188-'Carbacid Model'!$C$189)/'Carbacid Model'!$C$191)*'Carbacid Model'!$C$198+(('Carbacid Model'!$O$66*$B14*'Carbacid Model'!$O$157)/'Carbacid Model'!$C$191)*'Carbacid Model'!$C$199 -> 31.728342 | D14: ='Carbacid Model'!$C$192*'Carbacid Model'!$C$197+((('Carbacid Model'!$O$58*D$13*'Carbacid Model'!$O$157)+'Carbacid Model'!$C$188-'Carbacid Model'!$C$189)/'Carbacid Model'!$C$191)*'Carbacid Model'!$C$198+(('Carbacid Model'!$O$66*$B14*'Carbacid Model'!$O$157)/'Carbacid Model'!$C$191)*'Carbacid Model'!$C$199 -> 31.992244 | E14: ='Carbacid Model'!$C$192*'Carbacid Model'!$C$197+((('Carbacid Model'!$O$58*E$13*'Carbacid Model'!$O$157)+'Carbacid Model'!$C$188-'Carbacid Model'!$C$189)/'Carbacid Model'!$C$191)*'Carbacid Model'!$C$198+(('Carbacid Model'!$O$66*$B14*'Carbacid Model'!$O$157)/'Carbacid Model'!$C$191)*'Carbacid Model'!$C$199 -> 32.256146 | F14: ='Carbacid Model'!$C$192*'Carbacid Model'!$C$197+((('Carbacid Model'!$O$58*F$13*'Carbacid Model'!$O$157)+'Carbacid Model'!$C$188-'Carbacid Model'!$C$189)/'Carbacid Model'!$C$191)*'Carbacid Model'!$C$198+(('Carbacid Model'!$O$66*$B14*'Carbacid Model'!$O$157)/'Carbacid Model'!$C$191)*'Carbacid Model'!$C$199 -> 32.520048 | G14: ='Carbacid Model'!$C$192*'Carbacid Model'!$C$197+((('Carbacid Model'!$O$58*G$13*'Carbacid Model'!$O$157)+'Carbacid Model'!$C$188-'Carbacid Model'!$C$189)/'Carbacid Model'!$C$191)*'Carbacid Model'!$C$198+(('Carbacid Model'!$O$66*$B14*'Carbacid Model'!$O$157)/'Carbacid Model'!$C$191)*'Carbacid Model'!$C$199 -> 32.783949 | H14: ='Carbacid Model'!$C$192*'Carbacid Model'!$C$197+((('Carbacid Model'!$O$58*H$13*'Carbacid Model'!$O$157)+'Carbacid Model'!$C$188-'Carbacid Model'!$C$189)/'Carbacid Model'!$C$191)*'Carbacid Model'!$C$198+(('Carbacid Model'!$O$66*$B14*'Carbacid Model'!$O$157)/'Carbacid Model'!$C$191)*'Carbacid Model'!$C$199 -> 33.047851
B15: 9 | C15: ='Carbacid Model'!$C$192*'Carbacid Model'!$C$197+((('Carbacid Model'!$O$58*C$13*'Carbacid Model'!$O$157)+'Carbacid Model'!$C$188-'Carbacid Model'!$C$189)/'Carbacid Model'!$C$191)*'Carbacid Model'!$C$198+(('Carbacid Model'!$O$66*$B15*'Carbacid Model'!$O$157)/'Carbacid Model'!$C$191)*'Carbacid Model'!$C$199 -> 32.028023 | D15: ='Carbacid Model'!$C$192*'Carbacid Model'!$C$197+((('Carbacid Model'!$O$58*D$13*'Carbacid Model'!$O$157)+'Carbacid Model'!$C$188-'Carbacid Model'!$C$189)/'Carbacid Model'!$C$191)*'Carbacid Model'!$C$198+(('Carbacid Model'!$O$66*$B15*'Carbacid Model'!$O$157)/'Carbacid Model'!$C$191)*'Carbacid Model'!$C$199 -> 32.291925 | E15: ='Carbacid Model'!$C$192*'Carbacid Model'!$C$197+((('Carbacid Model'!$O$58*E$13*'Carbacid Model'!$O$157)+'Carbacid Model'!$C$188-'Carbacid Model'!$C$189)/'Carbacid Model'!$C$191)*'Carbacid Model'!$C$198+(('Carbacid Model'!$O$66*$B15*'Carbacid Model'!$O$157)/'Carbacid Model'!$C$191)*'Carbacid Model'!$C$199 -> 32.555827 | F15: ='Carbacid Model'!$C$192*'Carbacid Model'!$C$197+((('Carbacid Model'!$O$58*F$13*'Carbacid Model'!$O$157)+'Carbacid Model'!$C$188-'Carbacid Model'!$C$189)/'Carbacid Model'!$C$191)*'Carbacid Model'!$C$198+(('Carbacid Model'!$O$66*$B15*'Carbacid Model'!$O$157)/'Carbacid Model'!$C$191)*'Carbacid Model'!$C$199 -> 32.819729 | G15: ='Carbacid Model'!$C$192*'Carbacid Model'!$C$197+((('Carbacid Model'!$O$58*G$13*'Carbacid Model'!$O$157)+'Carbacid Model'!$C$188-'Carbacid Model'!$C$189)/'Carbacid Model'!$C$191)*'Carbacid Model'!$C$198+(('Carbacid Model'!$O$66*$B15*'Carbacid Model'!$O$157)/'Carbacid Model'!$C$191)*'Carbacid Model'!$C$199 -> 33.083631 | H15: ='Carbacid Model'!$C$192*'Carbacid Model'!$C$197+((('Carbacid Model'!$O$58*H$13*'Carbacid Model'!$O$157)+'Carbacid Model'!$C$188-'Carbacid Model'!$C$189)/'Carbacid Model'!$C$191)*'Carbacid Model'!$C$198+(('Carbacid Model'!$O$66*$B15*'Carbacid Model'!$O$157)/'Carbacid Model'!$C$191)*'Carbacid Model'!$C$199 -> 33.347533
B16: 10 | C16: ='Carbacid Model'!$C$192*'Carbacid Model'!$C$197+((('Carbacid Model'!$O$58*C$13*'Carbacid Model'!$O$157)+'Carbacid Model'!$C$188-'Carbacid Model'!$C$189)/'Carbacid Model'!$C$191)*'Carbacid Model'!$C$198+(('Carbacid Model'!$O$66*$B16*'Carbacid Model'!$O$157)/'Carbacid Model'!$C$191)*'Carbacid Model'!$C$199 -> 32.327705 | D16: ='Carbacid Model'!$C$192*'Carbacid Model'!$C$197+((('Carbacid Model'!$O$58*D$13*'Carbacid Model'!$O$157)+'Carbacid Model'!$C$188-'Carbacid Model'!$C$189)/'Carbacid Model'!$C$191)*'Carbacid Model'!$C$198+(('Carbacid Model'!$O$66*$B16*'Carbacid Model'!$O$157)/'Carbacid Model'!$C$191)*'Carbacid Model'!$C$199 -> 32.591607 | E16: ='Carbacid Model'!$C$192*'Carbacid Model'!$C$197+((('Carbacid Model'!$O$58*E$13*'Carbacid Model'!$O$157)+'Carbacid Model'!$C$188-'Carbacid Model'!$C$189)/'Carbacid Model'!$C$191)*'Carbacid Model'!$C$198+(('Carbacid Model'!$O$66*$B16*'Carbacid Model'!$O$157)/'Carbacid Model'!$C$191)*'Carbacid Model'!$C$199 -> 32.855509 | F16: ='Carbacid Model'!$C$192*'Carbacid Model'!$C$197+((('Carbacid Model'!$O$58*F$13*'Carbacid Model'!$O$157)+'Carbacid Model'!$C$188-'Carbacid Model'!$C$189)/'Carbacid Model'!$C$191)*'Carbacid Model'!$C$198+(('Carbacid Model'!$O$66*$B16*'Carbacid Model'!$O$157)/'Carbacid Model'!$C$191)*'Carbacid Model'!$C$199 -> 33.11941 | G16: ='Carbacid Model'!$C$192*'Carbacid Model'!$C$197+((('Carbacid Model'!$O$58*G$13*'Carbacid Model'!$O$157)+'Carbacid Model'!$C$188-'Carbacid Model'!$C$189)/'Carbacid Model'!$C$191)*'Carbacid Model'!$C$198+(('Carbacid Model'!$O$66*$B16*'Carbacid Model'!$O$157)/'Carbacid Model'!$C$191)*'Carbacid Model'!$C$199 -> 33.383312 | H16: ='Carbacid Model'!$C$192*'Carbacid Model'!$C$197+((('Carbacid Model'!$O$58*H$13*'Carbacid Model'!$O$157)+'Carbacid Model'!$C$188-'Carbacid Model'!$C$189)/'Carbacid Model'!$C$191)*'Carbacid Model'!$C$198+(('Carbacid Model'!$O$66*$B16*'Carbacid Model'!$O$157)/'Carbacid Model'!$C$191)*'Carbacid Model'!$C$199 -> 33.647214
B17: 11 | C17: ='Carbacid Model'!$C$192*'Carbacid Model'!$C$197+((('Carbacid Model'!$O$58*C$13*'Carbacid Model'!$O$157)+'Carbacid Model'!$C$188-'Carbacid Model'!$C$189)/'Carbacid Model'!$C$191)*'Carbacid Model'!$C$198+(('Carbacid Model'!$O$66*$B17*'Carbacid Model'!$O$157)/'Carbacid Model'!$C$191)*'Carbacid Model'!$C$199 -> 32.627386 | D17: ='Carbacid Model'!$C$192*'Carbacid Model'!$C$197+((('Carbacid Model'!$O$58*D$13*'Carbacid Model'!$O$157)+'Carbacid Model'!$C$188-'Carbacid Model'!$C$189)/'Carbacid Model'!$C$191)*'Carbacid Model'!$C$198+(('Carbacid Model'!$O$66*$B17*'Carbacid Model'!$O$157)/'Carbacid Model'!$C$191)*'Carbacid Model'!$C$199 -> 32.891288 | E17: ='Carbacid Model'!$C$192*'Carbacid Model'!$C$197+((('Carbacid Model'!$O$58*E$13*'Carbacid Model'!$O$157)+'Carbacid Model'!$C$188-'Carbacid Model'!$C$189)/'Carbacid Model'!$C$191)*'Carbacid Model'!$C$198+(('Carbacid Model'!$O$66*$B17*'Carbacid Model'!$O$157)/'Carbacid Model'!$C$191)*'Carbacid Model'!$C$199 -> 33.15519 | F17: ='Carbacid Model'!$C$192*'Carbacid Model'!$C$197+((('Carbacid Model'!$O$58*F$13*'Carbacid Model'!$O$157)+'Carbacid Model'!$C$188-'Carbacid Model'!$C$189)/'Carbacid Model'!$C$191)*'Carbacid Model'!$C$198+(('Carbacid Model'!$O$66*$B17*'Carbacid Model'!$O$157)/'Carbacid Model'!$C$191)*'Carbacid Model'!$C$199 -> 33.419092 | G17: ='Carbacid Model'!$C$192*'Carbacid Model'!$C$197+((('Carbacid Model'!$O$58*G$13*'Carbacid Model'!$O$157)+'Carbacid Model'!$C$188-'Carbacid Model'!$C$189)/'Carbacid Model'!$C$191)*'Carbacid Model'!$C$198+(('Carbacid Model'!$O$66*$B17*'Carbacid Model'!$O$157)/'Carbacid Model'!$C$191)*'Carbacid Model'!$C$199 -> 33.682994 | H17: ='Carbacid Model'!$C$192*'Carbacid Model'!$C$197+((('Carbacid Model'!$O$58*H$13*'Carbacid Model'!$O$157)+'Carbacid Model'!$C$188-'Carbacid Model'!$C$189)/'Carbacid Model'!$C$191)*'Carbacid Model'!$C$198+(('Carbacid Model'!$O$66*$B17*'Carbacid Model'!$O$157)/'Carbacid Model'!$C$191)*'Carbacid Model'!$C$199 -> 33.946896
B18: 12 | C18: ='Carbacid Model'!$C$192*'Carbacid Model'!$C$197+((('Carbacid Model'!$O$58*C$13*'Carbacid Model'!$O$157)+'Carbacid Model'!$C$188-'Carbacid Model'!$C$189)/'Carbacid Model'!$C$191)*'Carbacid Model'!$C$198+(('Carbacid Model'!$O$66*$B18*'Carbacid Model'!$O$157)/'Carbacid Model'!$C$191)*'Carbacid Model'!$C$199 -> 32.927068 | D18: ='Carbacid Model'!$C$192*'Carbacid Model'!$C$197+((('Carbacid Model'!$O$58*D$13*'Carbacid Model'!$O$157)+'Carbacid Model'!$C$188-'Carbacid Model'!$C$189)/'Carbacid Model'!$C$191)*'Carbacid Model'!$C$198+(('Carbacid Model'!$O$66*$B18*'Carbacid Model'!$O$157)/'Carbacid Model'!$C$191)*'Carbacid Model'!$C$199 -> 33.19097 | E18: ='Carbacid Model'!$C$192*'Carbacid Model'!$C$197+((('Carbacid Model'!$O$58*E$13*'Carbacid Model'!$O$157)+'Carbacid Model'!$C$188-'Carbacid Model'!$C$189)/'Carbacid Model'!$C$191)*'Carbacid Model'!$C$198+(('Carbacid Model'!$O$66*$B18*'Carbacid Model'!$O$157)/'Carbacid Model'!$C$191)*'Carbacid Model'!$C$199 -> 33.454872 | F18: ='Carbacid Model'!$C$192*'Carbacid Model'!$C$197+((('Carbacid Model'!$O$58*F$13*'Carbacid Model'!$O$157)+'Carbacid Model'!$C$188-'Carbacid Model'!$C$189)/'Carbacid Model'!$C$191)*'Carbacid Model'!$C$198+(('Carbacid Model'!$O$66*$B18*'Carbacid Model'!$O$157)/'Carbacid Model'!$C$191)*'Carbacid Model'!$C$199 -> 33.718773 | G18: ='Carbacid Model'!$C$192*'Carbacid Model'!$C$197+((('Carbacid Model'!$O$58*G$13*'Carbacid Model'!$O$157)+'Carbacid Model'!$C$188-'Carbacid Model'!$C$189)/'Carbacid Model'!$C$191)*'Carbacid Model'!$C$198+(('Carbacid Model'!$O$66*$B18*'Carbacid Model'!$O$157)/'Carbacid Model'!$C$191)*'Carbacid Model'!$C$199 -> 33.982675 | H18: ='Carbacid Model'!$C$192*'Carbacid Model'!$C$197+((('Carbacid Model'!$O$58*H$13*'Carbacid Model'!$O$157)+'Carbacid Model'!$C$188-'Carbacid Model'!$C$189)/'Carbacid Model'!$C$191)*'Carbacid Model'!$C$198+(('Carbacid Model'!$O$66*$B18*'Carbacid Model'!$O$157)/'Carbacid Model'!$C$191)*'Carbacid Model'!$C$199 -> 34.246577
