Workbook

Sheet KPLC_MODEL
B1: Model by Brian Githinji
B3: Dashboard / Final Output
B4: Recommendation | D4: =Q308 -> BUY | F4: Current Share Price | G4: =D19 -> 18.35 | J4: Target Price | K4: =Q304 -> 56.152765 | N4: Upside / Downside | O4: =Q305 -> 2.0600962
B5: Current share price | D5: =D19 -> 18.35
B6: Target price | D6: =Q304 -> 56.152765
B7: Upside / downside | D7: =Q305 -> 2.0600962
B8: FY2026E DPS | D8: =M247 -> 0.70286511
B9: Forward dividend yield | D9: =Q306 -> 0.038303276
B10: Total return | D10: =Q307 -> 2.0983995
B11: Residual Income value | D11: =Q283 -> 54.025189
B12: FCFE value | D12: =Q288 -> 60.826951
B13: DDM value | D13: =Q292 -> 8.0111417
B14: Justified P/B value | D14: =Q295 -> 73.054245
B16: ASSUMPTIONS
B17: Core principle
B18: Control / Assumption | C18: Unit | D18: Value | S18: Notes
B19: Current share price | C19: KSh/share | D19: 18.35 | S19: Editable input only used for upside/total return.
B20: Shares outstanding | C20: mn shares | D20: ='Historical Dataset'!N266 -> 1951.4668 | S20: Formula-linked to share data.
B21: Market capitalization | C21: KSh mn | D21: =D19*D20 -> 35809.416 | S21: Current price × shares outstanding.
B22: Risk-free rate | C22: % | D22: 0.1239 | S22: Editable market input.
B23: Beta | C23: x | D23: 0.3 | S23: Low-beta regulated utility assumption; editable.
B24: Equity risk premium | C24: % | D24: 0.06 | S24: Editable ERP input.
B25: Size / liquidity premium | C25: % | D25: 0.02 | S25: NSE liquidity and small-cap premium.
B26: Regulatory / turnaround premium | C26: % | D26: 0.015 | S26: Tariff, policy and execution risk.
B27: Cost of equity | C27: % | D27: =D22+D23*D24+D25+D26 -> 0.1769 | S27: Rf + beta×ERP + size/liquidity + regulatory premium.
B28: Normalized pre-tax cost of debt | C28: % | D28: 0.055 | S28: Editable; compare against actual interest/debt.
B29: Normalized tax rate | C29: % | D29: =MIN(MAX(AVERAGE(ABS('Historical Dataset'!L124/'Historical Dataset'!L123),ABS('Historical Dataset'!M124/'Historical Dataset'!M123),ABS('Historical Dataset'!N124/'Historical Dataset'!N123)),0),30%) -> 0.29976869 | S29: Capped at 30% statutory proxy.
B30: Inflation assumption | C30: % | D30: 0.064 | S30: Editable macro input.
B31: Real GDP growth assumption | C31: % | D31: 0.045 | S31: Editable demand anchor.
B32: Terminal growth | C32: % | D32: =MIN((D30*0.6)+(D31*0.4),5.5%) -> 0.055 | S32: Long-run nominal regulated utility growth cap.
B33: Unit growth floor | C33: % | D33: =MAX(2%,D31*0.5) -> 0.0225 | S33: Electrification and GDP floor.
B34: Unit growth cap | C34: % | D34: =MIN(6%,D31+1.5%) -> 0.06 | S34: Prevents extrapolating FY2025 rebound indefinitely.
B35: Annual unit-growth fade | C35: % | D35: 0.005 | S35: Growth fades toward mature demand.
B36: Effective price growth floor | C36: % | D36: 0 | S36: Current tariffs remain in force unless reviewed.
B37: Effective price growth cap | C37: % | D37: =MIN(D30*0.5,3%) -> 0.03 | S37: Partial inflation pass-through, capped.
B38: Annual effective-price growth fade | C38: % | D38: 0.0025 | S38: Price growth fades as tariffs normalize.
B39: Distribution efficiency target | C39: % | D39: 0.82 | S39: Gradual target, not immediate full recovery.
B40: Annual efficiency improvement | C40: % | D40: =MIN(0.75%,('Historical Dataset'!N20-'Historical Dataset'!M20)/2) -> 0.0075 | S40: Half latest improvement, capped at 75bps.
B41: Thermal share floor | C41: % | D41: 0.07 | S41: Thermal dispatch does not disappear.
B42: Thermal share annual fade | C42: % | D42: 0.005 | S42: Gradual renewable integration.
B43: Power purchase cost inflation | C43: % | D43: =D30*0.5 -> 0.032 | S43: Partial inflation under regulated PPAs.
B44: Opex inflation | C44: % | D44: =D30*0.65 -> 0.0416 | S44: Efficiency offsets full CPI.
B45: Normalized ECL charge / revenue | C45: % | D45: =AVERAGE(ABS('Historical Dataset'!H109/'Historical Dataset'!H71),ABS('Historical Dataset'!I109/'Historical Dataset'!I71),ABS('Historical Dataset'!J109/'Historical Dataset'!J71),ABS('Historical Dataset'!L109/'Historical Dataset'!L71),ABS('Historical Dataset'!M109/'Historical Dataset'!M71)) -> 0.011053389 | S45: Excludes FY2025 reversal.
B46: Capex / revenue | C46: % | D46: =AVERAGE('Historical Dataset'!L220/'Historical Dataset'!L71,'Historical Dataset'!M220/'Historical Dataset'!M71,'Historical Dataset'!N220/'Historical Dataset'!N71) -> 0.10494766 | S46: 3-year average capex intensity.
B47: Depreciation / opening PPE | C47: % | D47: =AVERAGE(ABS('Historical Dataset'!L221/'Historical Dataset'!K219),ABS('Historical Dataset'!M221/'Historical Dataset'!L219),ABS('Historical Dataset'!N221/'Historical Dataset'!M219)) -> 0.06185189 | S47: Recent depreciation / opening PPE proxy.
B48: Receivable days target | C48: days | D48: =AVERAGE('Historical Dataset'!L215:N215) -> 109.1379 | S48: Recent historical collection profile.
B49: Inventory days target | C49: days | D49: =AVERAGE('Historical Dataset'!L216:N216) -> 24.903488 | S49: Recent historical inventory days.
B50: Payables days target | C50: days | D50: =AVERAGE('Historical Dataset'!L217:N217) -> 229.57499 | S50: Recent historical supplier financing.
B51: Debt repayment rate | C51: % | D51: =MIN(MAX(('Historical Dataset'!M228-'Historical Dataset'!N228)/'Historical Dataset'!M228,5%),12%) -> 0.11003895 | S51: Anchored to latest debt reduction, capped.
B52: Dividend payout ratio | C52: % | D52: =MIN(MAX(ABS('Historical Dataset'!N268/'Historical Dataset'!N125),5%),45%) -> 0.071784612 | S52: Latest dividend / PAT, floored at 5%.
B53: Residual income weight | C53: % | D53: 0.45 | S53: Primary method for asset-heavy regulated utility.
B54: FCFE weight | C54: % | D54: 0.15 | S54: Useful, but debt/WC movements can distort.
B55: DDM weight | C55: % | D55: 0.1 | S55: Dividend cross-check.
B56: Justified P/B weight | C56: % | D56: 0.3 | S56: Market-friendly utility cross-check.
B57: P/B discount factor | C57: % | D57: 0.8 | S57: Discount theoretical P/B for regulatory/liquidity risk.
B59: REVENUE | D59: 43100 | E59: =EOMONTH(D59,12) -> 43465 | F59: =EOMONTH(E59,12) -> 43830 | G59: =EOMONTH(F59,12) -> 44196 | H59: =EOMONTH(G59,12) -> 44561 | I59: =EOMONTH(H59,12) -> 44926 | J59: =EOMONTH(I59,12) -> 45291 | K59: =EOMONTH(J59,12) -> 45657 | L59: =EOMONTH(K59,12) -> 46022 | ... Q59: =EOMONTH(P59,12) -> 47848
B60: Line item | C60: Unit | D60: 2017 | E60: 2018 | F60: 2019 | G60: 2020 | H60: 2021 | I60: 2022 | J60: 2023 | K60: 2024 | L60: 2025 | M60: 2026F | N60: 2027F | O60: 2028F | P60: 2029F | Q60: 2030F
B61: TOTAL UNITS SOLD | C61: GWh | D61: =D64+D68+D72+D76+D80+D84+D88 -> 8231 | E61: =E64+E68+E72+E76+E80+E84+E88 -> 8425 | F61: =F64+F68+F72+F76+F80+F84+F88 -> 8768 | G61: =G64+G68+G72+G76+G80+G84+G88 -> 8775 | H61: =H64+H68+H72+H76+H80+H84+H88 -> 9203 | I61: =I64+I68+I72+I76+I80+I84+I88 -> 9814 | J61: =J64+J68+J72+J76+J80+J84+J88 -> 10232 | K61: =K64+K68+K72+K76+K80+K84+K88 -> 10516.24 | ... Q61: =Q64+Q68+Q72+Q76+Q80+Q84+Q88 -> 13823.137
B62: YoY growth | C62: % | E62: =IFERROR(E61/D61-1,"") -> 0.023569433 | F62: =IFERROR(F61/E61-1,"") -> 0.040712166 | G62: =IFERROR(G61/F61-1,"") -> 0.00079835766 | H62: =IFERROR(H61/G61-1,"") -> 0.048774929 | I62: =IFERROR(I61/H61-1,"") -> 0.066391394 | J62: =IFERROR(J61/I61-1,"") -> 0.042592215 | K62: =IFERROR(K61/J61-1,"") -> 0.027779515 | L62: =IFERROR(L61/K61-1,"") -> 0.084311503 | ... Q62: =IFERROR(Q61/P61-1,"") -> 0.029289597
B64: Domestic unit sales | C64: GWh | D64: ='Historical Dataset'!F39 -> 2138 | E64: ='Historical Dataset'!G39 -> 2335 | F64: ='Historical Dataset'!H39 -> 2366 | G64: ='Historical Dataset'!I39 -> 2508 | H64: ='Historical Dataset'!J39 -> 2630 | I64: ='Historical Dataset'!K39 -> 2728 | J64: ='Historical Dataset'!L39 -> 2798 | K64: ='Historical Dataset'!M39 -> 2769 | L64: ='Historical Dataset'!N39 -> 3104 | M64: =L64*(1+M65) -> 3245.0019 | N64: =M64*(1+N65) -> 3376.1839 | O64: =N64*(1+O65) -> 3495.7881 | P64: =O64*(1+P65) -> 3602.1504 | Q64: =P64*(1+Q65) -> 3693.7382
B65: YoY growth | C65: % | E65: =IFERROR(E64/D64-1,"") -> 0.092142189 | F65: =IFERROR(F64/E64-1,"") -> 0.013276231 | G65: =IFERROR(G64/F64-1,"") -> 0.060016906 | H65: =IFERROR(H64/G64-1,"") -> 0.048644338 | I65: =IFERROR(I64/H64-1,"") -> 0.037262357 | J65: =IFERROR(J64/I64-1,"") -> 0.025659824 | K65: =IFERROR(K64/J64-1,"") -> -0.010364546 | L65: =IFERROR(L64/K64-1,"") -> 0.1209823 | M65: =IFERROR(MAX(MIN(AVERAGE(J65:L65),D34),D33),0) -> 0.045425861 | N65: =MAX(MIN(M65-D35,D34),D33) -> 0.040425861 | O65: =MAX(MIN(N65-D35,D34),D33) -> 0.035425861 | P65: =MAX(MIN(O65-D35,D34),D33) -> 0.030425861 | Q65: =MAX(MIN(P65-D35,D34),D33) -> 0.025425861
B66: % of total units | C66: % | D66: =IFERROR(D64/D61,"") -> 0.25974973 | E66: =IFERROR(E64/E61,"") -> 0.27715134 | F66: =IFERROR(F64/F61,"") -> 0.26984489 | G66: =IFERROR(G64/G61,"") -> 0.28581197 | H66: =IFERROR(H64/H61,"") -> 0.28577638 | I66: =IFERROR(I64/I61,"") -> 0.27797025 | J66: =IFERROR(J64/J61,"") -> 0.27345582 | K66: =IFERROR(K64/K61,"") -> 0.26330704 | ... Q66: =IFERROR(Q64/Q61,"") -> 0.26721417
B68: Small Commercial unit sales | C68: GWh | D68: ='Historical Dataset'!F42 -> 1201 | E68: ='Historical Dataset'!G42 -> 1222 | F68: ='Historical Dataset'!H42 -> 1250 | G68: ='Historical Dataset'!I42 -> 1262 | H68: ='Historical Dataset'!J42 -> 1326 | I68: ='Historical Dataset'!K42 -> 1474 | J68: ='Historical Dataset'!L42 -> 1504 | K68: ='Historical Dataset'!M42 -> 1526 | L68: ='Historical Dataset'!N42 -> 1710 | M68: =L68*(1+M69) -> 1798.6676 | N68: =M68*(1+N69) -> 1882.9394 | O68: =N68*(1+O69) -> 1961.7449 | P68: =O68*(1+P69) -> 2034.0398 | Q68: =P68*(1+Q69) -> 2098.8288
B69: YoY growth | C69: % | E69: =IFERROR(E68/D68-1,"") -> 0.017485429 | F69: =IFERROR(F68/E68-1,"") -> 0.022913257 | G69: =IFERROR(G68/F68-1,"") -> 0.0096 | H69: =IFERROR(H68/G68-1,"") -> 0.050713154 | I69: =IFERROR(I68/H68-1,"") -> 0.11161388 | J69: =IFERROR(J68/I68-1,"") -> 0.020352782 | K69: =IFERROR(K68/J68-1,"") -> 0.01462766 | L69: =IFERROR(L68/K68-1,"") -> 0.12057667 | M69: =IFERROR(MAX(MIN(AVERAGE(J69:L69),D34),D33),0) -> 0.051852371 | N69: =MAX(MIN(M69-D35,D34),D33) -> 0.046852371 | O69: =MAX(MIN(N69-D35,D34),D33) -> 0.041852371 | P69: =MAX(MIN(O69-D35,D34),D33) -> 0.036852371 | Q69: =MAX(MIN(P69-D35,D34),D33) -> 0.031852371
B70: % of total units | C70: % | D70: =IFERROR(D68/D61,"") -> 0.1459118 | E70: =IFERROR(E68/E61,"") -> 0.14504451 | F70: =IFERROR(F68/F61,"") -> 0.14256387 | G70: =IFERROR(G68/G61,"") -> 0.14381766 | H70: =IFERROR(H68/H61,"") -> 0.14408345 | I70: =IFERROR(I68/I61,"") -> 0.1501936 | J70: =IFERROR(J68/J61,"") -> 0.14698984 | K70: =IFERROR(K68/K61,"") -> 0.1451089 | ... Q70: =IFERROR(Q68/Q61,"") -> 0.15183448
B72: Commercial & Industrial unit sales | C72: GWh | D72: ='Historical Dataset'!F45 -> 4266 | E72: ='Historical Dataset'!G45 -> 4225 | F72: ='Historical Dataset'!H45 -> 4462 | G72: ='Historical Dataset'!I45 -> 4308 | H72: ='Historical Dataset'!J45 -> 4514 | I72: ='Historical Dataset'!K45 -> 4851 | J72: ='Historical Dataset'!L45 -> 5137 | K72: ='Historical Dataset'!M45 -> 5415 | L72: ='Historical Dataset'!N45 -> 5603 | M72: =L72*(1+M73) -> 5879.0271 | N72: =M72*(1+N73) -> 6139.2573 | O72: =N72*(1+O73) -> 6380.3101 | P72: =O72*(1+P73) -> 6598.926 | Q72: =P72*(1+Q73) -> 6792.0381
B73: YoY growth | C73: % | E73: =IFERROR(E72/D72-1,"") -> -0.0096108767 | F73: =IFERROR(F72/E72-1,"") -> 0.056094675 | G73: =IFERROR(G72/F72-1,"") -> -0.034513671 | H73: =IFERROR(H72/G72-1,"") -> 0.047818013 | I73: =IFERROR(I72/H72-1,"") -> 0.074656624 | J73: =IFERROR(J72/I72-1,"") -> 0.058956916 | K73: =IFERROR(K72/J72-1,"") -> 0.054117189 | L73: =IFERROR(L72/K72-1,"") -> 0.034718375 | M73: =IFERROR(MAX(MIN(AVERAGE(J73:L73),D34),D33),0) -> 0.04926416 | N73: =MAX(MIN(M73-D35,D34),D33) -> 0.04426416 | O73: =MAX(MIN(N73-D35,D34),D33) -> 0.03926416 | P73: =MAX(MIN(O73-D35,D34),D33) -> 0.03426416 | Q73: =MAX(MIN(P73-D35,D34),D33) -> 0.02926416
B74: % of total units | C74: % | D74: =IFERROR(D72/D61,"") -> 0.51828453 | E74: =IFERROR(E72/E61,"") -> 0.50148368 | F74: =IFERROR(F72/F61,"") -> 0.50889599 | G74: =IFERROR(G72/G61,"") -> 0.49094017 | H74: =IFERROR(H72/H61,"") -> 0.49049223 | I74: =IFERROR(I72/I61,"") -> 0.49429387 | J74: =IFERROR(J72/J61,"") -> 0.50205238 | K74: =IFERROR(K72/K61,"") -> 0.51491788 | ... Q74: =IFERROR(Q72/Q61,"") -> 0.49135286
B76: Street Lighting unit sales | C76: GWh | D76: ='Historical Dataset'!F48 -> 55 | E76: ='Historical Dataset'!G48 -> 66 | F76: ='Historical Dataset'!H48 -> 68 | G76: ='Historical Dataset'!I48 -> 76 | H76: ='Historical Dataset'!J48 -> 84 | I76: ='Historical Dataset'!K48 -> 95 | J76: ='Historical Dataset'!L48 -> 99 | K76: ='Historical Dataset'!M48 -> 102 | L76: ='Historical Dataset'!N48 -> 148 | M76: =L76*(1+M77) -> 156.88 | N76: =M76*(1+N77) -> 165.5084 | O76: =N76*(1+O77) -> 173.78382 | P76: =O76*(1+P77) -> 181.60409 | Q76: =P76*(1+Q77) -> 188.86826
B77: YoY growth | C77: % | E77: =IFERROR(E76/D76-1,"") -> 0.2 | F77: =IFERROR(F76/E76-1,"") -> 0.03030303 | G77: =IFERROR(G76/F76-1,"") -> 0.11764706 | H77: =IFERROR(H76/G76-1,"") -> 0.10526316 | I77: =IFERROR(I76/H76-1,"") -> 0.13095238 | J77: =IFERROR(J76/I76-1,"") -> 0.042105263 | K77: =IFERROR(K76/J76-1,"") -> 0.03030303 | L77: =IFERROR(L76/K76-1,"") -> 0.45098039 | M77: =IFERROR(MAX(MIN(AVERAGE(J77:L77),D34),D33),0) -> 0.06 | N77: =MAX(MIN(M77-D35,D34),D33) -> 0.055 | O77: =MAX(MIN(N77-D35,D34),D33) -> 0.05 | P77: =MAX(MIN(O77-D35,D34),D33) -> 0.045 | Q77: =MAX(MIN(P77-D35,D34),D33) -> 0.04
B78: % of total units | C78: % | D78: =IFERROR(D76/D61,"") -> 0.0066820556 | E78: =IFERROR(E76/E61,"") -> 0.0078338279 | F78: =IFERROR(F76/F61,"") -> 0.0077554745 | G78: =IFERROR(G76/G61,"") -> 0.0086609687 | H78: =IFERROR(H76/H61,"") -> 0.0091274584 | I78: =IFERROR(I76/I61,"") -> 0.0096800489 | J78: =IFERROR(J76/J61,"") -> 0.0096755278 | K78: =IFERROR(K76/K61,"") -> 0.0096992842 | ... Q78: =IFERROR(Q76/Q61,"") -> 0.013663198
B80: E-Mobility unit sales | C80: GWh | D80: ='Historical Dataset'!F51 -> 0 | E80: ='Historical Dataset'!G51 -> 0 | F80: ='Historical Dataset'!H51 -> 0 | G80: ='Historical Dataset'!I51 -> 0 | H80: ='Historical Dataset'!J51 -> 0 | I80: ='Historical Dataset'!K51 -> 0 | J80: ='Historical Dataset'!L51 -> 0 | K80: ='Historical Dataset'!M51 -> 1.24 | L80: ='Historical Dataset'!N51 -> 4.88 | M80: =L80*(1+M81) -> 5.1728 | N80: =M80*(1+N81) -> 5.457304 | O80: =N80*(1+O81) -> 5.7301692 | P80: =O80*(1+P81) -> 5.9880268 | Q80: =P80*(1+Q81) -> 6.2275479
B81: YoY growth | C81: % | E81: =IFERROR(E80/D80-1,"") | F81: =IFERROR(F80/E80-1,"") | G81: =IFERROR(G80/F80-1,"") | H81: =IFERROR(H80/G80-1,"") | I81: =IFERROR(I80/H80-1,"") | J81: =IFERROR(J80/I80-1,"") | K81: =IFERROR(K80/J80-1,"") | L81: =IFERROR(L80/K80-1,"") -> 2.9354839 | M81: =IFERROR(MAX(MIN(AVERAGE(J81:L81),D34),D33),0) -> 0.06 | N81: =MAX(MIN(M81-D35,D34),D33) -> 0.055 | O81: =MAX(MIN(N81-D35,D34),D33) -> 0.05 | P81: =MAX(MIN(O81-D35,D34),D33) -> 0.045 | Q81: =MAX(MIN(P81-D35,D34),D33) -> 0.04
B82: % of total units | C82: % | D82: =IFERROR(D80/D61,"") -> 0 | E82: =IFERROR(E80/E61,"") -> 0 | F82: =IFERROR(F80/F61,"") -> 0 | G82: =IFERROR(G80/G61,"") -> 0 | H82: =IFERROR(H80/H61,"") -> 0 | I82: =IFERROR(I80/I61,"") -> 0 | J82: =IFERROR(J80/J61,"") -> 0 | K82: =IFERROR(K80/K61,"") -> 0.00011791287 | ... Q82: =IFERROR(Q80/Q61,"") -> 0.00045051624
B84: Export unit sales | C84: GWh | D84: ='Historical Dataset'!F36 -> 22 | E84: ='Historical Dataset'!G36 -> 23 | F84: ='Historical Dataset'!H36 -> 27 | G84: ='Historical Dataset'!I36 -> 18 | H84: ='Historical Dataset'!J36 -> 17 | I84: ='Historical Dataset'!K36 -> 16 | J84: ='Historical Dataset'!L36 -> 27 | K84: ='Historical Dataset'!M36 -> 43 | L84: ='Historical Dataset'!N36 -> 73 | M84: =L84*(1+M85) -> 77.38 | N84: =M84*(1+N85) -> 81.6359 | O84: =N84*(1+O85) -> 85.717695 | P84: =O84*(1+P85) -> 89.574991 | Q84: =P84*(1+Q85) -> 93.157991
B85: YoY growth | C85: % | E85: =IFERROR(E84/D84-1,"") -> 0.045454545 | F85: =IFERROR(F84/E84-1,"") -> 0.17391304 | G85: =IFERROR(G84/F84-1,"") -> -0.33333333 | H85: =IFERROR(H84/G84-1,"") -> -0.055555556 | I85: =IFERROR(I84/H84-1,"") -> -0.058823529 | J85: =IFERROR(J84/I84-1,"") -> 0.6875 | K85: =IFERROR(K84/J84-1,"") -> 0.59259259 | L85: =IFERROR(L84/K84-1,"") -> 0.69767442 | M85: =IFERROR(MAX(MIN(AVERAGE(J85:L85),D34),D33),0) -> 0.06 | N85: =MAX(MIN(M85-D35,D34),D33) -> 0.055 | O85: =MAX(MIN(N85-D35,D34),D33) -> 0.05 | P85: =MAX(MIN(O85-D35,D34),D33) -> 0.045 | Q85: =MAX(MIN(P85-D35,D34),D33) -> 0.04
B86: % of total units | C86: % | D86: =IFERROR(D84/D61,"") -> 0.0026728223 | E86: =IFERROR(E84/E61,"") -> 0.0027299703 | F86: =IFERROR(F84/F61,"") -> 0.0030793796 | G86: =IFERROR(G84/G61,"") -> 0.0020512821 | H86: =IFERROR(H84/H61,"") -> 0.0018472237 | I86: =IFERROR(I84/I61,"") -> 0.001630324 | J86: =IFERROR(J84/J61,"") -> 0.0026387803 | K86: =IFERROR(K84/K61,"") -> 0.0040889139 | ... Q86: =IFERROR(Q84/Q61,"") -> 0.0067392799
B88: REP / Rural Electrification Programme (memo) unit sales | C88: GWh | D88: ='Historical Dataset'!F33 -> 549 | E88: ='Historical Dataset'!G33 -> 554 | F88: ='Historical Dataset'!H33 -> 595 | G88: ='Historical Dataset'!I33 -> 603 | H88: ='Historical Dataset'!J33 -> 632 | I88: ='Historical Dataset'!K33 -> 650 | J88: ='Historical Dataset'!L33 -> 667 | K88: ='Historical Dataset'!M33 -> 660 | L88: ='Historical Dataset'!N33 -> 760 | M88: =L88*(1+M89) -> 802.35081 | N88: =M88*(1+N89) -> 843.04985 | O88: =N88*(1+O89) -> 881.59809 | P88: =O88*(1+P89) -> 917.50095 | Q88: =P88*(1+Q89) -> 950.27845
B89: YoY growth | C89: % | E89: =IFERROR(E88/D88-1,"") -> 0.0091074681 | F89: =IFERROR(F88/E88-1,"") -> 0.07400722 | G89: =IFERROR(G88/F88-1,"") -> 0.013445378 | H89: =IFERROR(H88/G88-1,"") -> 0.048092869 | I89: =IFERROR(I88/H88-1,"") -> 0.028481013 | J89: =IFERROR(J88/I88-1,"") -> 0.026153846 | K89: =IFERROR(K88/J88-1,"") -> -0.010494753 | L89: =IFERROR(L88/K88-1,"") -> 0.15151515 | M89: =IFERROR(MAX(MIN(AVERAGE(J89:L89),D34),D33),0) -> 0.055724748 | N89: =MAX(MIN(M89-D35,D34),D33) -> 0.050724748 | O89: =MAX(MIN(N89-D35,D34),D33) -> 0.045724748 | P89: =MAX(MIN(O89-D35,D34),D33) -> 0.040724748 | Q89: =MAX(MIN(P89-D35,D34),D33) -> 0.035724748
B90: % of total units | C90: % | D90: =IFERROR(D88/D61,"") -> 0.066699065 | E90: =IFERROR(E88/E61,"") -> 0.065756677 | F90: =IFERROR(F88/F61,"") -> 0.067860401 | G90: =IFERROR(G88/G61,"") -> 0.068717949 | H90: =IFERROR(H88/H61,"") -> 0.068673259 | I90: =IFERROR(I88/I61,"") -> 0.066231914 | J90: =IFERROR(J88/J61,"") -> 0.065187647 | K90: =IFERROR(K88/K61,"") -> 0.062760074 | ... Q90: =IFERROR(Q88/Q61,"") -> 0.068745497
B91: % of Total Sales | M91: =SUM(M66,M70,M74,M78,M82,M86,M90) -> 1 | N91: =SUM(N66,N70,N74,N78,N82,N86,N90) -> 1 | O91: =SUM(O66,O70,O74,O78,O82,O86,O90) -> 1 | P91: =SUM(P66,P70,P74,P78,P82,P86,P90) -> 1 | Q91: =SUM(Q66,Q70,Q74,Q78,Q82,Q86,Q90) -> 1
B93: Revenue by customer category and effective average price per kWh | D93: 43100 | E93: =EOMONTH(D93,12) -> 43465 | F93: =EOMONTH(E93,12) -> 43830 | G93: =EOMONTH(F93,12) -> 44196 | H93: =EOMONTH(G93,12) -> 44561 | I93: =EOMONTH(H93,12) -> 44926 | J93: =EOMONTH(I93,12) -> 45291 | K93: =EOMONTH(J93,12) -> 45657 | L93: =EOMONTH(K93,12) -> 46022 | ... Q93: =EOMONTH(P93,12) -> 47848
B94: Line item | C94: Unit | D94: 2017 | E94: 2018 | F94: 2019 | G94: 2020 | H94: 2021 | I94: 2022 | J94: 2023 | K94: 2024 | L94: 2025 | M94: 2026F | N94: 2027F | O94: 2028F | P94: 2029F | Q94: 2030F
B95: KPLC CUSTOMER REVENUE FROM CONTRACTS (ex REP) | C95: KSh mn | D95: =D98+D104+D110+D116+D122+D128 -> 120117 | E95: =E98+E104+E110+E116+E122+E128 -> 125463 | F95: =F98+F104+F110+F116+F122+F128 -> 133094 | G95: =G98+G104+G110+G116+G122+G128 -> 133259 | H95: =H98+H104+H110+H116+H122+H128 -> 144120 | I95: =I98+I104+I110+I116+I122+I128 -> 157354 | J95: =J98+J104+J110+J116+J122+J128 -> 190974 | K95: =K98+K104+K110+K116+K122+K128 -> 231123 | ... Q95: =Q98+Q104+Q110+Q116+Q122+Q128 -> 299778.01
B96: YoY growth | C96: % | E96: =IFERROR(E95/D95-1,"") -> 0.044506606 | F96: =IFERROR(F95/E95-1,"") -> 0.060822713 | G96: =IFERROR(G95/F95-1,"") -> 0.0012397253 | H96: =IFERROR(H95/G95-1,"") -> 0.081502938 | I96: =IFERROR(I95/H95-1,"") -> 0.091826256 | J96: =IFERROR(J95/I95-1,"") -> 0.21365838 | K96: =IFERROR(K95/J95-1,"") -> 0.21023281 | L96: =IFERROR(L95/K95-1,"") -> -0.051223807 | ... Q96: =IFERROR(Q95/P95-1,"") -> 0.049186907
B98: Domestic revenue | C98: KSh mn | D98: ='Historical Dataset'!F72 -> 38064 | E98: ='Historical Dataset'!G72 -> 38066 | F98: ='Historical Dataset'!H72 -> 38706 | G98: ='Historical Dataset'!I72 -> 43916 | H98: ='Historical Dataset'!J72 -> 43210 | I98: ='Historical Dataset'!K72 -> 46105 | J98: ='Historical Dataset'!L72 -> 57057 | K98: ='Historical Dataset'!M72 -> 69155 | L98: ='Historical Dataset'!N72 -> 68189 | M98: =M64*M101 -> 73425.14 | N98: =N64*N101 -> 78494.234 | O98: =O64*O101 -> 83306.834 | P98: =P64*P101 -> 87772.95 | Q98: =Q64*Q101 -> 91804.746
B99: YoY growth | C99: % | E99: =IFERROR(E98/D98-1,"") -> 5.2543085e-05 | F99: =IFERROR(F98/E98-1,"") -> 0.016812904 | G99: =IFERROR(G98/F98-1,"") -> 0.13460445 | H99: =IFERROR(H98/G98-1,"") -> -0.016076145 | I99: =IFERROR(I98/H98-1,"") -> 0.06699838 | J99: =IFERROR(J98/I98-1,"") -> 0.23754473 | K99: =IFERROR(K98/J98-1,"") -> 0.21203358 | L99: =IFERROR(L98/K98-1,"") -> -0.013968621 | ... Q99: =IFERROR(Q98/P98-1,"") -> 0.045934378
B100: % of KPLC revenue | C100: % | D100: =IFERROR(D98/D95,"") -> 0.31689103 | E100: =IFERROR(E98/E95,"") -> 0.30340419 | F100: =IFERROR(F98/F95,"") -> 0.29081702 | G100: =IFERROR(G98/G95,"") -> 0.32955373 | H100: =IFERROR(H98/H95,"") -> 0.29981959 | I100: =IFERROR(I98/I95,"") -> 0.29300177 | J100: =IFERROR(J98/J95,"") -> 0.29876842 | K100: =IFERROR(K98/K95,"") -> 0.29921297 | ... Q100: =IFERROR(Q98/Q95,"") -> 0.30624243
B101: Effective average price per kWh — Domestic | C101: KSh/kWh | D101: =IFERROR(D98/D64,"") -> 17.803555 | E101: =IFERROR(E98/E64,"") -> 16.302355 | F101: =IFERROR(F98/F64,"") -> 16.359256 | G101: =IFERROR(G98/G64,"") -> 17.510367 | H101: =IFERROR(H98/H64,"") -> 16.429658 | I101: =IFERROR(I98/I64,"") -> 16.90066 | J101: =IFERROR(J98/J64,"") -> 20.392066 | K101: =IFERROR(K98/K64,"") -> 24.97472 | L101: =IFERROR(L98/L64,"") -> 21.968106 | M101: =L101*(1+M102) -> 22.627149 | N101: =M101*(1+N102) -> 23.249395 | O101: =N101*(1+O102) -> 23.83063 | P101: =O101*(1+P102) -> 24.36682 | Q101: =P101*(1+Q102) -> 24.854156
B102: Effective price growth | C102: % | E102: =IFERROR(E101/D101-1,"") -> -0.084320198 | F102: =IFERROR(F101/E101-1,"") -> 0.0034903342 | G102: =IFERROR(G101/F101-1,"") -> 0.070364489 | H102: =IFERROR(H101/G101-1,"") -> -0.061718241 | I102: =IFERROR(I101/H101-1,"") -> 0.028667793 | J102: =IFERROR(J101/I101-1,"") -> 0.206584 | K102: =IFERROR(K101/J101-1,"") -> 0.22472732 | L102: =IFERROR(L101/K101-1,"") -> -0.12038631 | M102: =IFERROR(MAX(MIN(AVERAGE(J102:L102),D37),D36),0) -> 0.03 | N102: =MAX(MIN(M102-D38,D37),D36) -> 0.0275 | O102: =MAX(MIN(N102-D38,D37),D36) -> 0.025 | P102: =MAX(MIN(O102-D38,D37),D36) -> 0.0225 | Q102: =MAX(MIN(P102-D38,D37),D36) -> 0.02
B104: Small Commercial revenue | C104: KSh mn | D104: ='Historical Dataset'!F73 -> 25590 | E104: ='Historical Dataset'!G73 -> 26995 | F104: ='Historical Dataset'!H73 -> 29314 | G104: ='Historical Dataset'!I73 -> 25553 | H104: ='Historical Dataset'!J73 -> 25953 | I104: ='Historical Dataset'!K73 -> 29799 | J104: ='Historical Dataset'!L73 -> 34811 | K104: ='Historical Dataset'!M73 -> 41998 | L104: ='Historical Dataset'!N73 -> 41715 | M104: =M68*M107 -> 45194.362 | N104: =N68*N107 -> 48612.901 | O104: =O68*O107 -> 51913.652 | P104: =P68*P107 -> 55037.896 | Q104: =Q68*Q107 -> 57926.803
B105: YoY growth | C105: % | E105: =IFERROR(E104/D104-1,"") -> 0.054904259 | F105: =IFERROR(F104/E104-1,"") -> 0.085904797 | G105: =IFERROR(G104/F104-1,"") -> -0.12830047 | H105: =IFERROR(H104/G104-1,"") -> 0.015653739 | I105: =IFERROR(I104/H104-1,"") -> 0.14819096 | J105: =IFERROR(J104/I104-1,"") -> 0.16819356 | K105: =IFERROR(K104/J104-1,"") -> 0.20645773 | L105: =IFERROR(L104/K104-1,"") -> -0.0067384161 | ... Q105: =IFERROR(Q104/P104-1,"") -> 0.052489418
B106: % of KPLC revenue | C106: % | D106: =IFERROR(D104/D95,"") -> 0.21304228 | E106: =IFERROR(E104/E95,"") -> 0.21516304 | F106: =IFERROR(F104/F95,"") -> 0.22025035 | G106: =IFERROR(G104/G95,"") -> 0.1917544 | H106: =IFERROR(H104/H95,"") -> 0.1800791 | I106: =IFERROR(I104/I95,"") -> 0.18937555 | J106: =IFERROR(J104/J95,"") -> 0.18228136 | K106: =IFERROR(K104/K95,"") -> 0.18171277 | ... Q106: =IFERROR(Q104/Q95,"") -> 0.19323233
B107: Effective average price per kWh — Small Commercial | C107: KSh/kWh | D107: =IFERROR(D104/D68,"") -> 21.307244 | E107: =IFERROR(E104/E68,"") -> 22.090835 | F107: =IFERROR(F104/F68,"") -> 23.4512 | G107: =IFERROR(G104/G68,"") -> 20.248019 | H107: =IFERROR(H104/H68,"") -> 19.572398 | I107: =IFERROR(I104/I68,"") -> 20.216418 | J107: =IFERROR(J104/J68,"") -> 23.145612 | K107: =IFERROR(K104/K68,"") -> 27.521625 | L107: =IFERROR(L104/L68,"") -> 24.394737 | M107: =L107*(1+M108) -> 25.126579 | N107: =M107*(1+N108) -> 25.81756 | O107: =N107*(1+O108) -> 26.462999 | P107: =O107*(1+P108) -> 27.058416 | Q107: =P107*(1+Q108) -> 27.599585
B108: Effective price growth | C108: % | E108: =IFERROR(E107/D107-1,"") -> 0.03677579 | F108: =IFERROR(F107/E107-1,"") -> 0.06158053 | G108: =IFERROR(G107/F107-1,"") -> -0.13658921 | H108: =IFERROR(H107/G107-1,"") -> -0.033367256 | I108: =IFERROR(I107/H107-1,"") -> 0.032904487 | J108: =IFERROR(J107/I107-1,"") -> 0.14489183 | K108: =IFERROR(K107/J107-1,"") -> 0.1890645 | L108: =IFERROR(L107/K107-1,"") -> -0.11361569 | M108: =IFERROR(MAX(MIN(AVERAGE(J108:L108),D37),D36),0) -> 0.03 | N108: =MAX(MIN(M108-D38,D37),D36) -> 0.0275 | O108: =MAX(MIN(N108-D38,D37),D36) -> 0.025 | P108: =MAX(MIN(O108-D38,D37),D36) -> 0.0225 | Q108: =MAX(MIN(P108-D38,D37),D36) -> 0.02
B110: Commercial & Industrial revenue | C110: KSh mn | D110: ='Historical Dataset'!F74 -> 55706 | E110: ='Historical Dataset'!G74 -> 59528 | F110: ='Historical Dataset'!H74 -> 63870 | G110: ='Historical Dataset'!I74 -> 62818 | H110: ='Historical Dataset'!J74 -> 73887 | I110: ='Historical Dataset'!K74 -> 80261 | J110: ='Historical Dataset'!L74 -> 97596 | K110: ='Historical Dataset'!M74 -> 117692 | L110: ='Historical Dataset'!N74 -> 106493 | M110: =M72*M113 -> 115091.47 | N110: =N72*N113 -> 123491.01 | O110: =O72*O113 -> 131548.27 | P110: =P72*P113 -> 139116.91 | Q110: =Q72*Q113 -> 146051.82
B111: YoY growth | C111: % | E111: =IFERROR(E110/D110-1,"") -> 0.068610204 | F111: =IFERROR(F110/E110-1,"") -> 0.072940465 | G111: =IFERROR(G110/F110-1,"") -> -0.016470957 | H111: =IFERROR(H110/G110-1,"") -> 0.17620746 | I111: =IFERROR(I110/H110-1,"") -> 0.086266867 | J111: =IFERROR(J110/I110-1,"") -> 0.21598286 | K111: =IFERROR(K110/J110-1,"") -> 0.20591008 | L111: =IFERROR(L110/K110-1,"") -> -0.095155151 | ... Q111: =IFERROR(Q110/P110-1,"") -> 0.049849443
B112: % of KPLC revenue | C112: % | D112: =IFERROR(D110/D95,"") -> 0.4637645 | E112: =IFERROR(E110/E95,"") -> 0.47446658 | F112: =IFERROR(F110/F95,"") -> 0.4798864 | G112: =IFERROR(G110/G95,"") -> 0.4713978 | H112: =IFERROR(H110/H95,"") -> 0.51267694 | I112: =IFERROR(I110/I95,"") -> 0.51006647 | J112: =IFERROR(J110/J95,"") -> 0.51104339 | K112: =IFERROR(K110/K95,"") -> 0.50921804 | ... Q112: =IFERROR(Q110/Q95,"") -> 0.4871999
B113: Effective average price per kWh —Commercial & Industrial | C113: KSh/kWh | D113: =IFERROR(D110/D72,"") -> 13.058134 | E113: =IFERROR(E110/E72,"") -> 14.089467 | F113: =IFERROR(F110/F72,"") -> 14.314209 | G113: =IFERROR(G110/G72,"") -> 14.581708 | H113: =IFERROR(H110/H72,"") -> 16.368409 | I113: =IFERROR(I110/I72,"") -> 16.545248 | J113: =IFERROR(J110/J72,"") -> 18.998637 | K113: =IFERROR(K110/K72,"") -> 21.734441 | L113: =IFERROR(L110/L72,"") -> 19.006425 | M113: =L113*(1+M114) -> 19.576618 | N113: =M113*(1+N114) -> 20.114975 | O113: =N113*(1+O114) -> 20.617849 | P113: =O113*(1+P114) -> 21.081751 | Q113: =P113*(1+Q114) -> 21.503386
B114: Effective price growth | C114: % | E114: =IFERROR(E113/D113-1,"") -> 0.078980149 | F114: =IFERROR(F113/E113-1,"") -> 0.015951023 | G114: =IFERROR(G113/F113-1,"") -> 0.018687695 | H114: =IFERROR(H113/G113-1,"") -> 0.12253029 | I114: =IFERROR(I113/H113-1,"") -> 0.010803677 | J114: =IFERROR(J113/I113-1,"") -> 0.1482836 | K114: =IFERROR(K113/J113-1,"") -> 0.14400001 | L114: =IFERROR(L113/K113-1,"") -> -0.12551582 | M114: =IFERROR(MAX(MIN(AVERAGE(J114:L114),D37),D36),0) -> 0.03 | N114: =MAX(MIN(M114-D38,D37),D36) -> 0.0275 | O114: =MAX(MIN(N114-D38,D37),D36) -> 0.025 | P114: =MAX(MIN(O114-D38,D37),D36) -> 0.0225 | Q114: =MAX(MIN(P114-D38,D37),D36) -> 0.02
...

Sheet Rev Cost Analytics
A1: Revenue & Cost Structure Analytics
A3: FY2025 income statement snapshot
A4: Metric | B4: KSh mn | C4: % / margin | D4: Formula basis
A5: Revenue from contracts with customers | B5: ='Historical Dataset'!N114 -> 219284.57 | C5: =B5/$B$5 -> 1 | D5: P&L revenue total
A6: Other income | B6: ='Historical Dataset'!N119 -> 7266.559 | C6: =B6/$B$5 -> 0.033137576 | D6: Other income / revenue
A7: Cost of sales | B7: ='Historical Dataset'!N115 -> -144663.61 | C7: =ABS(B7)/$B$5 -> 0.65970718 | D7: Cost burden / revenue
A8: Gross profit | B8: ='Historical Dataset'!N116 -> 74620.963 | C8: =B8/$B$5 -> 0.34029282 | D8: Gross profit / revenue
A9: Total net operating expenses | B9: ='Historical Dataset'!N117 -> -42421.437 | C9: =ABS(B9)/$B$5 -> 0.19345382 | D9: Opex burden / revenue
A10: Operating profit | B10: ='Historical Dataset'!N120 -> 39466.085 | C10: =B10/$B$5 -> 0.17997657 | D10: Operating profit / revenue
A11: Profit for the year | B11: ='Historical Dataset'!N125 -> 24466.525 | C11: =B11/$B$5 -> 0.11157431 | D11: Net margin
A13: IFRS revenue component contribution — % of revenue from contracts
A14: Component | B14: Unit | C14: 2018 | D14: 2019 | E14: 2020 | F14: 2021 | G14: 2022 | H14: 2023 | I14: 2024 | J14: 2025 | K14: FY2025 value | L14: CAGR 2018–2025
A15: Post-paid electricity sales | B15: KSh mn | C15: =IFERROR('Historical Dataset'!G65/'Historical Dataset'!G$71,"") -> 0.62256336 | D15: =IFERROR('Historical Dataset'!H65/'Historical Dataset'!H$71,"") -> 0.71918848 | E15: =IFERROR('Historical Dataset'!I65/'Historical Dataset'!I$71,"") -> 0.7380734 | F15: =IFERROR('Historical Dataset'!J65/'Historical Dataset'!J$71,"") -> 0.73988746 | G15: =IFERROR('Historical Dataset'!K65/'Historical Dataset'!K$71,"") -> 0.68130949 | H15: =IFERROR('Historical Dataset'!L65/'Historical Dataset'!L$71,"") -> 0.62932873 | I15: =IFERROR('Historical Dataset'!M65/'Historical Dataset'!M$71,"") -> 0.65319648 | J15: =IFERROR('Historical Dataset'!N65/'Historical Dataset'!N$71,"") -> 0.66812137 | K15: ='Historical Dataset'!N65 -> 146508.7 | L15: =IFERROR(IF(AND('Historical Dataset'!G65>0,'Historical Dataset'!N65>0),('Historical Dataset'!N65/'Historical Dataset'!G65)^(1/7)-1,""),"") -> 0.08683811
A16: Prepaid electricity sales | B16: KSh mn | C16: =IFERROR('Historical Dataset'!G66/'Historical Dataset'!G$71,"") -> 0.10384564 | D16: =IFERROR('Historical Dataset'!H66/'Historical Dataset'!H$71,"") -> 0.12524922 | E16: =IFERROR('Historical Dataset'!I66/'Historical Dataset'!I$71,"") -> 0.13370885 | F16: =IFERROR('Historical Dataset'!J66/'Historical Dataset'!J$71,"") -> 0.14278653 | G16: =IFERROR('Historical Dataset'!K66/'Historical Dataset'!K$71,"") -> 0.12498362 | H16: =IFERROR('Historical Dataset'!L66/'Historical Dataset'!L$71,"") -> 0.12657248 | I16: =IFERROR('Historical Dataset'!M66/'Historical Dataset'!M$71,"") -> 0.14839613 | J16: =IFERROR('Historical Dataset'!N66/'Historical Dataset'!N$71,"") -> 0.17131029 | K16: ='Historical Dataset'!N66 -> 37565.704 | L16: =IFERROR(IF(AND('Historical Dataset'!G66>0,'Historical Dataset'!N66>0),('Historical Dataset'!N66/'Historical Dataset'!G66)^(1/7)-1,""),"") -> 0.1556854
A17: Foreign exchange adjustment | B17: KSh mn | C17: =IFERROR('Historical Dataset'!G68/'Historical Dataset'!G$71,"") -> 0.070956522 | D17: =IFERROR('Historical Dataset'!H68/'Historical Dataset'!H$71,"") -> 0.0064569947 | E17: =IFERROR('Historical Dataset'!I68/'Historical Dataset'!I$71,"") -> 0.0069312449 | F17: =IFERROR('Historical Dataset'!J68/'Historical Dataset'!J$71,"") -> 0.043943119 | G17: =IFERROR('Historical Dataset'!K68/'Historical Dataset'!K$71,"") -> 0.046535955 | H17: =IFERROR('Historical Dataset'!L68/'Historical Dataset'!L$71,"") -> 0.073420167 | I17: =IFERROR('Historical Dataset'!M68/'Historical Dataset'!M$71,"") -> 0.10357323 | J17: =IFERROR('Historical Dataset'!N68/'Historical Dataset'!N$71,"") -> 0.0474847 | K17: ='Historical Dataset'!N68 -> 10412.662 | L17: =IFERROR(IF(AND('Historical Dataset'!G68>0,'Historical Dataset'!N68>0),('Historical Dataset'!N68/'Historical Dataset'!G68)^(1/7)-1,""),"") -> 0.015929028
A18: Fuel cost charge / fuel cost recovery | B18: KSh mn | C18: =IFERROR('Historical Dataset'!G69/'Historical Dataset'!G$71,"") -> 0.20263448 | D18: =IFERROR('Historical Dataset'!H69/'Historical Dataset'!H$71,"") -> 0.14910531 | E18: =IFERROR('Historical Dataset'!I69/'Historical Dataset'!I$71,"") -> 0.1212865 | F18: =IFERROR('Historical Dataset'!J69/'Historical Dataset'!J$71,"") -> 0.08229065 | G18: =IFERROR('Historical Dataset'!K69/'Historical Dataset'!K$71,"") -> 0.15536113 | H18: =IFERROR('Historical Dataset'!L69/'Historical Dataset'!L$71,"") -> 0.1788457 | I18: =IFERROR('Historical Dataset'!M69/'Historical Dataset'!M$71,"") -> 0.10510419 | J18: =IFERROR('Historical Dataset'!N69/'Historical Dataset'!N$71,"") -> 0.12389823 | K18: ='Historical Dataset'!N69 -> 27168.969 | L18: =IFERROR(IF(AND('Historical Dataset'!G69>0,'Historical Dataset'!N69>0),('Historical Dataset'!N69/'Historical Dataset'!G69)^(1/7)-1,""),"") -> 0.0029100711
A19: Revenue apportioned to RES | B19: KSh mn | C19: =IFERROR('Historical Dataset'!G70/'Historical Dataset'!G$71,"") -> 0 | D19: =IFERROR('Historical Dataset'!H70/'Historical Dataset'!H$71,"") -> 0 | E19: =IFERROR('Historical Dataset'!I70/'Historical Dataset'!I$71,"") -> 0 | F19: =IFERROR('Historical Dataset'!J70/'Historical Dataset'!J$71,"") -> -0.008907761 | G19: =IFERROR('Historical Dataset'!K70/'Historical Dataset'!K$71,"") -> -0.0081901961 | H19: =IFERROR('Historical Dataset'!L70/'Historical Dataset'!L$71,"") -> -0.0081670814 | I19: =IFERROR('Historical Dataset'!M70/'Historical Dataset'!M$71,"") -> -0.010270037 | J19: =IFERROR('Historical Dataset'!N70/'Historical Dataset'!N$71,"") -> -0.010814587 | K19: ='Historical Dataset'!N70 -> -2371.472 | L19: =IFERROR(IF(AND('Historical Dataset'!G70>0,'Historical Dataset'!N70>0),('Historical Dataset'!N70/'Historical Dataset'!G70)^(1/7)-1,""),"")
A20: Total revenue from contracts | B20: KSh mn | C20: =IFERROR('Historical Dataset'!G71/'Historical Dataset'!G$71,"") -> 1 | D20: =IFERROR('Historical Dataset'!H71/'Historical Dataset'!H$71,"") -> 1 | E20: =IFERROR('Historical Dataset'!I71/'Historical Dataset'!I$71,"") -> 1 | F20: =IFERROR('Historical Dataset'!J71/'Historical Dataset'!J$71,"") -> 1 | G20: =IFERROR('Historical Dataset'!K71/'Historical Dataset'!K$71,"") -> 1 | H20: =IFERROR('Historical Dataset'!L71/'Historical Dataset'!L$71,"") -> 1 | I20: =IFERROR('Historical Dataset'!M71/'Historical Dataset'!M$71,"") -> 1 | J20: =IFERROR('Historical Dataset'!N71/'Historical Dataset'!N$71,"") -> 1 | K20: ='Historical Dataset'!N71 -> 219284.57 | L20: =IFERROR(IF(AND('Historical Dataset'!G71>0,'Historical Dataset'!N71>0),('Historical Dataset'!N71/'Historical Dataset'!G71)^(1/7)-1,""),"") -> 0.075927906
A22: Tariff category revenue mix — % of tariff category total
A23: Tariff category | B23: Unit | C23: 2017 | D23: 2018 | E23: 2019 | F23: 2020 | G23: 2021 | H23: 2022 | I23: 2023 | J23: 2024 | K23: 2025 | L23: FY2025 value
A24: Domestic revenue | B24: KSh mn | C24: =IFERROR('Historical Dataset'!F72/SUM('Historical Dataset'!F$72:F$78),"") -> 0.29169381 | D24: =IFERROR('Historical Dataset'!G72/SUM('Historical Dataset'!G$72:G$78),"") -> 0.27722873 | E24: =IFERROR('Historical Dataset'!H72/SUM('Historical Dataset'!H$72:H$78),"") -> 0.26904203 | F24: =IFERROR('Historical Dataset'!I72/SUM('Historical Dataset'!I$72:I$78),"") -> 0.30639782 | G24: =IFERROR('Historical Dataset'!J72/SUM('Historical Dataset'!J$72:J$78),"") -> 0.27969629 | H24: =IFERROR('Historical Dataset'!K72/SUM('Historical Dataset'!K$72:K$78),"") -> 0.2745898 | I24: =IFERROR('Historical Dataset'!L72/SUM('Historical Dataset'!L$72:L$78),"") -> 0.28045142 | J24: =IFERROR('Historical Dataset'!M72/SUM('Historical Dataset'!M$72:M$78),"") -> 0.28394347 | K24: =IFERROR('Historical Dataset'!N72/SUM('Historical Dataset'!N$72:N$78),"") -> 0.29481143 | L24: ='Historical Dataset'!N72 -> 68189
A25: Small commercial revenue | B25: KSh mn | C25: =IFERROR('Historical Dataset'!F73/SUM('Historical Dataset'!F$72:F$78),"") -> 0.19610247 | D25: =IFERROR('Historical Dataset'!G73/SUM('Historical Dataset'!G$72:G$78),"") -> 0.19660037 | E25: =IFERROR('Historical Dataset'!H73/SUM('Historical Dataset'!H$72:H$78),"") -> 0.20375905 | F25: =IFERROR('Historical Dataset'!I73/SUM('Historical Dataset'!I$72:I$78),"") -> 0.17828089 | G25: =IFERROR('Historical Dataset'!J73/SUM('Historical Dataset'!J$72:J$78),"") -> 0.16799254 | H25: =IFERROR('Historical Dataset'!K73/SUM('Historical Dataset'!K$72:K$78),"") -> 0.17747536 | I25: =IFERROR('Historical Dataset'!L73/SUM('Historical Dataset'!L$72:L$78),"") -> 0.17110599 | J25: =IFERROR('Historical Dataset'!M73/SUM('Historical Dataset'!M$72:M$78),"") -> 0.17243956 | K25: =IFERROR('Historical Dataset'!N73/SUM('Historical Dataset'!N$72:N$78),"") -> 0.18035253 | L25: ='Historical Dataset'!N73 -> 41715
A26: Commercial & industrial revenue | B26: KSh mn | C26: =IFERROR('Historical Dataset'!F74/SUM('Historical Dataset'!F$72:F$78),"") -> 0.4268888 | D26: =IFERROR('Historical Dataset'!G74/SUM('Historical Dataset'!G$72:G$78),"") -> 0.43353313 | E26: =IFERROR('Historical Dataset'!H74/SUM('Historical Dataset'!H$72:H$78),"") -> 0.44395479 | F26: =IFERROR('Historical Dataset'!I74/SUM('Historical Dataset'!I$72:I$78),"") -> 0.43827531 | G26: =IFERROR('Historical Dataset'!J74/SUM('Historical Dataset'!J$72:J$78),"") -> 0.47826706 | H26: =IFERROR('Historical Dataset'!K74/SUM('Historical Dataset'!K$72:K$78),"") -> 0.47801435 | I26: =IFERROR('Historical Dataset'!L74/SUM('Historical Dataset'!L$72:L$78),"") -> 0.47971216 | J26: =IFERROR('Historical Dataset'!M74/SUM('Historical Dataset'!M$72:M$78),"") -> 0.48323151 | K26: =IFERROR('Historical Dataset'!N74/SUM('Historical Dataset'!N$72:N$78),"") -> 0.46041669 | L26: ='Historical Dataset'!N74 -> 106493
A27: Street lighting revenue | B27: KSh mn | C27: =IFERROR('Historical Dataset'!F75/SUM('Historical Dataset'!F$72:F$78),"") -> 0.003172584 | D27: =IFERROR('Historical Dataset'!G75/SUM('Historical Dataset'!G$72:G$78),"") -> 0.0033792395 | E27: =IFERROR('Historical Dataset'!H75/SUM('Historical Dataset'!H$72:H$78),"") -> 0.0045737005 | F27: =IFERROR('Historical Dataset'!I75/SUM('Historical Dataset'!I$72:I$78),"") -> 0.0053443103 | G27: =IFERROR('Historical Dataset'!J75/SUM('Historical Dataset'!J$72:J$78),"") -> 0.0053142942 | H27: =IFERROR('Historical Dataset'!K75/SUM('Historical Dataset'!K$72:K$78),"") -> 0.0054971561 | I27: =IFERROR('Historical Dataset'!L75/SUM('Historical Dataset'!L$72:L$78),"") -> 0.0046596902 | J27: =IFERROR('Historical Dataset'!M75/SUM('Historical Dataset'!M$72:M$78),"") -> 0.0054115754 | K27: =IFERROR('Historical Dataset'!N75/SUM('Historical Dataset'!N$72:N$78),"") -> 0.0070904508 | L27: ='Historical Dataset'!N75 -> 1640
A28: E-mobility revenue | B28: KSh mn | C28: =IFERROR('Historical Dataset'!F76/SUM('Historical Dataset'!F$72:F$78),"") -> 0 | D28: =IFERROR('Historical Dataset'!G76/SUM('Historical Dataset'!G$72:G$78),"") -> 0 | E28: =IFERROR('Historical Dataset'!H76/SUM('Historical Dataset'!H$72:H$78),"") -> 0 | F28: =IFERROR('Historical Dataset'!I76/SUM('Historical Dataset'!I$72:I$78),"") -> 0 | G28: =IFERROR('Historical Dataset'!J76/SUM('Historical Dataset'!J$72:J$78),"") -> 0 | H28: =IFERROR('Historical Dataset'!K76/SUM('Historical Dataset'!K$72:K$78),"") -> 0 | I28: =IFERROR('Historical Dataset'!L76/SUM('Historical Dataset'!L$72:L$78),"") -> 0 | J28: =IFERROR('Historical Dataset'!M76/SUM('Historical Dataset'!M$72:M$78),"") -> 9.8541585e-05 | K28: =IFERROR('Historical Dataset'!N76/SUM('Historical Dataset'!N$72:N$78),"") -> 0.00036749288 | L28: ='Historical Dataset'!N76 -> 85
A29: Export revenue | B29: KSh mn | C29: =IFERROR('Historical Dataset'!F77/SUM('Historical Dataset'!F$72:F$78),"") -> 0.0026284935 | D29: =IFERROR('Historical Dataset'!G77/SUM('Historical Dataset'!G$72:G$78),"") -> 0.002985966 | E29: =IFERROR('Historical Dataset'!H77/SUM('Historical Dataset'!H$72:H$78),"") -> 0.0037951983 | F29: =IFERROR('Historical Dataset'!I77/SUM('Historical Dataset'!I$72:I$78),"") -> 0.0014372427 | G29: =IFERROR('Historical Dataset'!J77/SUM('Historical Dataset'!J$72:J$78),"") -> 0.0016117652 | H29: =IFERROR('Historical Dataset'!K77/SUM('Historical Dataset'!K$72:K$78),"") -> 0.0015842292 | I29: =IFERROR('Historical Dataset'!L77/SUM('Historical Dataset'!L$72:L$78),"") -> 0.0027623902 | J29: =IFERROR('Historical Dataset'!M77/SUM('Historical Dataset'!M$72:M$78),"") -> 0.0038431218 | K29: =IFERROR('Historical Dataset'!N77/SUM('Historical Dataset'!N$72:N$78),"") -> 0.0050238438 | L29: ='Historical Dataset'!N77 -> 1162
A30: REP revenue | B30: KSh mn | C30: =IFERROR('Historical Dataset'!F78/SUM('Historical Dataset'!F$72:F$78),"") -> 0.079513844 | D30: =IFERROR('Historical Dataset'!G78/SUM('Historical Dataset'!G$72:G$78),"") -> 0.086272568 | E30: =IFERROR('Historical Dataset'!H78/SUM('Historical Dataset'!H$72:H$78),"") -> 0.074875231 | F30: =IFERROR('Historical Dataset'!I78/SUM('Historical Dataset'!I$72:I$78),"") -> 0.070264425 | G30: =IFERROR('Historical Dataset'!J78/SUM('Historical Dataset'!J$72:J$78),"") -> 0.067118047 | H30: =IFERROR('Historical Dataset'!K78/SUM('Historical Dataset'!K$72:K$78),"") -> 0.062839105 | I30: =IFERROR('Historical Dataset'!L78/SUM('Historical Dataset'!L$72:L$78),"") -> 0.061308351 | J30: =IFERROR('Historical Dataset'!M78/SUM('Historical Dataset'!M$72:M$78),"") -> 0.051032223 | K30: =IFERROR('Historical Dataset'!N78/SUM('Historical Dataset'!N$72:N$78),"") -> 0.051937552 | L30: ='Historical Dataset'!N78 -> 12013
A31: Total tariff category revenue | B31: KSh mn | C31: =IFERROR(SUM('Historical Dataset'!F$72:F$78)/SUM('Historical Dataset'!F$72:F$78),"") -> 1 | D31: =IFERROR(SUM('Historical Dataset'!G$72:G$78)/SUM('Historical Dataset'!G$72:G$78),"") -> 1 | E31: =IFERROR(SUM('Historical Dataset'!H$72:H$78)/SUM('Historical Dataset'!H$72:H$78),"") -> 1 | F31: =IFERROR(SUM('Historical Dataset'!I$72:I$78)/SUM('Historical Dataset'!I$72:I$78),"") -> 1 | G31: =IFERROR(SUM('Historical Dataset'!J$72:J$78)/SUM('Historical Dataset'!J$72:J$78),"") -> 1 | H31: =IFERROR(SUM('Historical Dataset'!K$72:K$78)/SUM('Historical Dataset'!K$72:K$78),"") -> 1 | I31: =IFERROR(SUM('Historical Dataset'!L$72:L$78)/SUM('Historical Dataset'!L$72:L$78),"") -> 1 | J31: =IFERROR(SUM('Historical Dataset'!M$72:M$78)/SUM('Historical Dataset'!M$72:M$78),"") -> 1 | K31: =IFERROR(SUM('Historical Dataset'!N$72:N$78)/SUM('Historical Dataset'!N$72:N$78),"") -> 1 | L31: =SUM('Historical Dataset'!N$72:N$78) -> 231297
A33: Cost of sales structure — % contribution to total cost of sales
A34: Cost component | B34: Unit | C34: 2018 | D34: 2019 | E34: 2020 | F34: 2021 | G34: 2022 | H34: 2023 | I34: 2024 | J34: 2025 | K34: FY2025 value | L34: FY2025 % of revenue
A35: Renewable/non-fuel energy cost | B35: KSh mn | C35: =IFERROR('Historical Dataset'!G90/'Historical Dataset'!G$95,"") -> 0.62776136 | D35: =IFERROR('Historical Dataset'!H90/'Historical Dataset'!H$95,"") -> 0.78620334 | E35: =IFERROR('Historical Dataset'!I90/'Historical Dataset'!I$95,"") -> 0.850806 | F35: =IFERROR('Historical Dataset'!J90/'Historical Dataset'!J$95,"") -> 0.80701854 | G35: =IFERROR('Historical Dataset'!K90/'Historical Dataset'!K$95,"") -> 0.68732376 | H35: =IFERROR('Historical Dataset'!L90/'Historical Dataset'!L$95,"") -> 0.65074398 | I35: =IFERROR('Historical Dataset'!M90/'Historical Dataset'!M$95,"") -> 0.70625711 | J35: =IFERROR('Historical Dataset'!N90/'Historical Dataset'!N$95,"") -> 0.69147454 | K35: ='Historical Dataset'!N90 -> -100031.2 | L35: =IFERROR(ABS(K35)/'Historical Dataset'!N$71,"") -> 0.45617072
A36: Foreign exchange costs on power purchases | B36: KSh mn | C36: =IFERROR('Historical Dataset'!G91/'Historical Dataset'!G$95,"") -> 0.091726755 | D36: =IFERROR('Historical Dataset'!H91/'Historical Dataset'!H$95,"") -> 0.010933765 | E36: =IFERROR('Historical Dataset'!I91/'Historical Dataset'!I$95,"") -> 0.022787381 | F36: =IFERROR('Historical Dataset'!J91/'Historical Dataset'!J$95,"") -> 0.074278529 | G36: =IFERROR('Historical Dataset'!K91/'Historical Dataset'!K$95,"") -> 0.077314433 | H36: =IFERROR('Historical Dataset'!L91/'Historical Dataset'!L$95,"") -> 0.11131724 | I36: =IFERROR('Historical Dataset'!M91/'Historical Dataset'!M$95,"") -> 0 | J36: =IFERROR('Historical Dataset'!N91/'Historical Dataset'!N$95,"") -> 0 | K36: ='Historical Dataset'!N91 -> 0 | L36: =IFERROR(ABS(K36)/'Historical Dataset'!N$71,"") -> 0
A37: Unrealised foreign exchange costs | B37: KSh mn | C37: =IFERROR('Historical Dataset'!G92/'Historical Dataset'!G$95,"") -> 0 | D37: =IFERROR('Historical Dataset'!H92/'Historical Dataset'!H$95,"") -> 0 | E37: =IFERROR('Historical Dataset'!I92/'Historical Dataset'!I$95,"") -> 0 | F37: =IFERROR('Historical Dataset'!J92/'Historical Dataset'!J$95,"") -> 0 | G37: =IFERROR('Historical Dataset'!K92/'Historical Dataset'!K$95,"") -> 0.0095742046 | H37: =IFERROR('Historical Dataset'!L92/'Historical Dataset'!L$95,"") -> 0.03704026 | I37: =IFERROR('Historical Dataset'!M92/'Historical Dataset'!M$95,"") -> 0.001855817 | J37: =IFERROR('Historical Dataset'!N92/'Historical Dataset'!N$95,"") -> 0.0028763973 | K37: ='Historical Dataset'!N92 -> -416.11 | L37: =IFERROR(ABS(K37)/'Historical Dataset'!N$71,"") -> 0.00189758
A38: Fuel / thermal energy cost | B38: KSh mn | C38: =IFERROR('Historical Dataset'!G93/'Historical Dataset'!G$95,"") -> 0.28051189 | D38: =IFERROR('Historical Dataset'!H93/'Historical Dataset'!H$95,"") -> 0.2028629 | E38: =IFERROR('Historical Dataset'!I93/'Historical Dataset'!I$95,"") -> 0.12640662 | F38: =IFERROR('Historical Dataset'!J93/'Historical Dataset'!J$95,"") -> 0.11870293 | G38: =IFERROR('Historical Dataset'!K93/'Historical Dataset'!K$95,"") -> 0.22577641 | H38: =IFERROR('Historical Dataset'!L93/'Historical Dataset'!L$95,"") -> 0.19567061 | I38: =IFERROR('Historical Dataset'!M93/'Historical Dataset'!M$95,"") -> 0.29053822 | J38: =IFERROR('Historical Dataset'!N93/'Historical Dataset'!N$95,"") -> 0.30552387 | K38: ='Historical Dataset'!N93 -> -44198.185 | L38: =IFERROR(ABS(K38)/'Historical Dataset'!N$71,"") -> 0.20155629
A39: Other power purchase costs | B39: KSh mn | C39: =IFERROR('Historical Dataset'!G94/'Historical Dataset'!G$95,"") -> 0 | D39: =IFERROR('Historical Dataset'!H94/'Historical Dataset'!H$95,"") -> 0 | E39: =IFERROR('Historical Dataset'!I94/'Historical Dataset'!I$95,"") -> 0 | F39: =IFERROR('Historical Dataset'!J94/'Historical Dataset'!J$95,"") -> 0 | G39: =IFERROR('Historical Dataset'!K94/'Historical Dataset'!K$95,"") -> 1.1197591e-05 | H39: =IFERROR('Historical Dataset'!L94/'Historical Dataset'!L$95,"") -> 0.0052279034 | I39: =IFERROR('Historical Dataset'!M94/'Historical Dataset'!M$95,"") -> 0.0013488581 | J39: =IFERROR('Historical Dataset'!N94/'Historical Dataset'!N$95,"") -> 0.00012519389 | K39: ='Historical Dataset'!N94 -> -18.111 | L39: =IFERROR(ABS(K39)/'Historical Dataset'!N$71,"") -> 8.2591311e-05
A40: Total cost of sales | B40: KSh mn | C40: =IFERROR('Historical Dataset'!G95/'Historical Dataset'!G$95,"") -> 1 | D40: =IFERROR('Historical Dataset'!H95/'Historical Dataset'!H$95,"") -> 1 | E40: =IFERROR('Historical Dataset'!I95/'Historical Dataset'!I$95,"") -> 1 | F40: =IFERROR('Historical Dataset'!J95/'Historical Dataset'!J$95,"") -> 1 | G40: =IFERROR('Historical Dataset'!K95/'Historical Dataset'!K$95,"") -> 1 | H40: =IFERROR('Historical Dataset'!L95/'Historical Dataset'!L$95,"") -> 1 | I40: =IFERROR('Historical Dataset'!M95/'Historical Dataset'!M$95,"") -> 1 | J40: =IFERROR('Historical Dataset'!N95/'Historical Dataset'!N$95,"") -> 1 | K40: ='Historical Dataset'!N95 -> -144663.61 | L40: =IFERROR(ABS(K40)/'Historical Dataset'!N$71,"") -> 0.65970718
A42: Operating expense structure — signed % contribution to total net operating expenses
A43: Operating expense | B43: Unit | C43: 2018 | D43: 2019 | E43: 2020 | F43: 2021 | G43: 2022 | H43: 2023 | I43: 2024 | J43: 2025 | K43: FY2025 value | L43: FY2025 impact / revenue
A44: Network management | B44: KSh mn | C44: =IFERROR('Historical Dataset'!G106/'Historical Dataset'!G$110,"") -> 0.25398841 | D44: =IFERROR('Historical Dataset'!H106/'Historical Dataset'!H$110,"") -> 0.26327081 | E44: =IFERROR('Historical Dataset'!I106/'Historical Dataset'!I$110,"") -> 0.23244242 | F44: =IFERROR('Historical Dataset'!J106/'Historical Dataset'!J$110,"") -> 0.25682854 | G44: =IFERROR('Historical Dataset'!K106/'Historical Dataset'!K$110,"") -> 0.56038907 | H44: =IFERROR('Historical Dataset'!L106/'Historical Dataset'!L$110,"") -> 0.55427543 | I44: =IFERROR('Historical Dataset'!M106/'Historical Dataset'!M$110,"") -> 0.49641191 | J44: =IFERROR('Historical Dataset'!N106/'Historical Dataset'!N$110,"") -> 0.57395795 | K44: ='Historical Dataset'!N106 -> -24348.121 | L44: =IFERROR(K44/'Historical Dataset'!N$71,"") -> -0.11103436
A45: Commercial services | B45: KSh mn | C45: =IFERROR('Historical Dataset'!G107/'Historical Dataset'!G$110,"") -> 0.34615654 | D45: =IFERROR('Historical Dataset'!H107/'Historical Dataset'!H$110,"") -> 0.18697601 | E45: =IFERROR('Historical Dataset'!I107/'Historical Dataset'!I$110,"") -> 0.13921791 | F45: =IFERROR('Historical Dataset'!J107/'Historical Dataset'!J$110,"") -> 0.14463591 | G45: =IFERROR('Historical Dataset'!K107/'Historical Dataset'!K$110,"") -> 0.13232188 | H45: =IFERROR('Historical Dataset'!L107/'Historical Dataset'!L$110,"") -> 0.079846511 | I45: =IFERROR('Historical Dataset'!M107/'Historical Dataset'!M$110,"") -> 0.12870528 | J45: =IFERROR('Historical Dataset'!N107/'Historical Dataset'!N$110,"") -> 0.14421991 | K45: ='Historical Dataset'!N107 -> -6118.016 | L45: =IFERROR(K45/'Historical Dataset'!N$71,"") -> -0.027899893
A46: Administration | B46: KSh mn | C46: =IFERROR('Historical Dataset'!G108/'Historical Dataset'!G$110,"") -> 0.39985505 | D46: =IFERROR('Historical Dataset'!H108/'Historical Dataset'!H$110,"") -> 0.51480571 | E46: =IFERROR('Historical Dataset'!I108/'Historical Dataset'!I$110,"") -> 0.56002729 | F46: =IFERROR('Historical Dataset'!J108/'Historical Dataset'!J$110,"") -> 0.58964987 | G46: =IFERROR('Historical Dataset'!K108/'Historical Dataset'!K$110,"") -> 0.33029846 | H46: =IFERROR('Historical Dataset'!L108/'Historical Dataset'!L$110,"") -> 0.30227902 | I46: =IFERROR('Historical Dataset'!M108/'Historical Dataset'!M$110,"") -> 0.34941735 | J46: =IFERROR('Historical Dataset'!N108/'Historical Dataset'!N$110,"") -> 0.38632458 | K46: ='Historical Dataset'!N108 -> -16388.444 | L46: =IFERROR(K46/'Historical Dataset'!N$71,"") -> -0.074735966
A47: Expected credit losses on financial assets | B47: KSh mn | C47: =IFERROR('Historical Dataset'!G109/'Historical Dataset'!G$110,"") -> 0 | D47: =IFERROR('Historical Dataset'!H109/'Historical Dataset'!H$110,"") -> 0.034947472 | E47: =IFERROR('Historical Dataset'!I109/'Historical Dataset'!I$110,"") -> 0.068312389 | F47: =IFERROR('Historical Dataset'!J109/'Historical Dataset'!J$110,"") -> 0.0088856799 | G47: =IFERROR('Historical Dataset'!K109/'Historical Dataset'!K$110,"") -> -0.023009412 | H47: =IFERROR('Historical Dataset'!L109/'Historical Dataset'!L$110,"") -> 0.063599046 | I47: =IFERROR('Historical Dataset'!M109/'Historical Dataset'!M$110,"") -> 0.02546546 | J47: =IFERROR('Historical Dataset'!N109/'Historical Dataset'!N$110,"") -> -0.10450245 | K47: ='Historical Dataset'!N109 -> 4433.144 | L47: =IFERROR(K47/'Historical Dataset'!N$71,"") -> 0.020216398
A48: Total net operating expenses | B48: KSh mn | C48: =IFERROR('Historical Dataset'!G110/'Historical Dataset'!G$110,"") -> 1 | D48: =IFERROR('Historical Dataset'!H110/'Historical Dataset'!H$110,"") -> 1 | E48: =IFERROR('Historical Dataset'!I110/'Historical Dataset'!I$110,"") -> 1 | F48: =IFERROR('Historical Dataset'!J110/'Historical Dataset'!J$110,"") -> 1 | G48: =IFERROR('Historical Dataset'!K110/'Historical Dataset'!K$110,"") -> 1 | H48: =IFERROR('Historical Dataset'!L110/'Historical Dataset'!L$110,"") -> 1 | I48: =IFERROR('Historical Dataset'!M110/'Historical Dataset'!M$110,"") -> 1 | J48: =IFERROR('Historical Dataset'!N110/'Historical Dataset'!N$110,"") -> 1 | K48: ='Historical Dataset'!N110 -> -42421.437 | L48: =IFERROR(K48/'Historical Dataset'!N$71,"") -> -0.19345382
A50: Other income contribution — % of total other income
A51: Other income item | B51: Unit | C51: 2018 | D51: 2019 | E51: 2020 | F51: 2021 | G51: 2022 | H51: 2023 | I51: 2024 | J51: 2025 | K51: FY2025 value | L51: CAGR 2018–2025
A52: GOK support for 15% tariff reduction | B52: KSh mn | C52: =IFERROR('Historical Dataset'!G80/'Historical Dataset'!G$88,"") -> 0 | D52: =IFERROR('Historical Dataset'!H80/'Historical Dataset'!H$88,"") -> 0 | E52: =IFERROR('Historical Dataset'!I80/'Historical Dataset'!I$88,"") -> 0 | F52: =IFERROR('Historical Dataset'!J80/'Historical Dataset'!J$88,"") -> 0 | G52: =IFERROR('Historical Dataset'!K80/'Historical Dataset'!K$88,"") -> 0.53024096 | H52: =IFERROR('Historical Dataset'!L80/'Historical Dataset'!L$88,"") -> 0.2592766 | I52: =IFERROR('Historical Dataset'!M80/'Historical Dataset'!M$88,"") -> 0 | J52: =IFERROR('Historical Dataset'!N80/'Historical Dataset'!N$88,"") -> 0 | K52: ='Historical Dataset'!N80 -> 0 | L52: =IFERROR(IF(AND('Historical Dataset'!G80>0,'Historical Dataset'!N80>0),('Historical Dataset'!N80/'Historical Dataset'!G80)^(1/7)-1,""),"")
A53: Amortisation of capital contribution | B53: KSh mn | C53: =IFERROR('Historical Dataset'!G81/'Historical Dataset'!G$88,"") -> 0.74495006 | D53: =IFERROR('Historical Dataset'!H81/'Historical Dataset'!H$88,"") -> 0.74990516 | E53: =IFERROR('Historical Dataset'!I81/'Historical Dataset'!I$88,"") -> 0.74691448 | F53: =IFERROR('Historical Dataset'!J81/'Historical Dataset'!J$88,"") -> 0.67683888 | G53: =IFERROR('Historical Dataset'!K81/'Historical Dataset'!K$88,"") -> 0.28638382 | H53: =IFERROR('Historical Dataset'!L81/'Historical Dataset'!L$88,"") -> 0.39320406 | I53: =IFERROR('Historical Dataset'!M81/'Historical Dataset'!M$88,"") -> 0.5070106 | J53: =IFERROR('Historical Dataset'!N81/'Historical Dataset'!N$88,"") -> 0.38589998 | K53: ='Historical Dataset'!N81 -> 2804.165 | L53: =IFERROR(IF(AND('Historical Dataset'!G81>0,'Historical Dataset'!N81>0),('Historical Dataset'!N81/'Historical Dataset'!G81)^(1/7)-1,""),"") -> -0.11955044
A54: Fibre optic leases | B54: KSh mn | C54: =IFERROR('Historical Dataset'!G82/'Historical Dataset'!G$88,"") -> 0.049098621 | D54: =IFERROR('Historical Dataset'!H82/'Historical Dataset'!H$88,"") -> 0.057404728 | E54: =IFERROR('Historical Dataset'!I82/'Historical Dataset'!I$88,"") -> 0.070985844 | F54: =IFERROR('Historical Dataset'!J82/'Historical Dataset'!J$88,"") -> 0.09125924 | G54: =IFERROR('Historical Dataset'!K82/'Historical Dataset'!K$88,"") -> 0.052705726 | H54: =IFERROR('Historical Dataset'!L82/'Historical Dataset'!L$88,"") -> 0.089311034 | I54: =IFERROR('Historical Dataset'!M82/'Historical Dataset'!M$88,"") -> 0.12959891 | J54: =IFERROR('Historical Dataset'!N82/'Historical Dataset'!N$88,"") -> 0.12879177 | K54: ='Historical Dataset'!N82 -> 935.873 | L54: =IFERROR(IF(AND('Historical Dataset'!G82>0,'Historical Dataset'!N82>0),('Historical Dataset'!N82/'Historical Dataset'!G82)^(1/7)-1,""),"") -> 0.11005176
A55: Miscellaneous revenue / sales | B55: KSh mn | C55: =IFERROR('Historical Dataset'!G83/'Historical Dataset'!G$88,"") -> 0.1111312 | D55: =IFERROR('Historical Dataset'!H83/'Historical Dataset'!H$88,"") -> 0.13466459 | E55: =IFERROR('Historical Dataset'!I83/'Historical Dataset'!I$88,"") -> 0.098509953 | F55: =IFERROR('Historical Dataset'!J83/'Historical Dataset'!J$88,"") -> 0.10570228 | G55: =IFERROR('Historical Dataset'!K83/'Historical Dataset'!K$88,"") -> 0.047981166 | H55: =IFERROR('Historical Dataset'!L83/'Historical Dataset'!L$88,"") -> 0.11885142 | I55: =IFERROR('Historical Dataset'!M83/'Historical Dataset'!M$88,"") -> 0.18246474 | J55: =IFERROR('Historical Dataset'!N83/'Historical Dataset'!N$88,"") -> 0.32196766 | K55: ='Historical Dataset'!N83 -> 2339.597 | L55: =IFERROR(IF(AND('Historical Dataset'!G83>0,'Historical Dataset'!N83>0),('Historical Dataset'!N83/'Historical Dataset'!G83)^(1/7)-1,""),"") -> 0.12592271
A56: Transmission line maintenance revenue | B56: KSh mn | C56: =IFERROR('Historical Dataset'!G84/'Historical Dataset'!G$88,"") -> 0.022491658 | D56: =IFERROR('Historical Dataset'!H84/'Historical Dataset'!H$88,"") -> 0.0085337507 | E56: =IFERROR('Historical Dataset'!I84/'Historical Dataset'!I$88,"") -> 0.0078589648 | F56: =IFERROR('Historical Dataset'!J84/'Historical Dataset'!J$88,"") -> 0.0021321039 | G56: =IFERROR('Historical Dataset'!K84/'Historical Dataset'!K$88,"") -> 0.0014165331 | H56: =IFERROR('Historical Dataset'!L84/'Historical Dataset'!L$88,"") -> 0 | I56: =IFERROR('Historical Dataset'!M84/'Historical Dataset'!M$88,"") -> 0 | J56: =IFERROR('Historical Dataset'!N84/'Historical Dataset'!N$88,"") -> 0 | K56: ='Historical Dataset'!N84 -> 0 | L56: =IFERROR(IF(AND('Historical Dataset'!G84>0,'Historical Dataset'!N84>0),('Historical Dataset'!N84/'Historical Dataset'!G84)^(1/7)-1,""),"")
A57: Capital contribution - Last Mile / recoveries | B57: KSh mn | C57: =IFERROR('Historical Dataset'!G85/'Historical Dataset'!G$88,"") -> 0.042631916 | D57: =IFERROR('Historical Dataset'!H85/'Historical Dataset'!H$88,"") -> 0.014986389 | E57: =IFERROR('Historical Dataset'!I85/'Historical Dataset'!I$88,"") -> 0.028682555 | F57: =IFERROR('Historical Dataset'!J85/'Historical Dataset'!J$88,"") -> 0.031715879 | G57: =IFERROR('Historical Dataset'!K85/'Historical Dataset'!K$88,"") -> 0.014582679 | H57: =IFERROR('Historical Dataset'!L85/'Historical Dataset'!L$88,"") -> 0.019814928 | I57: =IFERROR('Historical Dataset'!M85/'Historical Dataset'!M$88,"") -> 0.022429896 | J57: =IFERROR('Historical Dataset'!N85/'Historical Dataset'!N$88,"") -> 0.018674589 | K57: ='Historical Dataset'!N85 -> 135.7 | L57: =IFERROR(IF(AND('Historical Dataset'!G85>0,'Historical Dataset'!N85>0),('Historical Dataset'!N85/'Historical Dataset'!G85)^(1/7)-1,""),"") -> -0.1403929
A58: Reconnection charges | B58: KSh mn | C58: =IFERROR('Historical Dataset'!G86/'Historical Dataset'!G$88,"") -> 0.015682829 | D58: =IFERROR('Historical Dataset'!H86/'Historical Dataset'!H$88,"") -> 0.022656736 | E58: =IFERROR('Historical Dataset'!I86/'Historical Dataset'!I$88,"") -> 0.034164933 | F58: =IFERROR('Historical Dataset'!J86/'Historical Dataset'!J$88,"") -> 0.078414247 | G58: =IFERROR('Historical Dataset'!K86/'Historical Dataset'!K$88,"") -> 0.058639611 | H58: =IFERROR('Historical Dataset'!L86/'Historical Dataset'!L$88,"") -> 0.10573363 | I58: =IFERROR('Historical Dataset'!M86/'Historical Dataset'!M$88,"") -> 0.13854033 | J58: =IFERROR('Historical Dataset'!N86/'Historical Dataset'!N$88,"") -> 0.12806708 | K58: ='Historical Dataset'!N86 -> 930.607 | L58: =IFERROR(IF(AND('Historical Dataset'!G86>0,'Historical Dataset'!N86>0),('Historical Dataset'!N86/'Historical Dataset'!G86)^(1/7)-1,""),"") -> 0.30556818
A59: Rent | B59: KSh mn | C59: =IFERROR('Historical Dataset'!G87/'Historical Dataset'!G$88,"") -> 0.014013717 | D59: =IFERROR('Historical Dataset'!H87/'Historical Dataset'!H$88,"") -> 0.011848646 | E59: =IFERROR('Historical Dataset'!I87/'Historical Dataset'!I$88,"") -> 0.012883271 | F59: =IFERROR('Historical Dataset'!J87/'Historical Dataset'!J$88,"") -> 0.013937371 | G59: =IFERROR('Historical Dataset'!K87/'Historical Dataset'!K$88,"") -> 0.008049509 | H59: =IFERROR('Historical Dataset'!L87/'Historical Dataset'!L$88,"") -> 0.013808322 | I59: =IFERROR('Historical Dataset'!M87/'Historical Dataset'!M$88,"") -> 0.019955525 | J59: =IFERROR('Historical Dataset'!N87/'Historical Dataset'!N$88,"") -> 0.016598916 | K59: ='Historical Dataset'!N87 -> 120.617 | L59: =IFERROR(IF(AND('Historical Dataset'!G87>0,'Historical Dataset'!N87>0),('Historical Dataset'!N87/'Historical Dataset'!G87)^(1/7)-1,""),"") -> -0.0091321548
A60: Total other income | B60: KSh mn | C60: =IFERROR('Historical Dataset'!G88/'Historical Dataset'!G$88,"") -> 1 | D60: =IFERROR('Historical Dataset'!H88/'Historical Dataset'!H$88,"") -> 1 | E60: =IFERROR('Historical Dataset'!I88/'Historical Dataset'!I$88,"") -> 1 | F60: =IFERROR('Historical Dataset'!J88/'Historical Dataset'!J$88,"") -> 1 | G60: =IFERROR('Historical Dataset'!K88/'Historical Dataset'!K$88,"") -> 1 | H60: =IFERROR('Historical Dataset'!L88/'Historical Dataset'!L$88,"") -> 1 | I60: =IFERROR('Historical Dataset'!M88/'Historical Dataset'!M$88,"") -> 1 | J60: =IFERROR('Historical Dataset'!N88/'Historical Dataset'!N$88,"") -> 1 | K60: ='Historical Dataset'!N88 -> 7266.559 | L60: =IFERROR(IF(AND('Historical Dataset'!G88>0,'Historical Dataset'!N88>0),('Historical Dataset'!N88/'Historical Dataset'!G88)^(1/7)-1,""),"") -> -0.03280962
A62: FY2025 operating bridge — line item as % of revenue
A63: Line item | B63: KSh mn | C63: % of revenue | D63: Formula basis
A64: Revenue from contracts with customers | B64: ='Historical Dataset'!N114 -> 219284.57 | C64: =IFERROR(B64/'Historical Dataset'!N$114,"") -> 1 | D64: Revenue baseline
A65: Cost of sales | B65: ='Historical Dataset'!N115 -> -144663.61 | C65: =IFERROR(B65/'Historical Dataset'!N$114,"") -> -0.65970718 | D65: Signed impact on revenue
A66: Gross profit | B66: ='Historical Dataset'!N116 -> 74620.963 | C66: =IFERROR(B66/'Historical Dataset'!N$114,"") -> 0.34029282 | D66: Revenue less cost of sales
A67: Total net operating expenses | B67: ='Historical Dataset'!N117 -> -42421.437 | C67: =IFERROR(B67/'Historical Dataset'!N$114,"") -> -0.19345382 | D67: Signed impact on revenue
A68: Operating income before other income | B68: ='Historical Dataset'!N118 -> 32199.526 | C68: =IFERROR(B68/'Historical Dataset'!N$114,"") -> 0.146839 | D68: Gross profit less opex
A69: Other income | B69: ='Historical Dataset'!N119 -> 7266.559 | C69: =IFERROR(B69/'Historical Dataset'!N$114,"") -> 0.033137576 | D69: Incremental other income
A70: Operating profit | B70: ='Historical Dataset'!N120 -> 39466.085 | C70: =IFERROR(B70/'Historical Dataset'!N$114,"") -> 0.17997657 | D70: Revenue to operating profit
A71: Finance income | B71: ='Historical Dataset'!N121 -> 625.218 | C71: =IFERROR(B71/'Historical Dataset'!N$114,"") -> 0.0028511719 | D71: Below operating profit
A72: Finance costs | B72: ='Historical Dataset'!N122 -> -4716.619 | C72: =IFERROR(B72/'Historical Dataset'!N$114,"") -> -0.021509124 | D72: Below operating profit
A73: Profit before income tax | B73: ='Historical Dataset'!N123 -> 35374.684 | C73: =IFERROR(B73/'Historical Dataset'!N$114,"") -> 0.16131862 | D73: Pre-tax profit
A74: Income tax expense / credit | B74: ='Historical Dataset'!N124 -> -10908.159 | C74: =IFERROR(B74/'Historical Dataset'!N$114,"") -> -0.049744308 | D74: Tax impact
A75: Profit for the year | B75: ='Historical Dataset'!N125 -> 24466.525 | C75: =IFERROR(B75/'Historical Dataset'!N$114,"") -> 0.11157431 | D75: Net profit
A77: Interpretation notes: revenue mix tables use revenue from contracts as the denominator; tariff category mix uses the sum of tariff-category revenue lines; cost-of-sales and operating expense mix use their respective signed totals so components reconcile to 100%. Positive ECL in FY2025 is shown as a negative contribution to net operating expenses because it offsets expenses.
A82: Regional Segment Analysis (Revenue, FY2018–FY2025)
A83: Region | C83: FY2018 (KSh mn) | D83: FY2025 (KSh mn) | E83: CAGR FY18-25 | F83: FY2025 % of total revenue | G83: FY2025 operating margin
A84: Nairobi Region | C84: 63911 | D84: 101764 | E84: 0.069 | F84: 0.464 | G84: 0.273
A85: West Kenya Region | C85: 23860 | D85: 42238 | E85: 0.085 | F85: 0.193 | G85: -0.071
A86: Coast Region | C86: 23048 | D86: 37974 | E86: 0.074 | F86: 0.173 | G86: 0.27
A87: Mount Kenya Region | C87: 20560 | D87: 37308 | E87: 0.089 | F87: 0.17 | G87: 0.118
A88: Total | C88: 131379 | D88: 219285 | E88: 0.076 | F88: 1 | G88: 0.18

Sheet Historical Dataset
B1: Fahamisha Investing Model by Brian Githinji
D3: Company name | E3: Kenya Power Lightning & Co | F3: Ticker | G3: KPLC
D4: Share price | E4: 18.35 | F4: Share price date | G4: 46210
D5: Financial Year - Last year ended | E5: 45838 | F5: Model date | G5: 46212
D6: Shares Outstanding (Millions) | E6: 35809.4
F9: 43100 | G9: =EOMONTH(F9,12) -> 43465 | H9: =EOMONTH(G9,12) -> 43830 | I9: =EOMONTH(H9,12) -> 44196 | J9: =EOMONTH(I9,12) -> 44561 | K9: =EOMONTH(J9,12) -> 44926 | L9: =EOMONTH(K9,12) -> 45291 | M9: =EOMONTH(L9,12) -> 45657 | N9: =EOMONTH(M9,12) -> 46022
B10: Section | C10: Sub-section | D10: Line item | E10: Unit | F10: 2017 | G10: 2018 | H10: 2019 | I10: 2020 | J10: 2021 | K10: 2022 | L10: 2023 | M10: 2024 | N10: 2025
C11: Ownership | D11: Government of Kenya ordinary shareholding | E11: % | F11: 0.501 | G11: 0.501 | H11: 0.501 | I11: 0.501 | J11: 0.501 | K11: 0.501 | L11: 0.501 | M11: 0.501 | N11: 0.501
B12: Key operating KPIs | C12: Units, losses, efficiency, demand
B13: D. Key operating KPIs | C13: Energy demand | D13: Energy purchased - system total | E13: GWh | F13: 10204 | G13: 10702 | H13: 11493 | I13: 11462 | J13: 12101 | K13: 12653 | L13: 13290 | M13: 13684 | N13: 14472
D14: Growth Rate | G14: =G13/F13-1 -> 0.04880439 | H14: =H13/G13-1 -> 0.073911418 | I14: =I13/H13-1 -> -0.002697294 | J14: =J13/I13-1 -> 0.055749433 | K14: =K13/J13-1 -> 0.045616065 | L14: =L13/K13-1 -> 0.050343792 | M14: =M13/L13-1 -> 0.029646351 | N14: =N13/M13-1 -> 0.057585501
B15: D. Key operating KPIs | C15: Energy demand | D15: Total sales | E15: GWh | F15: 8272 | G15: 8459 | H15: 8769 | I15: 8773 | J15: 9203 | K15: 9813 | L15: 10233 | M15: 10516 | N15: 11403
D16: Growth Rate | G16: =G15/F15-1 -> 0.022606383 | H16: =H15/G15-1 -> 0.036647358 | I16: =I15/H15-1 -> 0.00045615235 | J16: =J15/I15-1 -> 0.04901402 | K16: =K15/J15-1 -> 0.066282734 | L16: =L15/K15-1 -> 0.042800367 | M16: =M15/L15-1 -> 0.027655624 | N16: =N15/M15-1 -> 0.084347661
B18: D. Key operating KPIs | C18: Efficiency | D18: System losses | E18: GWh | F18: 1932 | G18: 2244 | H18: 2724 | I18: 2689 | J18: 2898 | K18: 2839 | L18: 3057 | M18: 3169 | N18: 3069
D19: Growth Rate | G19: =G18/F18-1 -> 0.16149068 | H19: =H18/G18-1 -> 0.21390374 | I19: =I18/H18-1 -> -0.012848752 | J19: =J18/I18-1 -> 0.077724061 | K19: =K18/J18-1 -> -0.020358868 | L19: =L18/K18-1 -> 0.076787601 | M19: =M18/L18-1 -> 0.036637226 | N19: =N18/M18-1 -> -0.031555696
B20: D. Key operating KPIs | C20: Efficiency | D20: Distribution efficiency / sales % of energy purchased | E20: % | F20: =F15/F13 -> 0.81066249 | G20: =G15/G13 -> 0.79041301 | H20: =H15/H13 -> 0.76298617 | I20: =I15/I13 -> 0.76539871 | J20: =J15/J13 -> 0.76051566 | K20: =K15/K13 -> 0.7755473 | L20: =L15/L13 -> 0.76997743 | M20: =M15/M13 -> 0.76848875 | N20: =N15/N13 -> 0.78793532
B21: D. Key operating KPIs | C21: Efficiency | D21: System losses as % of energy purchased | E21: % | F21: =1-F20 -> 0.18933751 | G21: =1-G20 -> 0.20958699 | H21: =1-H20 -> 0.23701383 | I21: =1-I20 -> 0.23460129 | J21: =1-J20 -> 0.23948434 | K21: =1-K20 -> 0.2244527 | L21: =1-L20 -> 0.23002257 | M21: =1-M20 -> 0.23151125 | N21: =1-N20 -> 0.21206468
B22: D. Key operating KPIs | C22: Demand | D22: System peak demand | E22: MW | F22: 1656 | G22: 1802 | H22: 1882 | I22: 1926 | J22: 1994 | K22: 2057 | L22: 2149 | M22: 2177 | N22: 2316
D23: Growth Rate | G23: =G22/F22-1 -> 0.088164251 | H23: =H22/G22-1 -> 0.044395117 | I23: =I22/H22-1 -> 0.023379384 | J23: =J22/I22-1 -> 0.035306334 | K23: =K22/J22-1 -> 0.031594784 | L23: =L22/K22-1 -> 0.044725328 | M23: =M22/L22-1 -> 0.013029316 | N23: =N22/M22-1 -> 0.063849334
B24: D. Key operating KPIs | C24: Demand | D24: System load factor | E24: % | F24: 0.703 | G24: 0.678 | H24: 0.697 | I24: 0.679 | J24: 0.693 | K24: 0.702 | L24: 0.706 | M24: 0.718 | N24: 0.713
B25: D. Key operating KPIs | C25: Tariff/revenue | D25: Average yield of units sold | E25: cents/kWh | F25: 1564.63 | G25: 1661.97 | H25: 1629.03 | I25: 1630.87 | J25: 1681.48 | K25: 1717.27 | L25: 1996.18 | M25: 2345.24 | N25: 2041.38
D26: Growth Rate | G26: =G25/F25-1 -> 0.062212792 | H26: =H25/G25-1 -> -0.019819852 | I26: =I25/H25-1 -> 0.0011295065 | J26: =J25/I25-1 -> 0.031032516 | K26: =K25/J25-1 -> 0.021284821 | L26: =L25/K25-1 -> 0.16241476 | M26: =M25/L25-1 -> 0.17486399 | N26: =N25/M25-1 -> -0.12956456
B27: D. Key operating KPIs | C27: Cost/revenue | D27: Average cost of units sold | E27: cents/kWh | F27: 1493.09 | G27: 1627.34 | H27: 1607.31 | I27: 1656.27 | J27: 1564.35 | K27: 1675.24 | L27: 1890.43 | M27: 1835.184 | N27: 1683.647
D28: Growth Rate | G28: =G27/F27-1 -> 0.089914205 | H28: =H27/G27-1 -> -0.01230843 | I28: =I27/H27-1 -> 0.030460832 | J28: =J27/I27-1 -> -0.055498198 | K28: =K27/J27-1 -> 0.070885671 | L28: =L27/K27-1 -> 0.12845324 | M28: =M27/L27-1 -> -0.029224039 | N28: =N27/M27-1 -> -0.082573192
B29: E. Unit sales and customer metrics | C29: Customer mix and sales mix
B30: E. Unit sales and customer metrics | C30: Unit sales | D30: KPLC system sales | E30: GWh | F30: 7701 | G30: 7881 | H30: 8147 | I30: 8154 | J30: 8553 | K30: 9147 | L30: 9539 | M30: 9813 | N30: 10570
D31: Growth Rate | G31: =G30/F30-1 -> 0.023373588 | H31: =H30/G30-1 -> 0.033752062 | I31: =I30/H30-1 -> 0.00085921198 | J31: =J30/I30-1 -> 0.048933039 | K31: =K30/J30-1 -> 0.069449316 | L31: =L30/K30-1 -> 0.042855581 | M31: =M30/L30-1 -> 0.028724185 | N31: =N30/M30-1 -> 0.077142566
D32: % of total sales | F32: =F30/F15 -> 0.93097195 | G32: =G30/G15 -> 0.93167041 | H32: =H30/H15 -> 0.92906831 | I32: =I30/I15 -> 0.92944261 | J32: =J30/J15 -> 0.92937086 | K32: =K30/K15 -> 0.93213085 | L32: =L30/L15 -> 0.9321802 | M32: =M30/M15 -> 0.93314949 | N32: =N30/N15 -> 0.92694905
B33: E. Unit sales and customer metrics | C33: Unit sales | D33: REP system sales | E33: GWh | F33: 549 | G33: 554 | H33: 595 | I33: 603 | J33: 632 | K33: 650 | L33: 667 | M33: 660 | N33: 760
D34: Growth Rate | G34: =G33/F33-1 -> 0.0091074681 | H34: =H33/G33-1 -> 0.07400722 | I34: =I33/H33-1 -> 0.013445378 | J34: =J33/I33-1 -> 0.048092869 | K34: =K33/J33-1 -> 0.028481013 | L34: =L33/K33-1 -> 0.026153846 | M34: =M33/L33-1 -> -0.010494753 | N34: =N33/M33-1 -> 0.15151515
D35: % of total sales | F35: =F33/$F$15 -> 0.066368472 | G35: =G33/$G$15 -> 0.065492375 | H35: =H33/$H$15 -> 0.067852663 | I35: =I33/$I$15 -> 0.068733614 | J35: =J33/$J$15 -> 0.068673259 | K35: =K33/$K$15 -> 0.066238663 | L35: =L33/$L$15 -> 0.065181276 | M35: =M33/$M$15 -> 0.062761506 | N35: =N33/$N$15 -> 0.066649127
B36: E. Unit sales and customer metrics | C36: Unit sales | D36: Export sales | E36: GWh | F36: 22 | G36: 23 | H36: 27 | I36: 18 | J36: 17 | K36: 16 | L36: 27 | M36: 43 | N36: 73
D37: Growth Rate | G37: =G36/F36-1 -> 0.045454545 | H37: =H36/G36-1 -> 0.17391304 | I37: =I36/H36-1 -> -0.33333333 | J37: =J36/I36-1 -> -0.055555556 | K37: =K36/J36-1 -> -0.058823529 | L37: =L36/K36-1 -> 0.6875 | M37: =M36/L36-1 -> 0.59259259 | N37: =N36/M36-1 -> 0.69767442
D38: % of total sales | F38: =F36/$F$15 -> 0.0026595745 | G38: =G36/$G$15 -> 0.0027189975 | H38: =H36/$H$15 -> 0.0030790284 | I38: =I36/$I$15 -> 0.0020517497 | J38: =J36/$J$15 -> 0.0018472237 | K38: =K36/$K$15 -> 0.0016304902 | L38: =L36/$L$15 -> 0.0026385224 | M38: =M36/$M$15 -> 0.0040890072 | N38: =N36/$N$15 -> 0.0064018241
B39: E. Unit sales and customer metrics | C39: Customer category | D39: Domestic sales | E39: GWh | F39: 2138 | G39: 2335 | H39: 2366 | I39: 2508 | J39: 2630 | K39: 2728 | L39: 2798 | M39: 2769 | N39: 3104
D40: Growth Rate | G40: =G39/F39-1 -> 0.092142189 | H40: =H39/G39-1 -> 0.013276231 | I40: =I39/H39-1 -> 0.060016906 | J40: =J39/I39-1 -> 0.048644338 | K40: =K39/J39-1 -> 0.037262357 | L40: =L39/K39-1 -> 0.025659824 | M40: =M39/L39-1 -> -0.010364546 | N40: =N39/M39-1 -> 0.1209823
D41: % of total sales | F41: =F39/$F$15 -> 0.25846228 | G41: =G39/$G$15 -> 0.27603736 | H41: =H39/$H$15 -> 0.26981412 | I41: =I39/$I$15 -> 0.28587712 | J41: =J39/$J$15 -> 0.28577638 | K41: =K39/$K$15 -> 0.27799857 | L41: =L39/$L$15 -> 0.2734291 | M41: =M39/$M$15 -> 0.26331305 | N41: =N39/$N$15 -> 0.27220907
B42: E. Unit sales and customer metrics | C42: Customer category | D42: Small commercial sales | E42: GWh | F42: 1201 | G42: 1222 | H42: 1250 | I42: 1262 | J42: 1326 | K42: 1474 | L42: 1504 | M42: 1526 | N42: 1710
D43: Growth Rate | G43: =G42/F42-1 -> 0.017485429 | H43: =H42/G42-1 -> 0.022913257 | I43: =I42/H42-1 -> 0.0096 | J43: =J42/I42-1 -> 0.050713154 | K43: =K42/J42-1 -> 0.11161388 | L43: =L42/K42-1 -> 0.020352782 | M43: =M42/L42-1 -> 0.01462766 | N43: =N42/M42-1 -> 0.12057667
D44: % of total sales | F44: =F42/$F$15 -> 0.14518859 | G44: =G42/$G$15 -> 0.14446152 | H44: =H42/$H$15 -> 0.14254761 | I44: =I42/$I$15 -> 0.14385045 | J44: =J42/$J$15 -> 0.14408345 | K44: =K42/$K$15 -> 0.15020891 | L44: =L42/$L$15 -> 0.14697547 | M44: =M42/$M$15 -> 0.14511221 | N44: =N42/$N$15 -> 0.14996054
B45: E. Unit sales and customer metrics | C45: Customer category | D45: Commercial and industrial sales | E45: GWh | F45: 4266 | G45: 4225 | H45: 4462 | I45: 4308 | J45: 4514 | K45: 4851 | L45: 5137 | M45: 5415 | N45: 5603
D46: Growth Rate | G46: =G45/F45-1 -> -0.0096108767 | H46: =H45/G45-1 -> 0.056094675 | I46: =I45/H45-1 -> -0.034513671 | J46: =J45/I45-1 -> 0.047818013 | K46: =K45/J45-1 -> 0.074656624 | L46: =L45/K45-1 -> 0.058956916 | M46: =M45/L45-1 -> 0.054117189 | N46: =N45/M45-1 -> 0.034718375
D47: % of total sales | F47: =F45/$F$15 -> 0.51571567 | G47: =G45/$G$15 -> 0.49946802 | H47: =H45/$H$15 -> 0.50883795 | I47: =I45/$I$15 -> 0.49105209 | J47: =J45/$J$15 -> 0.49049223 | K47: =K45/$K$15 -> 0.49434424 | L47: =L45/$L$15 -> 0.50200332 | M47: =M45/$M$15 -> 0.51492963 | N47: =N45/$N$15 -> 0.49136192
B48: E. Unit sales and customer metrics | C48: Customer category | D48: Street lighting sales | E48: GWh | F48: 55 | G48: 66 | H48: 68 | I48: 76 | J48: 84 | K48: 95 | L48: 99 | M48: 102 | N48: 148
D49: Growth Rate | G49: =G48/F48-1 -> 0.2 | H49: =H48/G48-1 -> 0.03030303 | I49: =I48/H48-1 -> 0.11764706 | J49: =J48/I48-1 -> 0.10526316 | K49: =K48/J48-1 -> 0.13095238 | L49: =L48/K48-1 -> 0.042105263 | M49: =M48/L48-1 -> 0.03030303 | N49: =N48/M48-1 -> 0.45098039
D50: % of total sales | F50: =F48/$F$15 -> 0.0066489362 | G50: =G48/$G$15 -> 0.0078023407 | H50: =H48/$H$15 -> 0.00775459 | I50: =I48/$I$15 -> 0.0086629431 | J50: =J48/$J$15 -> 0.0091274584 | K50: =K48/$K$15 -> 0.0096810354 | L50: =L48/$L$15 -> 0.0096745822 | M50: =M48/$M$15 -> 0.0096995055 | N50: =N48/$N$15 -> 0.012979041
B51: E. Unit sales and customer metrics | C51: Customer category | D51: E-mobility sales | E51: GWh | M51: 1.24 | N51: 4.88
D52: Growth Rate | N52: =N51/M51-1 -> 2.9354839
D53: % of total sales | F53: =F51/$F$15 -> 0 | G53: =G51/$G$15 -> 0 | H53: =H51/$H$15 -> 0 | I53: =I51/$I$15 -> 0 | J53: =J51/$J$15 -> 0 | K53: =K51/$K$15 -> 0 | L53: =L51/$L$15 -> 0 | M53: =M51/$M$15 -> 0.00011791556 | N53: =N51/$N$15 -> 0.00042795756
B54: E. Unit sales and customer metrics | C54: Customer base | D54: KPLC customers | E54: Customers | F54: 4912772 | G54: 5428881 | H54: 5658605 | I54: 6073202 | J54: 6365757 | K54: 6818706 | L54: 6998044 | M54: 7310665 | N54: 7538127
D55: Growth Rate | G55: =G54/F54-1 -> 0.10505454 | H55: =H54/G54-1 -> 0.042315166 | I55: =I54/H54-1 -> 0.073268412 | J55: =J54/I54-1 -> 0.048171459 | K55: =K54/J54-1 -> 0.071153988 | L55: =L54/K54-1 -> 0.026300885 | M55: =M54/L54-1 -> 0.044672626 | N55: =N54/M54-1 -> 0.031113722
D56: % of total customers | F56: =F54/F60 -> 0.7946535 | G56: =G54/G60 -> 0.80295943 | H56: =H54/H60 -> 0.80061068 | I56: =I54/I60 -> 0.80162167 | J56: =J54/J60 -> 0.76897803 | K56: =K54/K60 -> 0.76447692 | L56: =L54/L60 -> 0.75960391 | M56: =M54/M60 -> 0.75679723 | N56: =N54/N60 -> 0.75036268
B57: E. Unit sales and customer metrics | C57: Customer base | D57: REP customers | E57: Customers | F57: 1269510 | G57: 1332209 | H57: 1409256 | I57: 1502943 | J57: 1912447 | K57: 2100734 | L57: 2214710 | M57: 2349340 | N57: 2507851
D58: Growth Rate | G58: =G57/F57-1 -> 0.049388347 | H58: =H57/G57-1 -> 0.057834019 | I58: =I57/H57-1 -> 0.06647976 | J58: =J57/I57-1 -> 0.27246808 | K58: =K57/J57-1 -> 0.098453447 | L58: =L57/K57-1 -> 0.054255322 | M58: =M57/L57-1 -> 0.060788997 | N58: =N57/M57-1 -> 0.067470439
D59: % of total customers | F59: =F57/F60 -> 0.2053465 | G59: =G57/G60 -> 0.19704057 | H59: =H57/H60 -> 0.19938932 | I59: =I57/I60 -> 0.19837833 | J59: =J57/J60 -> 0.23102197 | K59: =K57/K60 -> 0.23552308 | L59: =L57/L60 -> 0.24039609 | M59: =M57/M60 -> 0.24320277 | N59: =N57/N60 -> 0.24963732
B60: E. Unit sales and customer metrics | C60: Customer base | D60: Total customers | E60: Customers | F60: =SUM(F54,F57) -> 6182282 | G60: =SUM(G54,G57) -> 6761090 | H60: =SUM(H54,H57) -> 7067861 | I60: =SUM(I54,I57) -> 7576145 | J60: =SUM(J54,J57) -> 8278204 | K60: =SUM(K54,K57) -> 8919440 | L60: =SUM(L54,L57) -> 9212754 | M60: =SUM(M54,M57) -> 9660005 | N60: =SUM(N54,N57) -> 10045978
D61: Growth Rate | G61: =G60/F60-1 -> 0.093623681 | H61: =H60/G60-1 -> 0.045373009 | I61: =I60/H60-1 -> 0.071914827 | J61: =J60/I60-1 -> 0.092667049 | K61: =K60/J60-1 -> 0.077460763 | L61: =L60/K60-1 -> 0.0328848 | M61: =M60/L60-1 -> 0.048546938 | N61: =N60/M60-1 -> 0.039955776
B62: E. Unit sales and customer metrics | C62: Productivity | D62: Customers per employee | E62: x | F62: 615 | G62: 615 | H62: 643 | I62: 723 | J62: 814 | K62: 925 | L62: 920 | M62: 923 | N62: 951
B63: E. Unit sales and customer metrics | C63: Productivity | D63: Sales per employee | E63: kWh/employee | F63: 682800 | G63: 719094 | H63: 743473 | I63: 837198 | J63: 904294 | K63: 1017524 | L63: 1021561 | M63: 1004585 | N63: 1077585
B64: F. Revenue breakdown | C64: Tariff / pass-through revenue
B65: F. Revenue breakdown | C65: IFRS 15 revenue | D65: Post-paid electricity sales | E65: KSh mn | G65: 81791.735 | H65: 95753.392 | I65: 98354.629 | J65: 106632.29 | K65: 107206.26 | L65: 120186.03 | M65: 150969.12 | N65: 146508.7
B66: F. Revenue breakdown | C66: IFRS 15 revenue | D66: Prepaid electricity sales | E66: KSh mn | G66: 13643.134 | H66: 16675.792 | I66: 17817.855 | J66: 20578.339 | K66: 19666.579 | L66: 24172.173 | M66: 34297.848 | N66: 37565.704
B67: F. Revenue breakdown | C67: IFRS 15 revenue | D67: Base electricity sales subtotal | E67: KSh mn | G67: 95434.869 | H67: 112429.18 | I67: 116172.48 | J67: 127210.63 | K67: 126872.84 | L67: 144358.2 | M67: 185266.97 | N67: 184074.41
B68: F. Revenue breakdown | C68: Pass-through revenue | D68: Foreign exchange adjustment | E68: KSh mn | G68: 9322.195 | H68: 859.69 | I68: 923.648 | J68: 6333.065 | K68: 7322.584 | L68: 14021.413 | M68: 23938.217 | N68: 10412.662
B69: F. Revenue breakdown | C69: Pass-through revenue | D69: Fuel cost charge / fuel cost recovery | E69: KSh mn | G69: 26621.91 | H69: 19852.013 | I69: 16162.47 | J69: 11859.696 | K69: 24446.58 | L69: 34155.05 | M69: 24292.059 | N69: 27168.969
B70: F. Revenue breakdown | C70: RES | D70: Revenue apportioned to RES | E70: KSh mn | J70: -1283.783 | K70: -1288.754 | L70: -1559.708 | M70: -2373.648 | N70: -2371.472
B71: F. Revenue breakdown | C71: IFRS 15 revenue | D71: Revenue from contracts with customers | E71: KSh mn | F71: 120742.27 | G71: 131378.97 | H71: 133140.89 | I71: 133258.6 | J71: 144119.61 | K71: 157353.25 | L71: 190974.95 | M71: 231123.6 | N71: 219284.57
B72: F. Revenue breakdown | C72: Tariff category revenue | D72: Domestic revenue | E72: KSh mn | F72: 38064 | G72: 38066 | H72: 38706 | I72: 43916 | J72: 43210 | K72: 46105 | L72: 57057 | M72: 69155 | N72: 68189
B73: F. Revenue breakdown | C73: Tariff category revenue | D73: Small commercial revenue | E73: KSh mn | F73: 25590 | G73: 26995 | H73: 29314 | I73: 25553 | J73: 25953 | K73: 29799 | L73: 34811 | M73: 41998 | N73: 41715
B74: F. Revenue breakdown | C74: Tariff category revenue | D74: Commercial & industrial revenue | E74: KSh mn | F74: 55706 | G74: 59528 | H74: 63870 | I74: 62818 | J74: 73887 | K74: 80261 | L74: 97596 | M74: 117692 | N74: 106493
B75: F. Revenue breakdown | C75: Tariff category revenue | D75: Street lighting revenue | E75: KSh mn | F75: 414 | G75: 464 | H75: 658 | I75: 766 | J75: 821 | K75: 923 | L75: 948 | M75: 1318 | N75: 1640
B76: F. Revenue breakdown | C76: Tariff category revenue | D76: E-mobility revenue | E76: KSh mn | M76: 24 | N76: 85
B77: F. Revenue breakdown | C77: Tariff category revenue | D77: Export revenue | E77: KSh mn | F77: 343 | G77: 410 | H77: 546 | I77: 206 | J77: 249 | K77: 266 | L77: 562 | M77: 936 | N77: 1162
B78: F. Revenue breakdown | C78: Tariff category revenue | D78: REP revenue | E78: KSh mn | F78: 10376 | G78: 11846 | H78: 10772 | I78: 10071 | J78: 10369 | K78: 10551 | L78: 12473 | M78: 12429 | N78: 12013
B79: G. Other income breakdown | C79: Non-core and ancillary income
B80: G. Other income breakdown | C80: Other income | D80: GOK support for 15% tariff reduction | E80: KSh mn | J80: 0 | K80: 7050 | L80: 2358.333 | M80: 0 | N80: 0
B81: G. Other income breakdown | C81: Other income | D81: Amortisation of capital contribution | E81: KSh mn | G81: 6837.104 | H81: 6438.529 | I81: 5517.821 | J81: 4769.069 | K81: 3807.714 | L81: 3576.513 | M81: 3675.584 | N81: 2804.165
B82: G. Other income breakdown | C82: Other income | D82: Fibre optic leases | E82: KSh mn | G82: 450.624 | H82: 492.865 | I82: 524.407 | J82: 643.021 | K82: 700.767 | L82: 812.357 | M82: 939.53 | N82: 935.873
B83: G. Other income breakdown | C83: Other income | D83: Miscellaneous revenue / sales | E83: KSh mn | G83: 1019.955 | H83: 1156.202 | I83: 727.741 | J83: 744.788 | K83: 637.95 | L83: 1081.051 | M83: 1322.782 | N83: 2339.597
B84: G. Other income breakdown | C84: Other income | D84: Transmission line maintenance revenue | E84: KSh mn | G84: 206.427 | H84: 73.269 | I84: 58.058 | J84: 15.023 | K84: 18.834 | L84: 0 | M84: 0 | N84: 0
B85: G. Other income breakdown | C85: Other income | D85: Capital contribution - KPLC Last Mile / recovery from Last Mile customers | E85: KSh mn | G85: 391.273 | H85: 128.67 | I85: 211.892 | J85: 223.473 | K85: 193.889 | L85: 180.233 | M85: 162.606 | N85: 135.7
B86: G. Other income breakdown | C86: Other income | D86: Reconnection charges | E86: KSh mn | G86: 143.936 | H86: 194.526 | I86: 252.393 | J86: 552.514 | K86: 779.663 | L86: 961.734 | M86: 1004.351 | N86: 930.607
B87: G. Other income breakdown | C87: Other income | D87: Rent | E87: KSh mn | G87: 128.617 | H87: 101.73 | I87: 95.175 | J87: 98.204 | K87: 107.025 | L87: 125.598 | M87: 144.668 | N87: 120.617
B88: G. Other income breakdown | C88: Other income | D88: Total other income | E88: KSh mn | G88: 9177.936 | H88: 8585.791 | I88: 7387.487 | J88: 7046.092 | K88: 13295.842 | L88: 9095.819 | M88: 7249.521 | N88: 7266.559
B89: H. Cost of sales / power purchase cost breakdown | C89: Power purchase economics
B90: H. Cost of sales / power purchase cost breakdown | C90: Cost components | D90: Renewable/non-fuel energy cost | E90: KSh mn | G90: -52795.031 | H90: -70878.036 | I90: -74445.008 | J90: -76037.298 | K90: -80655.152 | L90: -93430.912 | M90: -106366.49 | N90: -100031.2
B91: H. Cost of sales / power purchase cost breakdown | C91: Cost components | D91: Foreign exchange costs on power purchases | E91: KSh mn | G91: -7714.264 | H91: -985.704 | I91: -1993.882 | J91: -6998.524 | K91: -9072.591 | L91: -15982.432
B92: H. Cost of sales / power purchase cost breakdown | C92: Cost components | D92: Unrealised foreign exchange costs | E92: KSh mn | K92: -1123.501 | L92: -5318.075 | M92: -279.497 | N92: -416.11
B93: H. Cost of sales / power purchase cost breakdown | C93: Cost components | D93: Fuel / thermal energy cost | E93: KSh mn | G93: -23591.184 | H93: -18288.556 | I93: -11060.502 | J93: -11184.192 | K93: -26494.109 | L93: -28093.512 | M93: -43756.771 | N93: -44198.185
B94: H. Cost of sales / power purchase cost breakdown | C94: Cost components | D94: Other power purchase costs | E94: KSh mn | K94: -1.314 | L94: -750.599 | M94: -203.146 | N94: -18.111
B95: H. Cost of sales / power purchase cost breakdown | C95: Cost components | D95: Total cost of sales | E95: KSh mn | G95: -84100.479 | H95: -90152.296 | I95: -87499.392 | J95: -94220.014 | K95: -117346.67 | L95: -143575.53 | M95: -150605.9 | N95: -144663.61
B96: H. Cost of sales / power purchase cost breakdown | C96: Pass-through analysis | D96: Fuel cost charge / recovery | E96: KSh mn | G96: 26621.91 | H96: 19852.013 | I96: 16162.47 | J96: 11859.696 | K96: 24446.58 | L96: 34155.05 | M96: 24292.059 | N96: 27168.969
B97: H. Cost of sales / power purchase cost breakdown | C97: Pass-through analysis | D97: Fuel cost incurred - explicit fuel-cost note/paragraph | E97: KSh mn | G97: -23591.184 | H97: -18288.556 | I97: -11060.502 | J97: -11184.192 | K97: -26494.109 | L97: -28093.512 | M97: -24910.417 | N97: -23479
B98: H. Cost of sales / power purchase cost breakdown | C98: Pass-through analysis | D98: Fuel recovery surplus / (shortfall) | E98: KSh mn | F98: =IF(OR(F96="",F97=""),"",F96+F97) | G98: =IF(OR(G96="",G97=""),"",G96+G97) -> 3030.726 | H98: =IF(OR(H96="",H97=""),"",H96+H97) -> 1563.457 | I98: =IF(OR(I96="",I97=""),"",I96+I97) -> 5101.968 | J98: =IF(OR(J96="",J97=""),"",J96+J97) -> 675.504 | K98: =IF(OR(K96="",K97=""),"",K96+K97) -> -2047.529 | L98: =IF(OR(L96="",L97=""),"",L96+L97) -> 6061.538 | M98: =IF(OR(M96="",M97=""),"",M96+M97) -> -618.358 | N98: =IF(OR(N96="",N97=""),"",N96+N97) -> 3689.969
B99: H. Cost of sales / power purchase cost breakdown | C99: Purchased energy by technology | D99: Geothermal purchases | E99: GWh | G99: 5053 | H99: 5033 | M99: 5707 | N99: 5718
B100: H. Cost of sales / power purchase cost breakdown | C100: Purchased energy by technology | D100: Hydro purchases | E100: GWh | F100: 3339 | G100: 3224 | H100: 3741 | M100: 3396 | N100: 3504
B101: H. Cost of sales / power purchase cost breakdown | C101: Purchased energy by technology | D101: Wind purchases | E101: GWh | G101: 0 | H101: 1192 | M101: 1780 | N101: 1908
B102: H. Cost of sales / power purchase cost breakdown | C102: Purchased energy by technology | D102: Thermal purchases | E102: GWh | F102: 832 | G102: 2206 | H102: 1240 | M102: 1129 | N102: 1335
B103: H. Cost of sales / power purchase cost breakdown | C103: Purchased energy by technology | D103: Solar purchases | E103: GWh | M103: 473 | N103: 473
B104: H. Cost of sales / power purchase cost breakdown | C104: Purchased energy by technology | D104: Imports | E104: GWh | F104: 184 | G104: 171 | H104: 170 | M104: 1199 | N104: 1534
...
